Workbook

Sheet Savings-Rates-India
A1: Year | B1: Total Savings | C1: Public non-financial corp. | D1: Private non- financial corp. | E1: Public financial corp. | F1: Private financial corp | G1: General Government | H1: Households including NPISH
A2: 2023-24 | B2: 30.74 | C2: 1.51 | D2: 9.54 | E2: 1.39 | F2: 1.11 | G2: -0.95 | H2: 18.13

Sheet Savings-Rates-Institutions
A1: Rate of Savings for Institutional Sectors at Current Prices: Base Year 2011-12
A2: Per cent : 1964-65 to 2023-24
A3: Year | B3: Total Savings | C3: Public non-financial corporations | D3: Private non- financial corporations | E3: Public financial corporations | F3: Private financial corporations | G3: General Government | H3: Households including NPISH
A4: 1964-65 | B4: 11.93
A5: 1965-66 | B5: 13.9
A6: 1966-67 | B6: 13.71
A7: 1967-68 | B7: 12
A8: 1968-69 | B8: 11.88
A9: 1969-70 | B9: 13.95
A10: 1970-71 | B10: 13.87 | D10: 1.26 | F10: 0.03 | G10: 1.47
A11: 1971-72 | B11: 14.67 | D11: 1.35 | F11: 0.04 | G11: 1.36
A12: 1972-73 | B12: 13.76 | D12: 1.29 | F12: 0.03 | G12: 1.32
A13: 1973-74 | B13: 16.34 | D13: 1.45 | F13: 0.02 | G13: 1.64
A14: 1974-75 | B14: 16.13 | D14: 1.67 | F14: 0.02 | G14: 2
A15: 1975-76 | B15: 16.63 | D15: 1.09 | F15: 0.03 | G15: 2.56
A16: 1976-77 | B16: 18.07 | D16: 1.07 | F16: 0.04 | G16: 2.52
A17: 1977-78 | B17: 18.55 | D17: 1.15 | F17: 0.03 | G17: 2.25
A18: 1978-79 | B18: 20.31 | D18: 1.22 | F18: 0.03 | G18: 2.43
A19: 1979-80 | B19: 19.24 | D19: 1.71 | F19: 0.03 | G19: 2.36
A20: 1980-81 | B20: 17.21 | D20: 1.4 | F20: 0.02 | G20: 2.04
A21: 1981-82 | B21: 16.78 | D21: 1.31 | F21: 0.03 | G21: 2.43
... A50: 2010-11 | B50: 36.91 | D50: 8.92 | F50: 1.28 | G50: -0.47
A51: 2011-12 | B51: 34.65 | C51: 1.42 | D51: 8.28 | E51: 1.93 | F51: 1.18 | G51: -1.81 | H51: 23.64
A52: 2012-13 | B52: 33.88 | C52: 1.25 | D52: 8.73 | E52: 1.76 | F52: 1.27 | G52: -1.6 | H52: 22.48
A53: 2013-14 | B53: 32.12 | C53: 1.12 | D53: 9.59 | E53: 1.45 | F53: 1.16 | G53: -1.55 | H53: 20.34
A54: 2014-15 | B54: 32.24 | C54: 1.04 | D54: 10.33 | E54: 1.36 | F54: 1.36 | G54: -1.41 | H54: 19.56
A55: 2015-16 | B55: 31.09 | C55: 1.12 | D55: 11.06 | E55: 1.28 | F55: 0.84 | G55: -1.17 | H55: 17.97
A56: 2016-17 | B56: 31.35 | C56: 1.12 | D56: 10.65 | E56: 1.4 | F56: 0.87 | G56: -0.79 | H56: 18.11
A57: 2017-18 | B57: 32.07 | C57: 1.39 | D57: 10.34 | E57: 1.39 | F57: 0.88 | G57: -1.22 | H57: 19.29
A58: 2018-19 | B58: 31.75 | C58: 1.33 | D58: 9.58 | E58: 0.94 | F58: 0.93 | G58: -1.37 | H58: 20.34
A59: 2019-20 | B59: 29.55 | C59: 1.45 | D59: 9.15 | E59: 1.56 | F59: 1.05 | G59: -2.79 | H59: 19.13
A60: 2020-21 | B60: 29.15 | C60: 1.18 | D60: 9.34 | E60: 1.41 | F60: 1.18 | G60: -6.66 | H60: 22.69
A61: 2021-22 | B61: 31.2 | C61: 1.32 | D61: 10.26 | E61: 1.52 | F61: 0.98 | G61: -2.98 | H61: 20.1
A62: 2022-23 | B62: 30.66 | C62: 1.23 | D62: 9.83 | E62: 1.73 | F62: 1.14 | G62: -1.91 | H62: 18.63
A63: 2023-24 | B63: 30.74 | C63: 1.51 | D63: 9.54 | E63: 1.39 | F63: 1.11 | G63: -0.95 | H63: 18.13

Sheet GCF-Financing
A1: Sources of Financing Gross Capital Formation at Current Prices: Base Year 2011-12
A2: Rs. Million : 1997-98 to 2020-21
A3: Year | B3: 2011-12 | C3: 2012-13 | D3: 2013-14 | E3: 2014-15 | F3: 2015-16 | G3: 2016-17 | H3: 2017-18 | I3: 2018-19 | J3: 2019-20 | K3: 2020-21
A4: Total Savings | B4: 34030080 | C4: 38471220 | D4: 37941350 | E4: 41797790 | F4: 44226590 | G4: 49180770 | H4: 57915730 | I4: 63960530 | J4: 61612130 | K4: 54031100
A5: Net capital inflow from rest of the world | B5: 3761710 | C5: 4779200 | D5: 1859420 | E5: 1598220 | F5: 1403990 | G5: 929640 | H5: 3108320 | I5: 3956620 | J5: 1652710 | K5: -1893360
A6: Gross saving | B6: 30268370 | C6: 33692020 | D6: 36081930 | E6: 40199570 | F6: 42822590 | G6: 48251130 | H6: 54807410 | I6: 60003900 | J6: 59959420 | K6: 55924460
A7: Non financial corporations save | B7: 8471340 | C7: 9921930 | D7: 12035360 | E7: 14170530 | F7: 16771840 | G7: 18110190 | H7: 20053740 | I7: 20612170 | J7: 21251810 | K7: 19900770
A8: Public non-financial corporations | B8: 1237690 | C8: 1239810 | D8: 1262500 | E8: 1291080 | F8: 1540150 | G8: 1721860 | H8: 2374830 | I8: 2507970 | J8: 2917520 | K8: 2760590
A9: Departmental enterprises | B9: 247230 | C9: 312820 | D9: 326880 | E9: 392530 | F9: 476200 | G9: 443000 | H9: 503520 | I9: 551280 | J9: 531610 | K9: 528980
A10: Non-departmental enterprises | B10: 990460 | C10: 926990 | D10: 935620 | E10: 898550 | F10: 1063950 | G10: 1278860 | H10: 1871310 | I10: 1956690 | J10: 2385900 | K10: 2231610
A11: Private non-financial corporations | B11: 7233650 | C11: 8682120 | D11: 10772860 | E11: 12879440 | F11: 15231690 | G11: 16388330 | H11: 17678910 | I11: 18104210 | J11: 18334290 | K11: 17140180
A12: Financial corporations save | B12: 2723710 | C12: 3006260 | D12: 2930840 | E12: 3390270 | F12: 2916410 | G12: 3484090 | H12: 3870280 | I12: 3537190 | J12: 5829460 | K12: 5572630
A13: Public financial corporations | B13: 1689310 | C13: 1748330 | D13: 1631840 | E13: 1699080 | F13: 1765130 | G13: 2152580 | H13: 2371270 | I13: 1779640 | J13: 3121720 | K13: 2850350
A14: Departmental enterprises | B14: 42840 | C14: 51720 | D14: 59610 | E14: 67220 | F14: 78780 | G14: 71590 | H14: 82180 | I14: 84510 | J14: 88750 | K14: 77140
A15: Non-departmental enterprises | B15: 1646470 | C15: 1696610 | D15: 1572230 | E15: 1631860 | F15: 1686360 | G15: 2081000 | H15: 2289090 | I15: 1695130 | J15: 3032970 | K15: 2773210
... A17: General Government Saving | B17: -1582340 | C17: -1588970 | D17: -1737290 | E17: -1752270 | F17: -1614780 | G17: -1214490 | H17: -2082570 | I17: -2591270 | J17: -6413320 | K17: -13454780
A18: Household sector | B18: 20655660 | C18: 22352800 | D18: 22853010 | E18: 24391040 | F18: 24749130 | G18: 27871340 | H18: 32965960 | I18: 38445820 | J18: 39291480 | K18: 43905840 | L18: =K19+K22+K23 -> 43905840
A19: Net financial saving (household) | B19: 6426090 | C19: 7336160 | D19: 8320910 | E19: 8804160 | F19: 11108450 | G19: 11460290 | H19: 13057050 | I19: 14924450 | J19: 16124680 | K19: 23037080 | L19: =K20-K21 -> 23037080
A20: Gross financial saving | B20: 9327290 | C20: 10640410 | D20: 11907700 | E20: 12572470 | F20: 14962320 | G20: 16146770 | H20: 20564050 | I20: 22636900 | J20: 23990870 | K20: 31089970
A21: Financial liabilities | B21: 2901200 | C21: 3304250 | D21: 3586790 | E21: 3768320 | F21: 3853880 | G21: 4686480 | H21: 7507000 | I21: 7712450 | J21: 7866190 | K21: 8052890
A22: Saving in physical assets | B22: 13893220 | C22: 14650130 | D22: 14164280 | E22: 15131270 | F22: 13175990 | G22: 15945730 | H22: 19442260 | I22: 23094630 | J22: 22735440 | K22: 20484320
A23: Saving in the form of gold & silver ornaments | B23: 336350 | C23: 366500 | D23: 367820 | E23: 455620 | F23: 464690 | G23: 465320 | H23: 466650 | I23: 426730 | J23: 431360 | K23: 384440
A25: Total | B25: 32057160 | C25: 35394970 | D25: 36602420 | E25: 40630900 | F25: 42195700 | G25: 44767540 | H25: 50531810 | I25: 58866570 | J25: 58721170 | K25: 52523090 | L25: 20000550 | M25: 20445960 | N25: 23799360 | O25: 28703880 | P25: 32057160 | Q25: 35394970 | R25: 36602420 | S25: 40630900 | T25: 42195700 | U25: 44767540 | V25: 50531810 | W25: 58866570 | X25: 58721170 | Y25: 52523090

Sheet RBI-Rates
A1: CRR, SLR, Repo, Reverse Repo and Bank Rate
A2: Per cent : Oct 2020 to Sep 2025
A3: Month | B3: CRR | C3: SLR | D3: Repo rate | E3: Reverse repo rate | F3: SDF | G3: MSF | H3: Bank rate
A4: 44105 | B4: 3 | C4: 18 | D4: 4 | E4: 3.35 | G4: 4.25 | H4: 4.25
A5: 44136 | B5: 3 | C5: 18 | D5: 4 | E5: 3.35 | G5: 4.25 | H5: 4.25
A6: 44166 | B6: 3 | C6: 18 | D6: 4 | E6: 3.35 | G6: 4.25 | H6: 4.25
A7: 44197 | B7: 3 | C7: 18 | D7: 4 | E7: 3.35 | G7: 4.25 | H7: 4.25
A8: 44228 | B8: 3 | C8: 18 | D8: 4 | E8: 3.35 | G8: 4.25 | H8: 4.25
A9: 44256 | B9: 3 | C9: 18 | D9: 4 | E9: 3.35 | G9: 4.25 | H9: 4.25
A10: 44287 | B10: 3.5 | C10: 18 | D10: 4 | E10: 3.35 | G10: 4.25 | H10: 4.25
A11: 44317 | B11: 4 | C11: 18 | D11: 4 | E11: 3.35 | G11: 4.25 | H11: 4.25
A12: 44348 | B12: 4 | C12: 18 | D12: 4 | E12: 3.35 | G12: 4.25 | H12: 4.25
A13: 44378 | B13: 4 | C13: 18 | D13: 4 | E13: 3.35 | G13: 4.25 | H13: 4.25
A14: 44409 | B14: 4 | C14: 18 | D14: 4 | E14: 3.35 | G14: 4.25 | H14: 4.25
A15: 44440 | B15: 4 | C15: 18 | D15: 4 | E15: 3.35 | G15: 4.25 | H15: 4.25
... A21: 44621 | B21: 4 | C21: 18 | D21: 4 | E21: 3.35 | G21: 4.25 | H21: 4.25
A22: 44652 | B22: 4 | C22: 18 | D22: 4 | E22: 3.35 | F22: 3.75 | G22: 4.25 | H22: 4.25
A23: 44682 | B23: 4.5 | C23: 18 | D23: 4.4 | E23: 3.35 | F23: 4.15 | G23: 4.65 | H23: 4.65
A24: 44713 | B24: 4.5 | C24: 18 | D24: 4.9 | E24: 3.35 | F24: 4.65 | G24: 5.15 | H24: 5.15
A25: 44743 | B25: 4.5 | C25: 18 | D25: 4.9 | E25: 3.35 | F25: 4.65 | G25: 5.15 | H25: 5.15
A26: 44774 | B26: 4.5 | C26: 18 | D26: 5.4 | E26: 3.35 | F26: 5.15 | G26: 5.65 | H26: 5.65
A27: 44805 | B27: 4.5 | C27: 18 | D27: 5.9 | E27: 3.35 | F27: 5.65 | G27: 6.15 | H27: 6.15
A28: 44835 | B28: 4.5 | C28: 18 | D28: 5.9 | E28: 3.35 | F28: 5.65 | G28: 6.15 | H28: 6.15
A29: 44866 | B29: 4.5 | C29: 18 | D29: 5.9 | E29: 3.35 | F29: 5.65 | G29: 6.15 | H29: 6.15
A30: 44896 | B30: 4.5 | C30: 18 | D30: 6.25 | E30: 3.35 | F30: 6 | G30: 6.5 | H30: 6.5
A31: 44927 | B31: 4.5 | C31: 18 | D31: 6.25 | E31: 3.35 | F31: 6 | G31: 6.5 | H31: 6.5
A32: 44958 | B32: 4.5 | C32: 18 | D32: 6.5 | E32: 3.35 | F32: 6.25 | G32: 6.75 | H32: 6.75
A33: 44986 | B33: 4.5 | C33: 18 | D33: 6.5 | E33: 3.35 | F33: 6.25 | G33: 6.75 | H33: 6.75
... A63: 45901 | B63: 3.75 | C63: 18 | D63: 5.5 | E63: 3.35 | F63: 5.25 | G63: 5.75 | H63: 5.75

Sheet WPI-Inflation
A1: Wholesale Price Index (WPI): General Index, Groups and Sub-groups including Food Group: Base Year: 2011-12
A2: Y-o-Y % change : September 2020 to August 2025
A3: Month | B3: All commodities | C3: Primary articles | D3: Primary articles | E3: Primary articles | F3: Primary articles | G3: Primary articles | H3: Fuel & power | I3: Fuel & power | J3: Fuel & power | K3: Fuel & power | L3: Manufactured products | M3: Food group
C4: Total | D4: Food articles | E4: Non-food articles | F4: Minerals | G4: Crude petroleum & natural gas | H4: Total | I4: Coal | J4: Mineral oils | K4: Electricity
A5: Weight | B5: 100 | C5: 22.61756 | D5: 15.25585 | E5: 4.11894 | F5: 0.83317 | G5: 2.4096 | H5: 13.1519 | I5: 2.13813 | J5: 7.94968 | K5: 3.06409 | L5: 64.23054 | M5: 24.37758
A6: 44075 | B6: 1.32 | C6: 4.06 | D6: 8.37 | E6: -1.81 | F6: -6.01 | G6: -23.41 | H6: -8.65 | I6: 1.28 | J6: -14.36 | K6: -4.27 | L6: 1.87 | M6: 7.19
A7: 44105 | B7: 1.31 | C7: 4.33 | D7: 7.05 | E7: 2.93 | F7: -0.2 | G7: -22.95 | H7: -11.14 | I7: -0.08 | J7: -18.32 | K7: -4.27 | L7: 2.21 | M7: 6.18
A8: 44136 | B8: 2.29 | C8: 3.8 | D8: 4.61 | E8: 8.66 | F8: 10.38 | G8: -21.51 | H8: -7.01 | I8: 0 | J8: -15.92 | K8: 6.73 | L8: 3.23 | M8: 4.79
A9: 44166 | B9: 1.95 | C9: -0.6 | D9: -0.92 | E9: 2.99 | F9: 16.67 | G9: -15.99 | H9: -6.1 | I9: 0.4 | J9: -11.17 | K9: -0.85 | L9: 4.49 | M9: 1.11
A10: 44197 | B10: 2.51 | C10: -1.56 | D10: -2.93 | E10: 4.24 | F10: 12.35 | G10: -9.44 | H10: -3.82 | I10: 0.4 | J10: -6.82 | K10: -0.85 | L10: 5.47 | M10: -0.26
A11: 44228 | B11: 4.83 | C11: 3.01 | D11: 1.81 | E11: 4.02 | F11: 17.09 | G11: 5.29 | H11: 2.03 | I11: 0.32 | J11: 3.14 | K11: 0.86 | L11: 6.06 | M11: 3.58
A12: 44256 | B12: 7.89 | C12: 7.28 | D12: 3.44 | E12: 11.94 | F12: 19.96 | G12: 38.49 | H12: 9.75 | I12: 0.32 | J12: 19.61 | K12: -2.46 | L12: 7.84 | M12: 5.63
A13: 44287 | B13: 10.74 | C13: 9.94 | D13: 4.6 | E13: 15.58 | F13: 20.64 | G13: 80.76 | H13: 21.27 | I13: 0.63 | J13: 46.03 | K13: -2.46 | L13: 9.44 | M13: 7.52
A14: 44317 | B14: 13.11 | C14: 9.4 | D14: 4.25 | E14: 18.37 | F14: 13.25 | G14: 59.52 | H14: 36.74 | I14: 0.71 | J14: 83.05 | K14: 0.19 | L14: 11.25 | M14: 8.25
A15: 44348 | B15: 12.07 | C15: 8.59 | D15: 3.28 | E15: 18.63 | F15: 15.33 | G15: 46.97 | H15: 29.32 | I15: 0.71 | J15: 61.81 | K15: -2.77 | L15: 10.96 | M15: 6.72
A16: 44378 | B16: 11.57 | C16: 6.34 | D16: 0.12 | E16: 22.94 | F16: 12.55 | G16: 42.25 | H16: 27.01 | I16: 0.87 | J16: 53.7 | K16: -2.77 | L16: 11.46 | M16: 4.52
A17: 44409 | B17: 11.64 | C17: 5.93 | D17: -0.8 | E17: 28.69 | F17: 7.16 | G17: 34.49 | H17: 28.15 | I17: 1.03 | J17: 52.68 | K17: 2.9 | L17: 11.56 | M17: 3.76
... A65: 45870 | B65: 0.52 | C65: -2.1 | D65: -3.06 | E65: 5.56 | F65: 3.3 | G65: -9.87 | H65: -3.17 | I65: 0.52 | J65: -4.72 | K65: -1.11 | L65: 2.55 | M65: 0.21
A67: Cumulative | B67: Apr-Aug | C67: Apr-Aug | D67: Apr-Aug | E67: Apr-Aug | F67: Apr-Aug | G67: Apr-Aug | H67: Apr-Aug | I67: Apr-Aug | J67: Apr-Aug | K67: Apr-Aug | L67: Apr-Aug | M67: Apr-Aug
A68: 2021-22 | B68: 11.82 | C68: 8 | D68: 2.24 | E68: 20.86 | F68: 13.68 | G68: 50.66 | H68: 28.31 | I68: 0.79 | J68: 58.37 | K68: -0.99 | L68: 10.93 | M68: 6.12
A69: 2022-23 | B69: 14.94 | C69: 16.42 | D69: 11.45 | E69: 17.31 | F69: 10.89 | G69: 70.27 | H69: 43.59 | I69: 3.26 | J69: 62.36 | K69: 25.72 | L69: 9.34 | M69: 10.17
A70: 2023-24 | B70: -2.07 | C70: 2.37 | D70: 6.68 | E70: -7.7 | F70: 5.16 | G70: -10.25 | H70: -8.13 | I70: 3.74 | J70: -14.29 | K70: 5.68 | L70: -2.6 | M70: 2.41
A71: 2024-25 | B71: 2.14 | C71: 5.42 | D71: 6.97 | E71: -2.68 | F71: 6.29 | G71: 7.5 | H71: 0.39 | I71: -0.56 | J71: 1.39 | K71: -1.91 | L71: 0.98 | M71: 5.84
A72: 2025-26 | B72: 0.14 | C72: -2.61 | D72: -2.85 | E72: 2.8 | F72: 1.27 | G72: -11.81 | H72: -3.46 | I72: 0.5 | J72: -5.83 | K72: 0.93 | L72: 2.25 | M72: 0.57

Sheet CPI-Level
A1: Consumer Price Index (CPI): Combined, Urban and Rural: General Index, Core Index and Non-core Index: Base Year 2012
A2: Index numbers : September 2020 to August 2025
B3: Combined | C3: Urban | D3: Rural | E3: Combined | F3: Urban | G3: Rural | H3: Combined | I3: Urban | J3: Rural | K3: Combined | L3: Combined | M3: Combined | N3: Combined
A4: Weight | B4: 100 | C4: 100 | D4: 100 | E4: 54.11 | F4: 64.8 | G4: 44.81 | H4: 45.9 | I4: 35.2 | J4: 55.19 | K4: 51.72 | L4: 48.29 | M4: 42.2 | N4: 57.8
A5: Month | B5: CPI general index | C5: CPI general index | D5: CPI general index | E5: Core CPI index (CPI excluding food group and fuel & light group) | F5: Core CPI index (CPI excluding food group and fuel & light group) | G5: Core CPI index (CPI excluding food group and fuel & light group) | H5: Non-core CPI index (includes food group and fuel & light group) | I5: Non-core CPI index (includes food group and fuel & light group) | J5: Non-core CPI index (includes food group and fuel & light group) | K5: Core Core CPI index (CPI excluding food group, fuel & light group and petrol, diesel & other fuels for vehicle) | L5: Non-core-core CPI index (includes food group, fuel & light group and petrol, diesel & other fuels for vehicle) | M5: Super core CPI index (excluding food group, fuel & light group and petrol, diesel & other fuels for vehicle and house rent) | N5: Non-super-core CPI index (includes food group, fuel & light group and petrol, diesel & other fuels for vehicle and house rent)
A6: 43009 | B6: 136.1 | C6: 133.5 | D6: 138.3 | E6: 134.2 | F6: 131.9 | G6: 137.1 | H6: 138.3 | I6: 136.5 | J6: 139.3 | K6: 135.7 | L6: 136.5 | M6: 135.3 | N6: 136.7
A7: 43040 | B7: 137.6 | C7: 134.8 | D7: 140 | E7: 135.1 | F7: 132.7 | G7: 138.2 | H7: 140.6 | I7: 138.8 | J7: 141.5 | K7: 136.6 | L7: 138.7 | M7: 136.1 | N7: 138.7
A8: 43070 | B8: 137.2 | C8: 134.1 | D8: 139.8 | E8: 135.4 | F8: 133 | G8: 138.4 | H8: 139.2 | I8: 136.1 | J8: 141 | K8: 136.9 | L8: 137.5 | M8: 136.3 | N8: 137.7
A9: 43101 | B9: 136.9 | C9: 134.1 | D9: 139.3 | E9: 136 | F9: 133.9 | G9: 138.7 | H9: 137.9 | I9: 134.5 | J9: 139.7 | K9: 137.4 | L9: 136.3 | M9: 136.7 | N9: 137
A10: 43132 | B10: 136.4 | C10: 134 | D10: 138.5 | E10: 136.5 | F10: 134.6 | G10: 138.9 | H10: 136.2 | I10: 132.8 | J10: 138.1 | K10: 137.8 | L10: 134.8 | M10: 137 | N10: 135.9
A11: 43160 | B11: 136.5 | C11: 134 | D11: 138.7 | E11: 137.2 | F11: 135.2 | G11: 139.7 | H11: 135.7 | I11: 131.7 | J11: 137.9 | K11: 138.5 | L11: 134.3 | M11: 137.7 | N11: 135.6
A12: 43191 | B12: 137.1 | C12: 134.8 | D12: 139.1 | E12: 138.1 | F12: 136.1 | G12: 140.6 | H12: 135.9 | I12: 132.3 | J12: 138 | K12: 139.4 | L12: 134.6 | M12: 138.6 | N12: 136
A13: 43221 | B13: 137.8 | C13: 135.4 | D13: 139.8 | E13: 138.8 | F13: 136.7 | G13: 141.4 | H13: 136.6 | I13: 133 | J13: 138.5 | K13: 140 | L13: 135.3 | M13: 139.3 | N13: 136.7
A14: 43252 | B14: 138.5 | C14: 136.2 | D14: 140.5 | E14: 139 | F14: 136.8 | G14: 141.8 | H14: 138 | I14: 135.2 | J14: 139.5 | K14: 140.2 | L14: 136.8 | M14: 139.7 | N14: 137.7
A15: 43282 | B15: 139.8 | C15: 137.5 | D15: 141.8 | E15: 139.6 | F15: 137.6 | G15: 142.1 | H15: 140 | I15: 137.4 | J15: 141.6 | K15: 140.8 | L15: 138.7 | M15: 140.2 | N15: 139.5
A16: 43313 | B16: 140.4 | C16: 138 | D16: 142.5 | E16: 140.3 | F16: 138.4 | G16: 142.7 | H16: 140.6 | I16: 137.3 | J16: 142.4 | K16: 141.5 | L16: 139.3 | M16: 140.8 | N16: 140.2
A17: 43344 | B17: 140.2 | C17: 138.1 | D17: 142.1 | E17: 141 | F17: 139.2 | G17: 143.3 | H17: 139.4 | I17: 136.1 | J17: 141.2 | K17: 142.1 | L17: 138.4 | M17: 141.3 | N17: 139.6
... A34: 43862 | B34: 149.1 | C34: 147.7 | D34: 150.4 | E34: 149 | F34: 146.8 | G34: 151.7 | H34: 149.3 | I34: 149.2 | J34: 149.5 | K34: 150.9 | L34: 147.3 | M34: 150 | N34: 148.5
A35: 43891 | B35: 148.6 | C35: 147.3 | D35: 149.8 | E35: 149.2 | F35: 146.9 | G35: 152 | H35: 148 | I35: 147.9 | J35: 148 | L35: 148 | N35: 148
A36: 43922 | B36: 151.4 | C36: 150.9 | D36: 151.9 | E36: 150.9 | F36: 149.9 | G36: 152.2 | H36: 152 | I36: 152.8 | J36: 151.6 | L36: 152 | N36: 152
A37: 43952 | B37: 150.9 | C37: 150.6 | D37: 151.2 | E37: 151.4 | F37: 150.2 | G37: 152.8 | H37: 150.4 | I37: 151.4 | J37: 149.9 | L37: 150.4 | N37: 150.4
A38: 43983 | B38: 151.8 | C38: 150.8 | D38: 152.7 | E38: 151.9 | F38: 149.2 | G38: 155.3 | H38: 151.7 | I38: 153.8 | J38: 150.6 | K38: 153.8 | L38: 149.7 | M38: 153.7 | N38: 150.5
A39: 44013 | B39: 153.9 | C39: 152.9 | D39: 154.7 | E39: 153.2 | F39: 151 | G39: 156 | H39: 154.7 | I39: 156.6 | J39: 153.6 | K39: 154.8 | L39: 152.9 | M39: 154.7 | N39: 153.3
A40: 44044 | B40: 154.7 | C40: 154 | D40: 155.4 | E40: 154.1 | F40: 152 | G40: 156.7 | H40: 155.6 | I40: 157.7 | J40: 154.4 | K40: 155.7 | L40: 153.8 | M40: 155.6 | N40: 154.2
A41: 44075 | B41: 156.4 | C41: 155.2 | D41: 157.5 | E41: 154.4 | F41: 152.2 | G41: 157.2 | H41: 158.8 | I41: 160.8 | J41: 157.8 | K41: 156 | L41: 156.9 | M41: 156 | N41: 156.8
A42: 44105 | B42: 158.4 | C42: 156.7 | D42: 159.8 | E42: 155.1 | F42: 153 | G42: 157.7 | H42: 162.2 | I42: 163.5 | J42: 161.5 | K42: 156.7 | L42: 160.1 | M42: 156.4 | N42: 159.7
A43: 44136 | B43: 158.9 | C43: 156.9 | D43: 160.7 | E43: 155.7 | F43: 153.5 | G43: 158.4 | H43: 162.8 | I43: 163.2 | J43: 162.6 | K43: 157.4 | L43: 160.7 | M43: 157.2 | N43: 160.3
A44: 44166 | B44: 157.3 | C44: 156 | D44: 158.5 | E44: 156.2 | F44: 153.8 | G44: 159.2 | H44: 158.7 | I44: 160.2 | J44: 157.9 | K44: 157.7 | L44: 156.9 | M44: 157.8 | N44: 157
A45: 44197 | B45: 156.3 | C45: 155.8 | D45: 156.8 | E45: 157.1 | F45: 154.8 | G45: 160.1 | H45: 155.5 | I45: 157.6 | J45: 154.3 | K45: 158.6 | L45: 153.9 | M45: 158.6 | N45: 154.7
A46: 44228 | B46: 156.6 | C46: 156.5 | D46: 156.7 | E46: 157.9 | F46: 155.7 | G46: 160.7 | H46: 155 | I46: 158 | J46: 153.5 | K46: 159.2 | L46: 153.8 | M46: 159.2 | N46: 154.7
A47: 44256 | B47: 156.8 | C47: 156.9 | D47: 156.7 | E47: 158.3 | F47: 156.2 | G47: 160.9 | H47: 155.1 | I47: 158.3 | J47: 153.4 | K47: 159.5 | L47: 154 | M47: 159.4 | N47: 154.9
A48: 44287 | B48: 157.8 | C48: 158 | D48: 157.6 | E48: 159.1 | F48: 157.1 | G48: 161.6 | H48: 156.3 | I48: 159.7 | J48: 154.4 | K48: 160.4 | L48: 155.1 | M48: 160.2 | N48: 156.1
A49: 44317 | B49: 160.4 | C49: 159.5 | D49: 161.1 | E49: 161.1 | F49: 158.1 | G49: 164.9 | H49: 159.4 | I49: 162.2 | J49: 157.9 | K49: 162.4 | L49: 158.2 | M49: 162.7 | N49: 158.7
... A100: 45870 | B100: 197 | C100: 195 | D100: 198.7 | E100: 195.3 | F100: 191.2 | G100: 200.5 | H100: 198.9 | I100: 201.9 | J100: 197.3 | K100: 197.7 | L100: 196.2 | M100: 200.4 | N100: 194.4
A101: Cumulative | B101: Apr-Aug | C101: Apr-Aug | D101: Apr-Aug | E101: Apr-Aug | F101: Apr-Aug | G101: Apr-Aug | H101: Apr-Aug | I101: Apr-Aug | J101: Apr-Aug | K101: Apr-Aug | L101: Apr-Aug | M101: Apr-Aug | N101: Apr-Aug
A102: 2021-22 | B102: 161 | C102: 160.4 | D102: 161.5 | E102: 161.5 | F102: 158.7 | G102: 165 | H102: 160.4 | I102: 163.4 | J102: 158.7 | K102: 162.6 | L102: 159.3 | M102: 162.9 | N102: 159.6
A103: 2022-23 | B103: 172.4 | C103: 171.4 | D103: 173.3 | E103: 171.6 | F103: 168.3 | G103: 175.7 | H103: 173.3 | I103: 177.1 | J103: 171.3 | K103: 172.5 | L103: 172.2 | M103: 173.7 | N103: 171.4
A104: 2023-24 | B104: 182.1 | C104: 180.9 | D104: 183.1 | E104: 180.3 | F104: 176.8 | G104: 184.8 | H104: 184.2 | I104: 188.6 | J104: 181.8 | K104: 181.9 | L104: 182.3 | M104: 183.5 | N104: 181.1
A105: 2024-25 | B105: 190.1 | C105: 187.8 | D105: 192.2 | E105: 186.2 | F105: 182.5 | G105: 190.9 | H105: 194.7 | I105: 197.6 | J105: 193.2 | K105: 188.2 | L105: 192.2 | M105: 190.1 | N105: 190.1
A106: 2025-26 | B106: 194.6 | C106: 192.9 | D106: 196 | E106: 194 | F106: 190 | G106: 199.2 | H106: 195.2 | I106: 198.1 | J106: 193.5 | K106: 196.4 | L106: 192.6 | M106: 199 | N106: 191.3

Sheet CPI-Inflation
A1: Consumer Price Index (CPI): Combined, Urban and Rural: General Index, Core Index and Non-core Index: Base Year 2012
A2: Y-o-Y % change : September 2020 to August 2025
B3: Combined | C3: Urban | D3: Rural | E3: Combined | F3: Urban | G3: Rural | H3: Combined | I3: Urban | J3: Rural | K3: Combined | L3: Combined | M3: Combined | N3: Combined
A4: Weight | B4: 100 | C4: 100 | D4: 100 | E4: 54.11 | F4: 64.8 | G4: 44.81 | H4: 45.9 | I4: 35.2 | J4: 55.19 | K4: 51.72 | L4: 48.29 | M4: 42.2 | N4: 57.8
A5: Month | B5: CPI general index | C5: CPI general index | D5: CPI general index | E5: Core CPI index (CPI excluding food group and fuel & light group) | F5: Core CPI index (CPI excluding food group and fuel & light group) | G5: Core CPI index (CPI excluding food group and fuel & light group) | H5: Non-core CPI index (includes food group and fuel & light group) | I5: Non-core CPI index (includes food group and fuel & light group) | J5: Non-core CPI index (includes food group and fuel & light group) | K5: Core Core CPI index (CPI excluding food group, fuel & light group and petrol, diesel & other fuels for vehicle) | L5: Non-core-core CPI index (includes food group, fuel & light group and petrol, diesel & other fuels for vehicle) | M5: Super core CPI index (excluding food group, fuel & light group and petrol, diesel & other fuels for vehicle and house rent) | N5: Non-super-core CPI index (includes food group, fuel & light group and petrol, diesel & other fuels for vehicle and house rent)
A6: 43556 | B6: 2.99 | C6: 4.3 | D6: 1.87 | E6: 4.29 | F6: 4.18 | G6: 4.45 | H6: 1.32 | I6: 4.48 | J6: -0.39 | K6: 4.56 | L6: 1.17 | M6: 4.55 | N6: 1.77
A7: 43586 | B7: 3.05 | C7: 4.51 | D7: 1.86 | E7: 4 | F7: 3.97 | G7: 4.09 | H7: 1.93 | I7: 5.56 | J7: 0.09 | K7: 4.35 | L7: 1.63 | M7: 4.25 | N7: 2.15
A8: 43617 | B8: 3.18 | C8: 4.33 | D8: 2.21 | E8: 3.95 | F8: 3.86 | G8: 4.01 | H8: 2.25 | I8: 5.26 | J8: 0.64 | K8: 4.37 | L8: 1.83 | M8: 4.27 | N8: 2.32
A9: 43647 | B9: 3.15 | C9: 4.22 | D9: 2.19 | E9: 4.07 | F9: 3.93 | G9: 4.26 | H9: 1.96 | I9: 4.65 | J9: 0.48 | K9: 4.42 | L9: 1.65 | M9: 4.34 | N9: 2.19
A10: 43678 | B10: 3.28 | C10: 4.49 | D10: 2.25 | E10: 4.01 | F10: 3.88 | G10: 4.21 | H10: 2.29 | I10: 5.51 | J10: 0.59 | K10: 4.45 | L10: 1.92 | M10: 4.36 | N10: 2.41
A11: 43709 | B11: 3.99 | C11: 4.78 | D11: 3.24 | E11: 3.77 | F11: 3.58 | G11: 4 | H11: 4 | I11: 6.89 | J11: 2.51 | K11: 4.29 | L11: 3.4 | M11: 4.19 | N11: 3.63
A12: 43739 | B12: 4.62 | C12: 5.11 | D12: 4.29 | E12: 3.31 | F12: 3.4 | G12: 3.23 | H12: 6.36 | I12: 8.33 | J12: 5.23 | K12: 3.82 | L12: 5.69 | M12: 3.63 | N12: 5.52
A13: 43770 | B13: 5.54 | C13: 5.76 | D13: 5.27 | E13: 3.26 | F13: 3.52 | G13: 3.02 | H13: 8.15 | I13: 9.81 | J13: 7.27 | K13: 3.54 | L13: 7.68 | M13: 3.3 | N13: 7.15
A14: 43800 | B14: 7.35 | C14: 7.46 | D14: 7.33 | E14: 3.55 | F14: 4.11 | G14: 2.91 | H14: 12.09 | I14: 13.75 | J14: 11.11 | K14: 3.47 | L14: 11.86 | M14: 3.26 | N14: 10.56
A15: 43831 | B15: 7.59 | C15: 7.39 | D15: 7.73 | E15: 3.95 | F15: 4.3 | G15: 3.51 | H15: 12.1 | I15: 13.3 | J15: 11.46 | K15: 3.83 | L15: 11.92 | M15: 3.72 | N15: 10.53
A16: 43862 | B16: 6.58 | C16: 6.57 | D16: 6.67 | E16: 3.89 | F16: 4.14 | G16: 3.48 | H16: 10.13 | I16: 11.18 | J16: 9.52 | K16: 3.89 | L16: 9.85 | M16: 3.79 | N16: 8.86
A17: 43891 | B17: 5.84 | C17: 5.59 | D17: 6.09 | E17: 3.79 | F17: 3.93 | G17: 3.58 | H17: 8.42 | I17: 8.78 | J17: 8.25 | L17: 9.63 | N17: 7.79
A18: 43922 | B18: 7.22 | C18: 7.33 | D18: 7.2 | E18: 4.76 | F18: 5.69 | G18: 3.67 | H18: 10.39 | I18: 10.54 | J18: 10.28 | L18: 11.64 | N18: 9.84
A19: 43952 | B19: 6.27 | C19: 6.43 | D19: 6.18 | E19: 4.88 | F19: 5.72 | G19: 3.81 | H19: 8.06 | I19: 7.85 | J19: 8.16 | L19: 9.36 | N19: 7.74
A20: 43983 | B20: 6.23 | C20: 6.12 | D20: 6.34 | E20: 5.13 | F20: 5 | G20: 5.27 | H20: 7.5 | I20: 8.07 | J20: 7.2 | K20: 5.13 | L20: 7.5 | M20: 5.53 | N20: 6.78
A21: 44013 | B21: 6.73 | C21: 6.7 | D21: 6.76 | E21: 5.45 | F21: 5.57 | G21: 5.31 | H21: 8.31 | I21: 8.97 | J21: 7.96 | K21: 5.29 | L21: 8.42 | M21: 5.79 | N21: 7.51
A22: 44044 | B22: 6.69 | C22: 6.8 | D22: 6.66 | E22: 5.57 | F22: 5.67 | G22: 5.39 | H22: 8.21 | I22: 8.89 | J22: 7.77 | K22: 5.35 | L22: 8.35 | M22: 5.92 | N22: 7.4
A23: 44075 | B23: 7.27 | C23: 7.26 | D23: 7.36 | E23: 5.51 | F23: 5.52 | G23: 5.47 | H23: 9.55 | I23: 10.57 | J23: 8.98 | K23: 5.29 | L23: 9.64 | M23: 5.92 | N23: 8.41
A24: 44105 | B24: 7.61 | C24: 7.33 | D24: 7.75 | E24: 5.66 | F24: 5.69 | G24: 5.59 | H24: 9.75 | I24: 10.27 | J24: 9.5 | K24: 5.51 | L24: 9.75 | M24: 6.06 | N24: 8.61
A25: 44136 | B25: 6.93 | C25: 6.73 | D25: 7.2 | E25: 5.8 | F25: 5.75 | G25: 5.8 | H25: 8.39 | I25: 8.55 | J25: 8.3 | K25: 5.67 | L25: 8.44 | M25: 6.29 | N25: 7.53
A26: 44166 | B26: 4.59 | C26: 5.19 | D26: 4.07 | E26: 5.68 | F26: 5.6 | G26: 5.73 | H26: 3.35 | I26: 4.48 | J26: 2.77 | K26: 5.48 | L26: 3.63 | M26: 6.05 | N26: 3.53
A27: 44197 | B27: 4.06 | C27: 5.13 | D27: 3.23 | E27: 5.75 | F27: 5.74 | G27: 5.78 | H27: 2.23 | I27: 3.99 | J27: 1.19 | K27: 5.54 | L27: 2.59 | M27: 6.11 | N27: 2.67
A28: 44228 | B28: 5.03 | C28: 5.96 | D28: 4.19 | E28: 5.99 | F28: 6.04 | G28: 5.95 | H28: 3.82 | I28: 5.89 | J28: 2.67 | K28: 5.54 | L28: 4.42 | M28: 6.13 | N28: 4.17
A29: 44256 | B29: 5.52 | C29: 6.52 | D29: 4.61 | E29: 6.11 | F29: 6.3 | G29: 5.86 | H29: 4.81 | I29: 7.07 | J29: 3.61 | L29: 4.06 | N29: 4.68
A30: 44287 | B30: 4.23 | C30: 4.71 | D30: 3.75 | E30: 5.45 | F30: 4.82 | G30: 6.16 | H30: 2.81 | I30: 4.55 | J30: 1.85 | L30: 2.01 | N30: 2.68
A31: 44317 | B31: 6.3 | C31: 5.91 | D31: 6.55 | E31: 6.43 | F31: 5.25 | G31: 7.94 | H31: 5.98 | I31: 7.14 | J31: 5.35 | L31: 5.15 | N31: 5.5
A32: 44348 | B32: 6.26 | C32: 6.37 | D32: 6.16 | E32: 6.35 | F32: 6.21 | G32: 6.52 | H32: 6.19 | I32: 6.61 | J32: 5.96 | K32: 5.68 | L32: 6.87 | M32: 6.14 | N32: 6.33
A33: 44378 | B33: 5.59 | C33: 5.82 | D33: 5.49 | E33: 6.13 | F33: 5.74 | G33: 6.59 | H33: 5.11 | I33: 5.89 | J33: 4.63 | K33: 5.53 | L33: 5.82 | M33: 5.93 | N33: 5.46
A34: 44409 | B34: 5.3 | C34: 5.32 | D34: 5.28 | E34: 5.98 | F34: 5.53 | G34: 6.54 | H34: 4.45 | I34: 4.97 | J34: 4.22 | K34: 5.38 | L34: 5.18 | M34: 5.72 | N34: 4.95
A35: 44440 | B35: 4.35 | C35: 4.57 | D35: 4.13 | E35: 6 | F35: 5.54 | G35: 6.57 | H35: 2.42 | I35: 2.91 | J35: 2.14 | K35: 5.46 | L35: 3.15 | M35: 5.89 | N35: 3.21
A36: 44470 | B36: 4.48 | C36: 5.04 | D36: 4.07 | E36: 6.24 | F36: 5.73 | G36: 6.85 | H36: 2.63 | I36: 3.96 | J36: 1.87 | K36: 5.52 | L36: 3.53 | M36: 5.99 | N36: 3.51
A37: 44501 | B37: 4.91 | C37: 5.54 | D37: 4.29 | E37: 6.21 | F37: 5.75 | G37: 6.74 | H37: 3.39 | I37: 5.19 | J37: 2.42 | K37: 5.61 | L37: 4.11 | M37: 6.08 | N37: 4.01
A38: 44531 | B38: 5.66 | C38: 5.9 | D38: 5.36 | E38: 6.12 | F38: 5.65 | G38: 6.73 | H38: 5 | I38: 6.22 | J38: 4.27 | K38: 5.73 | L38: 5.5 | M38: 6.22 | N38: 5.17
A39: 44562 | B39: 6.01 | C39: 5.91 | D39: 6.12 | E39: 6.01 | F39: 5.54 | G39: 6.59 | H39: 5.99 | I39: 6.63 | J39: 5.64 | K39: 5.64 | L39: 6.4 | M39: 6.15 | N39: 5.9
A40: 44593 | B40: 6.07 | C40: 5.75 | D40: 6.38 | E40: 6.02 | F40: 5.53 | G40: 6.63 | H40: 6.27 | I40: 6.29 | J40: 6.18 | K40: 5.77 | L40: 6.5 | M40: 6.29 | N40: 5.99
A41: 44621 | B41: 6.95 | C41: 6.12 | D41: 7.66 | E41: 6.33 | F41: 5.67 | G41: 7.14 | H41: 7.65 | I41: 6.93 | J41: 8.07 | K41: 6.21 | L41: 7.74 | M41: 6.87 | N41: 6.99
A42: 44652 | B42: 7.79 | C42: 7.09 | D42: 8.38 | E42: 6.95 | F42: 6.3 | G42: 7.73 | H42: 8.66 | I42: 8.4 | J42: 8.88 | K42: 6.46 | L42: 9.15 | M42: 7.15 | N42: 8.18
A43: 44682 | B43: 7.04 | C43: 7.08 | D43: 7.08 | E43: 6.17 | F43: 6.12 | G43: 6.16 | H43: 8.2 | I43: 8.71 | J43: 7.85 | K43: 5.73 | L43: 8.54 | M43: 6.2 | N43: 7.69
... A82: 45870 | B82: 2.07 | C82: 2.47 | D82: 1.69 | E82: 4.13 | F82: 3.98 | G82: 4.3 | H82: -0.28 | I82: -0.08 | J82: -0.34 | K82: 4.24 | L82: -0.26 | M82: 4.52 | N82: 0.23
A84: Cumulative | B84: Apr-Aug | C84: Apr-Aug | D84: Apr-Aug | E84: Apr-Aug | F84: Apr-Aug | G84: Apr-Aug | H84: Apr-Aug | I84: Apr-Aug | J84: Apr-Aug | K84: Apr-Aug | L84: Apr-Aug | M84: Apr-Aug | N84: Apr-Aug
A85: 2021-22 | B85: 5.53 | C85: 5.62 | D85: 5.44 | E85: 6.07 | F85: 5.51 | G85: 6.75 | H85: 4.9 | I85: 5.82 | J85: 4.4 | L85: 4.23 | N85: 4.98
A86: 2022-23 | B86: 7.11 | C86: 6.85 | D86: 7.29 | E86: 6.22 | F86: 6 | G86: 6.47 | H86: 8.09 | I86: 8.36 | J86: 7.94 | K86: 6.13 | L86: 8.08 | M86: 6.66 | N86: 7.36
A87: 2023-24 | B87: 5.64 | C87: 5.59 | D87: 5.68 | E87: 5.1 | F87: 5.05 | G87: 5.17 | H87: 6.26 | I87: 6.49 | J87: 6.13 | K87: 5.43 | L87: 5.86 | M87: 5.62 | N87: 5.66
A88: 2024-25 | B88: 4.38 | C88: 3.77 | D88: 4.93 | E88: 3.26 | F88: 3.23 | G88: 3.3 | H88: 5.73 | I88: 4.75 | J88: 6.28 | K88: 3.44 | L88: 5.42 | M88: 3.63 | N88: 4.98
A89: 2025-26 | B89: 2.35 | C89: 2.72 | D89: 2.01 | E89: 4.22 | F89: 4.13 | G89: 4.32 | H89: 0.21 | I89: 0.28 | J89: 0.17 | K89: 4.35 | L89: 0.21 | M89: 4.64 | N89: 0.65

Sheet REER-CPI
A1: Real Effective Exchange Rate Based On Consumer Price Index (CPI) : Base Year 2004-05
A2: Index numbers : 2004-05 to 2022-23
A3: Year | B3: Export weights | C3: Export weights | D3: Export weights | E3: Trade weights | F3: Trade weights | G3: Trade weights | H3: Trade weights | I3: Trade weights | J3: Trade weights | K3: Trade weights | L3: Trade weights | M3: Trade weights | N3: Trade weights
B4: 40 currency | C4: 36 currency | D4: 6 currency | E4: 40 currency | F4: 36 currency | G4: 6 currency | H4: 6 currency | I4: 6 currency | J4: 6 currency | K4: 6 currency | L4: 6 currency | M4: 6 currency | N4: 6 currency
B6: (2015-16 = 100) | C6: (2004-05 = 100) | D6: (2004-05 = 100) | E6: (2015-16 = 100) | F6: (2004-05 = 100) | G6: (2018-19 = 100) | H6: (2015-16 = 100) | I6: (2004-05 = 100) | J6: (2012-13 = 100) | K6: (2013-14 = 100) | L6: (2014-15 = 100) | M6: (2016-17 = 100) | N6: (2021-22 = 100)
A7: Year | B7: Export weights
A8: 2004-05 | B8: 87.4 | C8: 100 | D8: 100 | E8: 89.2 | F8: 100 | I8: 100
A9: 2005-06 | B9: 89.1 | C9: 102 | D9: 104.3 | E9: 91.3 | F9: 102.4 | I9: 104.4
A10: 2006-07 | B10: 87.8 | C10: 100.5 | D10: 104 | E10: 89.9 | F10: 100.8 | I10: 103.8
A11: 2007-08 | B11: 95.4 | C11: 109.2 | D11: 114.6 | E11: 97.4 | F11: 109.2 | I11: 113.4
A12: 2008-09 | B12: 87.1 | C12: 99.7 | D12: 106 | E12: 88.9 | F12: 99.7 | I12: 103.9
A13: 2009-10 | B13: 91.7 | C13: 105 | D13: 113.4 | E13: 92.7 | F13: 103.9 | I13: 110.7
A14: 2010-11 | B14: 100.5 | C14: 115 | D14: 128.5 | E14: 100.5 | F14: 112.7 | I14: 124.5
A15: 2011-12 | B15: 98.9 | C15: 113.2 | D15: 125.8 | E15: 98.4 | F15: 110.3 | I15: 121.2 | J15: 106.3
A16: 2012-13 | B16: 95 | C16: 108.7 | D16: 121.8 | E16: 94.2 | F16: 105.6 | I16: 117.2 | J16: 100 | K16: 103.9
A17: 2013-14 | B17: 92.2 | C17: 105.5 | D17: 117.6 | E17: 92.1 | F17: 103.3 | I17: 112.8 | J17: 96.1 | K17: 100 | L17: 94.1
A18: 2014-15 | B18: 97.2 | C18: 111.3 | E18: 97.2 | F18: 109 | H18: 97.7 | I18: 119.9 | K18: 106.4 | L18: 100
A19: 2015-16 | B19: 100 | C19: 114.4 | E19: 100 | F19: 112.1 | H19: 100 | I19: 122.7 | L19: 103 | M19: 98
A20: 2016-17 | B20: 101.4 | C20: 116.5 | E20: 101.8 | F20: 114.5 | H20: 102.7 | I20: 125.2 | M20: 100
A21: 2017-18 | B21: 105.7 | C21: 121.9 | E21: 105.9 | F21: 119.7 | I21: 129.2 | M21: 103.8
A22: 2018-19 | B22: 100.3 | C22: 116.3 | E22: 100.6 | F22: 114 | G22: 100 | H22: 100.3 | I22: 121.7
A23: 2019-20 | B23: 102.9 | C23: 119.6 | E23: 103.2 | F23: 116.8 | G23: 103.3 | H23: 103.6 | I23: 125.8
A24: 2020-21 | B24: 103 | E24: 103.5 | G24: 101.5 | H24: 101.8
A25: 2021-22 | B25: 103.5 | E25: 104.6 | H25: 102.3 | N25: 100
A26: 2022-23 | B26: 100.9 | E26: 102.7 | H26: 102 | N26: 99.7

Sheet Textile-Apparel-Imports
A1: India's Imports of Major Commodities from World
A2: USD Million : 1991-92 to 2023-24
A3: Year | B3: Non-POL | C3: Non-POL
B4: Manufactured goods | C4: Manufactured goods
A5: Year | B5: Textiles (excluding readymade garments) | C5: Readymade garments
A6: 1991-92 | B6: 158.9
A7: 1992-93 | B7: 167.8
A8: 1993-94 | B8: 254.3
A9: 1994-95 | B9: 371
A10: 1995-96 | B10: 396.6
A11: 1996-97 | B11: 391.4
A12: 1997-98 | B12: 443.8
A13: 1998-99 | B13: 480.8
A14: 1999-00 | B14: 545.7 | C14: 16.1
A15: 2000-01 | B15: 606.7 | C15: 21.4
A16: 2001-02 | B16: 733.8 | C16: 36.2
A17: 2002-03 | B17: 963.4 | C17: 23.9
A18: 2003-04 | B18: 1249.2 | C18: 38.7
A19: 2004-05 | B19: 1562.4 | C19: 33.3
A20: 2005-06 | B20: 2038.5 | C20: 56.8
A21: 2006-07 | B21: 2101.6 | C21: 70.9
A22: 2007-08 | B22: 2378.1 | C22: 111
A23: 2008-09 | B23: 2450.4 | C23: 138.9
A24: 2009-10 | B24: 2475 | C24: 107.6
A25: 2010-11 | B25: 3045 | C25: 197.2
... A37: 2022-23 | B37: 6153.3 | C37: 1756.7
A38: 2023-24

Sheet Textile-Apparel-Exports
A1: India's Exports to Regions and Countries : Textiles (excluding readymade garments)
A2: USD Million : 1991-92 to 2022-23
A3: Year | B3: World | C3: Regions | D3: Regions | E3: Regions | F3: Regions | G3: Regions | H3: Regions | I3: Regions | J3: Countries | K3: Countries | L3: Countries | M3: Countries | N3: Countries | O3: Countries | P3: Countries | Q3: Countries | R3: Countries | S3: Countries | T3: Countries | U3: Countries | V3: Countries | W3: Countries | X3: Countries | Y3: Countries | Z3: Countries | AA3: Countries | AB3: Countries | AC3: Countries | AD3: Countries | AE3: Countries | AF3: Countries | AG3: Countries | AH3: Countries | AI3: Countries | AJ3: Countries | AK3: Countries | AL3: Countries | AM3: Countries | AN3: Countries | AO3: Countries | AP3: Countries | AQ3: Countries | AR3: Countries | AS3: Countries | AT3: Countries | AU3: Countries | AV3: Countries | AW3: Countries | AX3: Countries | AY3: Countries | AZ3: Countries | BA3: Countries | BB3: Countries | BC3: Countries | BD3: Countries | BE3: Countries | BF3: Countries | BG3: Countries | BH3: Countries | BI3: Countries | BJ3: Countries | BK3: Countries | BL3: Countries | BM3: Countries | BN3: Countries | BO3: Countries | BP3: Countries | BQ3: Countries
C4: Africa | D4: America | E4: Europe | F4: Asia | G4: Oceania | H4: Antarctica | I4: Others | J4: USA | K4: Bangladesh | L4: UAE | M4: Turkey | N4: Sri Lanka | O4: UK | P4: Germany | Q4: Italy | R4: China | S4: Egypt | T4: Australia | U4: Netherlands | V4: France | W4: Spain | X4: Korea Republic (South) | Y4: Canada | Z4: Brazil | AA4: Senegal | AB4: Belgium | AC4: Nepal | AD4: Portugal | AE4: Japan | AF4: Vietnam | AG4: Nigeria | AH4: Mexico | AI4: Morocco | AJ4: Peru | AK4: Saudi Arabia | AL4: Indonesia | AM4: Thailand | AN4: South Africa | AO4: Colombia | AP4: Israel | AQ4: Kenya | AR4: Poland | AS4: Malaysia | AT4: Chile | AU4: Sudan (Former) | AV4: Sweden | AW4: Ghana | AX4: Togo | AY4: Denmark | AZ4: Benin | BA4: Argentina | BB4: Guatemala | BC4: Mauritius | BD4: Tanzania | BE4: Ethiopia | BF4: Philippines | BG4: Norway | BH4: New Zealand | BI4: Congo, D.R. | BJ4: Kuwait | BK4: Myanmar (Burma) | BL4: Jordan | BM4: Cote d'Ivoire (Ivory Coast) | BN4: Romania | BO4: Greece | BP4: Russia | BQ4: Afghanistan
A5: 1991-92 | B5: 2512.5 | C5: 106.7 | D5: 449.7 | E5: 1136.3 | F5: 765 | G5: 54.8 | J5: 394 | K5: 143 | L5: 166.8 | M5: 12.1 | N5: 31.1 | O5: 250.7 | P5: 304.8 | Q5: 120.8 | R5: 0.8 | S5: 7.8 | T5: 46 | U5: 29.2 | V5: 67.4 | W5: 31.6 | X5: 67.5 | Y5: 43.4 | Z5: 1.6 | AA5: 0.8 | AB5: 66.2 | AC5: 2.6 | AD5: 7.5 | AE5: 86.6 | AF5: 1.8 | AG5: 6.4 | AH5: 3.5 | AI5: 1.6 | AJ5: 0.1 | AK5: 36.5 | AL5: 8.4 | AM5: 12.3 | AO5: 0.6 | AP5: 3.6 | AQ5: 1.4 | AR5: 2.5 | AS5: 20.7 | AT5: 0.4 | AU5: 0.4 | AV5: 34.2 | AW5: 0.5 | AX5: 5.6 | AY5: 20.8 | AZ5: 9.7 | BA5: 2.3 | BB5: 0.2 | BC5: 30.9 | BD5: 6.3 | BE5: 0.9 | BF5: 3.6 | BG5: 10.9 | BH5: 8.5 | BJ5: 3.6 | BK5: 0.4 | BL5: 1.1 | BM5: 0.3 | BN5: 0.2 | BO5: 6.1 | BP5: 83 | BQ5: 0.6
A6: 1992-93 | B6: 2460.1 | C6: 125.9 | D6: 451.6 | E6: 1106.7 | F6: 704 | G6: 71.7 | J6: 399.1 | K6: 173.3 | L6: 157.2 | M6: 36 | N6: 34.9 | O6: 241.1 | P6: 306.9 | Q6: 114.2 | R6: 1.8 | S6: 10.6 | T6: 59.5 | U6: 31.6 | V6: 69.7 | W6: 32.8 | X6: 20.9 | Y6: 37.6 | Z6: 0.2 | AA6: 1 | AB6: 84.6 | AC6: 2.8 | AD6: 10.2 | AE6: 76.2 | AF6: 2 | AG6: 6.4 | AH6: 4.8 | AI6: 3.2 | AJ6: 0.1 | AK6: 38.4 | AL6: 7.4 | AM6: 6.9 | AN6: 0.1 | AO6: 1 | AP6: 8.3 | AQ6: 3.3 | AR6: 5 | AS6: 20.6 | AT6: 1 | AU6: 0.2 | AV6: 35.6 | AW6: 1 | AX6: 7 | AY6: 23.1 | AZ6: 6.4 | BA6: 1.9 | BB6: 0.4 | BC6: 32.1 | BD6: 5.8 | BE6: 4.7 | BF6: 4.4 | BG6: 11.9 | BH6: 12 | BI6: 0.1 | BJ6: 9.2 | BK6: 0.3 | BL6: 2 | BM6: 0.2 | BN6: 0.4 | BO6: 6.6 | BP6: 19.5 | BQ6: 0.8
A7: 1993-94 | B7: 2882.8 | C7: 146 | D7: 499.3 | E7: 1310.3 | F7: 860.5 | G7: 66.8 | J7: 433.6 | K7: 184.9 | L7: 210.3 | M7: 40.7 | N7: 41.9 | O7: 304.4 | P7: 349 | Q7: 116.3 | R7: 3 | S7: 9.8 | T7: 54.7 | U7: 47 | V7: 71.2 | W7: 29.6 | X7: 28.2 | Y7: 43.8 | Z7: 1.1 | AA7: 0.2 | AB7: 110.7 | AC7: 5.1 | AD7: 17.4 | AE7: 108.5 | AF7: 1.4 | AG7: 7.5 | AH7: 8.1 | AI7: 3.9 | AJ7: 0.2 | AK7: 38.5 | AL7: 5.4 | AM7: 9.3 | AN7: 4.3 | AO7: 0.7 | AP7: 17.5 | AQ7: 14.8 | AR7: 1.5 | AS7: 21.8 | AT7: 3.2 | AU7: 0.4 | AV7: 36.1 | AW7: 1.1 | AX7: 4.6 | AY7: 23.7 | AZ7: 5.4 | BA7: 2.6 | BB7: 0.4 | BC7: 49.3 | BD7: 4.7 | BE7: 1.5 | BF7: 5.1 | BG7: 13.4 | BH7: 11.9 | BI7: 0 | BJ7: 10.1 | BK7: 0.2 | BL7: 4.7 | BM7: 0.1 | BN7: 0.2 | BO7: 8.4 | BP7: 32.6 | BQ7: 0.4
A8: 1994-95 | B8: 3836.8 | C8: 224.4 | D8: 613 | E8: 1605 | F8: 1296.7 | G8: 97.7 | J8: 530.9 | K8: 268.7 | L8: 259.7 | M8: 41 | N8: 64 | O8: 381 | P8: 345.2 | Q8: 177 | R8: 11.2 | S8: 17.4 | T8: 78.1 | U8: 65 | V8: 92.3 | W8: 53.7 | X8: 95 | Y8: 49.3 | Z8: 5.3 | AA8: 0.9 | AB8: 163.1 | AC8: 4.5 | AD8: 21.8 | AE8: 157.6 | AF8: 3.8 | AG8: 8.8 | AH8: 8 | AI8: 4.4 | AJ8: 0.4 | AK8: 44.1 | AL8: 9.2 | AM8: 13.5 | AN8: 34.8 | AO8: 0.8 | AP8: 24.6 | AQ8: 18 | AR8: 1.9 | AS8: 38 | AT8: 4.8 | AU8: 1.1 | AV8: 42.9 | AW8: 1.1 | AX8: 10.4 | AY8: 30.6 | AZ8: 5.5 | BA8: 3.5 | BB8: 1.6 | BC8: 73.6 | BD8: 4.7 | BE8: 1.2 | BF8: 12 | BG8: 18.4 | BH8: 19.3 | BI8: 0.1 | BJ8: 11.5 | BK8: 0.1 | BL8: 5.1 | BM8: 0.6 | BN8: 0.4 | BO8: 10.2 | BP8: 67 | BQ8: 0.5
A9: 1995-96 | B9: 4361.2 | C9: 324.5 | D9: 698.2 | E9: 1797.1 | F9: 1446.7 | G9: 94.7 | J9: 602.5 | K9: 292 | L9: 262.7 | M9: 67.6 | N9: 64.2 | O9: 405.5 | P9: 382.4 | Q9: 210.6 | R9: 22.9 | S9: 26.3 | T9: 76.6 | U9: 69.2 | V9: 103.7 | W9: 70.6 | X9: 110.8 | Y9: 51.6 | Z9: 10.4 | AA9: 5.7 | AB9: 163.8 | AC9: 9.7 | AD9: 32.4 | AE9: 145 | AF9: 4.3 | AG9: 22.2 | AH9: 4.8 | AI9: 5.5 | AJ9: 0.4 | AK9: 63.1 | AL9: 11.8 | AM9: 15.9 | AN9: 42.2 | AO9: 2.8 | AP9: 39.2 | AQ9: 16.6 | AR9: 2.3 | AS9: 39.3 | AT9: 8 | AU9: 2.9 | AV9: 47.2 | AW9: 1.6 | AX9: 10.3 | AY9: 34.4 | AZ9: 5.9 | BA9: 4.4 | BB9: 1.1 | BC9: 92.5 | BD9: 10.9 | BE9: 1.6 | BF9: 11.5 | BG9: 18.5 | BH9: 17.7 | BJ9: 16.8 | BK9: 0.1 | BL9: 7.2 | BM9: 0.6 | BN9: 0.2 | BO9: 15.4 | BP9: 75 | BQ9: 1.7
A10: 1996-97 | B10: 4885.3 | C10: 386.4 | D10: 897.3 | E10: 1799.5 | F10: 1708.6 | G10: 93.5 | J10: 751.5 | K10: 355.6 | L10: 233.9 | M10: 60.3 | N10: 67.7 | O10: 415.9 | P10: 378.7 | Q10: 181.2 | R10: 48.4 | S10: 43.1 | T10: 75 | U10: 60.5 | V10: 98.4 | W10: 77.7 | X10: 130.3 | Y10: 69 | Z10: 18 | AA10: 4.6 | AB10: 158.1 | AC10: 13.7 | AD10: 32.8 | AE10: 150.9 | AF10: 6.8 | AG10: 12.4 | AH10: 7.5 | AI10: 7.2 | AJ10: 0.3 | AK10: 59.8 | AL10: 18.2 | AM10: 17.5 | AN10: 51.5 | AO10: 12.2 | AP10: 36.4 | AQ10: 24.5 | AR10: 5.6 | AS10: 45.9 | AT10: 13.8 | AU10: 1.7 | AV10: 54.8 | AW10: 4.6 | AX10: 20.8 | AY10: 34.5 | AZ10: 13.2 | BA10: 8.3 | BB10: 1.5 | BC10: 101.5 | BD10: 9.7 | BE10: 2.7 | BF10: 10.5 | BG10: 21.7 | BH10: 17.3 | BJ10: 18.4 | BK10: 0.1 | BL10: 7.3 | BM10: 3.3 | BN10: 0.4 | BO10: 17.8 | BP10: 83.9 | BQ10: 2
A11: 1997-98 | B11: 5179.1 | C11: 467.5 | D11: 942.1 | E11: 1886.2 | F11: 1783.9 | G11: 99.4 | J11: 746.9 | K11: 291.9 | L11: 260.8 | M11: 91.3 | N11: 77.4 | O11: 404 | P11: 336.9 | Q11: 246.4 | R11: 59.1 | S11: 69.2 | T11: 81.1 | U11: 66.9 | V11: 106.9 | W11: 89.8 | X11: 127 | Y11: 88.8 | Z11: 21.1 | AA11: 6.3 | AB11: 163.7 | AC11: 12.4 | AD11: 34.9 | AE11: 180.5 | AF11: 6.1 | AG11: 10.9 | AH11: 15.1 | AI11: 8.5 | AJ11: 0.7 | AK11: 77.2 | AL11: 20.7 | AM11: 18.2 | AN11: 67.8 | AO11: 13.6 | AP11: 63.6 | AQ11: 20.2 | AR11: 10.2 | AS11: 41.9 | AT11: 21.9 | AU11: 4.3 | AV11: 55.9 | AW11: 10.9 | AX11: 19.7 | AY11: 39.1 | AZ11: 14.7 | BA11: 9.5 | BB11: 1.8 | BC11: 114.9 | BD11: 12 | BE11: 3.6 | BF11: 11 | BG11: 17.7 | BH11: 17.2 | BI11: 2.4 | BJ11: 18.6 | BK11: 0.4 | BL11: 7.9 | BM11: 4.5 | BN11: 0.5 | BO11: 17.6 | BP11: 85.5 | BQ11: 1.7
A12: 1998-99 | B12: 4496.1 | C12: 436.6 | D12: 938.6 | E12: 1640.9 | F12: 1392.2 | G12: 87.8 | J12: 759.6 | K12: 138.2 | L12: 237.1 | M12: 47.7 | N12: 84.6 | O12: 338.3 | P12: 301.7 | Q12: 236.2 | R12: 44.9 | S12: 71.2 | T12: 72.2 | U12: 58.6 | V12: 105.2 | W12: 93.1 | X12: 88.2 | Y12: 85.9 | Z12: 17.7 | AA12: 7.1 | AB12: 129.1 | AC12: 6.7 | AD12: 37.8 | AE12: 115.5 | AF12: 7.5 | AG12: 21.2 | AH12: 8.9 | AI12: 7.2 | AJ12: 1.6 | AK12: 68.8 | AL12: 15.3 | AM12: 22.1 | AN12: 45.9 | AO12: 11.2 | AP12: 64.1 | AQ12: 19.4 | AR12: 12.8 | AS12: 33.4 | AT12: 15.6 | AU12: 7.9 | AV12: 46.9 | AW12: 12.6 | AX12: 13.9 | AY12: 38.7 | AZ12: 14.6 | BA12: 10 | BB12: 1.4 | BC12: 99.9 | BD12: 15.8 | BE12: 2.7 | BF12: 7.6 | BG12: 13.3 | BH12: 11.9 | BI12: 4 | BJ12: 20.9 | BK12: 2 | BL12: 10.2 | BM12: 8 | BN12: 1.3 | BO12: 15.3 | BP12: 56.5 | BQ12: 2.1
A13: 1999-00 | B13: 5056.1 | C13: 482.8 | D13: 1085.4 | E13: 1721.4 | F13: 1673.3 | G13: 93.3 | J13: 886.3 | K13: 173.9 | L13: 269.4 | M13: 65.8 | N13: 98.5 | O13: 327.1 | P13: 329.2 | Q13: 215.7 | R13: 60.7 | S13: 68.4 | T13: 76.1 | U13: 60.8 | V13: 118.8 | W13: 99.6 | X13: 199.9 | Y13: 93.9 | Z13: 14.7 | AA13: 7 | AB13: 137.6 | AC13: 5.3 | AD13: 42.6 | AE13: 139 | AF13: 5.6 | AG13: 44.3 | AH13: 10.2 | AI13: 6 | AJ13: 1.9 | AK13: 70.9 | AL13: 32.2 | AM13: 37.8 | AN13: 38.8 | AO13: 12.6 | AP13: 65.5 | AQ13: 20.6 | AR13: 15.7 | AS13: 48.4 | AT13: 13.8 | AU13: 11.6 | AV13: 47.8 | AW13: 13.5 | AX13: 12.4 | AY13: 39.5 | AZ13: 18.1 | BA13: 9.2 | BB13: 2.8 | BC13: 105.8 | BD13: 15.7 | BE13: 3.4 | BF13: 12.2 | BG13: 15.7 | BH13: 12.9 | BI13: 8 | BJ13: 16.4 | BK13: 1.8 | BL13: 5.1 | BM13: 15.5 | BN13: 1.3 | BO13: 19.5 | BP13: 77.5 | BQ13: 2.5
A14: 2000-01 | B14: 5714.1 | C14: 606.9 | D14: 1254 | E14: 1886.1 | F14: 1878.9 | G14: 87.5 | I14: 0.8 | J14: 1003.1 | K14: 201.4 | L14: 296.1 | M14: 120.7 | N14: 105.5 | O14: 331.1 | P14: 316.1 | Q14: 260.5 | R14: 79.4 | S14: 86.4 | T14: 72.6 | U14: 58.4 | V14: 128.4 | W14: 126.5 | X14: 142 | Y14: 97.4 | Z14: 17.9 | AA14: 8.8 | AB14: 157 | AC14: 13.4 | AD14: 53.6 | AE14: 152 | AF14: 9.2 | AG14: 44 | AH14: 13 | AI14: 13.3 | AJ14: 2.8 | AK14: 81 | AL14: 42.2 | AM14: 33 | AN14: 52.5 | AO14: 19.9 | AP14: 74.4 | AQ14: 17 | AR14: 16.9 | AS14: 53.4 | AT14: 20.3 | AU14: 15.6 | AV14: 49.1 | AW14: 12.6 | AX14: 26 | AY14: 25.9 | AZ14: 21.3 | BA14: 13.8 | BB14: 4.5 | BC14: 118 | BD14: 28.3 | BE14: 2.8 | BF14: 15.5 | BG14: 16.2 | BH14: 11.9 | BI14: 13.9 | BJ14: 16.4 | BK14: 1 | BL14: 8 | BM14: 26.9 | BN14: 2.1 | BO14: 26.6 | BP14: 74.8 | BQ14: 5.2
A15: 2001-02 | B15: 5200 | C15: 607 | D15: 1102.9 | E15: 1612.4 | F15: 1792.1 | G15: 84.3 | I15: 1.4 | J15: 886 | K15: 183.3 | L15: 315.2 | M15: 74.1 | N15: 97.5 | O15: 304.9 | P15: 249 | Q15: 241.7 | R15: 80.9 | S15: 70.1 | T15: 70.3 | U15: 47.6 | V15: 111.4 | W15: 134.9 | X15: 141.5 | Y15: 86.7 | Z15: 16.1 | AA15: 6.6 | AB15: 122.4 | AC15: 9.8 | AD15: 53.9 | AE15: 145.8 | AF15: 5.3 | AG15: 57.7 | AH15: 15.3 | AI15: 26 | AJ15: 4.9 | AK15: 82.2 | AL15: 51.6 | AM15: 22.9 | AN15: 45 | AO15: 18.4 | AP15: 53.8 | AQ15: 20.2 | AR15: 17.2 | AS15: 79.3 | AT15: 13.7 | AU15: 10.3 | AV15: 44.1 | AW15: 11.3 | AX15: 39.2 | AY15: 22.7 | AZ15: 31.7 | BA15: 7.2 | BB15: 2.5 | BC15: 92.8 | BD15: 21.8 | BE15: 3.2 | BF15: 14.2 | BG15: 13.3 | BH15: 10.9 | BI15: 13.2 | BJ15: 23.5 | BK15: 0.6 | BL15: 8.9 | BM15: 23.5 | BN15: 0.8 | BO15: 23.7 | BP15: 36.6 | BQ15: 5.8
A16: 2002-03 | B16: 5925.3 | C16: 644.3 | D16: 1384.6 | E16: 1742.9 | F16: 2042.7 | G16: 103.9 | I16: 6.9 | J16: 1131.9 | K16: 167.8 | L16: 396.4 | M16: 138.9 | N16: 115.2 | O16: 300.2 | P16: 261.5 | Q16: 251.5 | R16: 76.1 | S16: 83.9 | T16: 88.2 | U16: 54.1 | V16: 112.9 | W16: 158.8 | X16: 195.5 | Y16: 106.8 | Z16: 23.4 | AA16: 8.3 | AB16: 126.5 | AC16: 11.5 | AD16: 62 | AE16: 157.4 | AF16: 9.7 | AG16: 51.2 | AH16: 16 | AI16: 37 | AJ16: 6.5 | AK16: 112.5 | AL16: 44.8 | AM16: 19.5 | AN16: 45.2 | AO16: 20.1 | AP16: 68.7 | AQ16: 24.3 | AR16: 22.2 | AS16: 69.1 | AT16: 15.3 | AU16: 6.2 | AV16: 44.4 | AW16: 21.1 | AX16: 44 | AY16: 24.5 | AZ16: 30.3 | BA16: 2.6 | BB16: 3 | BC16: 88 | BD16: 24.2 | BE16: 2.9 | BF16: 17.6 | BG16: 12.6 | BH16: 11.6 | BI16: 10.6 | BJ16: 23.9 | BK16: 0.5 | BL16: 10.2 | BM16: 16.9 | BN16: 1 | BO16: 26.6 | BP16: 18.3 | BQ16: 9.9
A17: 2003-04 | B17: 6564.5 | C17: 684.3 | D17: 1381.9 | E17: 2038.3 | F17: 2345.6 | G17: 101 | I17: 13.4 | J17: 1154.1 | K17: 207.2 | L17: 476 | M17: 207.1 | N17: 139.1 | O17: 346.5 | P17: 305.1 | Q17: 291.4 | R17: 97.3 | S17: 106.7 | T17: 83.1 | U17: 61.4 | V17: 134 | W17: 169.8 | X17: 227.7 | Y17: 100 | Z17: 23.1 | AA17: 6.2 | AB17: 120.7 | AC17: 39.2 | AD17: 68.4 | AE17: 149.2 | AF17: 12.5 | AG17: 49.2 | AH17: 14.8 | AI17: 41.8 | AJ17: 4.9 | AK17: 142.5 | AL17: 67.3 | AM17: 24.2 | AN17: 54.2 | AO17: 16.8 | AP17: 58 | AQ17: 25.1 | AR17: 28.2 | AS17: 81.3 | AT17: 15 | AU17: 4.8 | AV17: 51.6 | AW17: 28.5 | AX17: 34.5 | AY17: 26.3 | AZ17: 25.2 | BA17: 7.3 | BB17: 4.1 | BC17: 98.9 | BD17: 17.1 | BE17: 2.2 | BF17: 17.9 | BG17: 14.9 | BH17: 13.3 | BI17: 16.6 | BJ17: 32.7 | BK17: 0.3 | BL17: 11 | BM17: 13.4 | BN17: 3 | BO17: 37.6 | BP17: 21.4 | BQ17: 21.3
A18: 2004-05 | B18: 6991 | C18: 716.4 | D18: 1558.9 | E18: 2160.2 | F18: 2443.8 | G18: 105.1 | I18: 6.6 | J18: 1262.2 | K18: 252.8 | L18: 565.1 | M18: 224.2 | N18: 139.2 | O18: 344.3 | P18: 336.5 | Q18: 338.1 | R18: 93.1 | S18: 129.5 | T18: 86.4 | U18: 67 | V18: 150.3 | W18: 175.6 | X18: 186.2 | Y18: 101.3 | Z18: 54.6 | AA18: 6.9 | AB18: 141.6 | AC18: 23.4 | AD18: 65.1 | AE18: 128.1 | AF18: 17.7 | AG18: 25.8 | AH18: 16.9 | AI18: 40.1 | AJ18: 17.4 | AK18: 154.6 | AL18: 66.3 | AM18: 23.2 | AN18: 64.5 | AO18: 21 | AP18: 66.5 | AQ18: 30.8 | AR18: 30.1 | AS18: 108.6 | AT18: 19.5 | AU18: 11.8 | AV18: 50.1 | AW18: 29 | AX18: 28.6 | AY18: 29.8 | AZ18: 24.6 | BA18: 11.8 | BB18: 7.3 | BC18: 79.2 | BD18: 17.3 | BE18: 1.6 | BF18: 19.5 | BG18: 17.8 | BH18: 14.4 | BI18: 21.5 | BJ18: 30.5 | BK18: 1.2 | BL18: 7.8 | BM18: 5.1 | BN18: 6.6 | BO18: 38.6 | BP18: 17.4 | BQ18: 46
A19: 2005-06 | B19: 7783.2 | C19: 708.1 | D19: 1991.6 | E19: 2475.4 | F19: 2490.9 | G19: 112.8 | I19: 4.4 | J19: 1632.8 | K19: 310.9 | L19: 520 | M19: 233.9 | N19: 174.1 | O19: 356.3 | P19: 414.2 | Q19: 392.8 | R19: 117.5 | S19: 164.7 | T19: 92.1 | U19: 81.7 | V19: 152.4 | W19: 197.9 | X19: 232.1 | Y19: 118.6 | Z19: 69.1 | AA19: 12.3 | AB19: 153.7 | AC19: 22.2 | AD19: 90 | AE19: 137.4 | AF19: 17.9 | AG19: 11.8 | AH19: 19.9 | AI19: 42.3 | AJ19: 20.9 | AK19: 150.9 | AL19: 43.7 | AM19: 30.7 | AN19: 68.7 | AO19: 24.2 | AP19: 74.2 | AQ19: 32.8 | AR19: 40.6 | AS19: 81.4 | AT19: 27 | AU19: 18 | AV19: 68.9 | AW19: 18.2 | AX19: 30.7 | AY19: 35.6 | AZ19: 24 | BA19: 19.2 | BB19: 11.8 | BC19: 63.5 | BD19: 24.5 | BE19: 2.3 | BF19: 21.2 | BG19: 24.7 | BH19: 14.8 | BI19: 22.5 | BJ19: 29 | BK19: 0.5 | BL19: 9 | BM19: 9.6 | BN19: 8.1 | BO19: 48.3 | BP19: 35 | BQ19: 28.7
A20: 2006-07 | B20: 8475.2 | C20: 920.2 | D20: 2176.6 | E20: 2725 | F20: 2538.4 | G20: 111.5 | I20: 3.5 | J20: 1640.6 | K20: 292 | L20: 512.2 | M20: 307.2 | N20: 191 | O20: 389.4 | P20: 424.2 | Q20: 421.2 | R20: 137.5 | S20: 207.5 | T20: 88.4 | U20: 88.9 | V20: 146.4 | W20: 206.3 | X20: 223.8 | Y20: 113.5 | Z20: 122.2 | AA20: 35.4 | AB20: 178.6 | AC20: 22.2 | AD20: 125.4 | AE20: 149.3 | AF20: 22 | AG20: 39.6 | AH20: 34.1 | AI20: 64.1 | AJ20: 39 | AK20: 156.1 | AL20: 69.8 | AM20: 33.1 | AN20: 74.1 | AO20: 48.9 | AP20: 81.9 | AQ20: 37 | AR20: 51.5 | AS20: 77.8 | AT20: 27.2 | AU20: 43.2 | AV20: 67.3 | AW20: 29.9 | AX20: 45.9 | AY20: 32.5 | AZ20: 35.7 | BA20: 28.6 | BB20: 13.5 | BC20: 73.3 | BD20: 41.3 | BE20: 2 | BF20: 31.8 | BG20: 27.3 | BH20: 15.1 | BI20: 18.4 | BJ20: 24.4 | BK20: 1.5 | BL20: 9.3 | BM20: 5.8 | BN20: 12.8 | BO20: 51.4 | BP20: 40.2 | BQ20: 34.4
A21: 2007-08 | B21: 9743.6 | C21: 1140.5 | D21: 2418.3 | E21: 3108.6 | F21: 2951.2 | G21: 120.1 | I21: 4.7 | J21: 1655.8 | K21: 434.8 | L21: 632.7 | M21: 512.6 | N21: 224 | O21: 417.2 | P21: 485.1 | Q21: 412.3 | R21: 119.8 | S21: 251.6 | T21: 94.5 | U21: 98.2 | V21: 162 | W21: 196.6 | X21: 187.8 | Y21: 119.8 | Z21: 247.9 | AA21: 73.4 | AB21: 200.2 | AC21: 83.1 | AD21: 138.9 | AE21: 129.3 | AF21: 36.2 | AG21: 28 | AH21: 43.5 | AI21: 73.2 | AJ21: 97.3 | AK21: 154.6 | AL21: 71.8 | AM21: 33.1 | AN21: 71.3 | AO21: 55.5 | AP21: 69.7 | AQ21: 49.3 | AR21: 55.6 | AS21: 72.7 | AT21: 31.8 | AU21: 44.2 | AV21: 60.3 | AW21: 30.8 | AX21: 59.9 | AY21: 34.2 | AZ21: 75.6 | BA21: 49.5 | BB21: 12.8 | BC21: 73 | BD21: 50.5 | BE21: 4.5 | BF21: 23.7 | BG21: 25.7 | BH21: 19.1 | BI21: 22.5 | BJ21: 24.9 | BK21: 4 | BL21: 9.3 | BM21: 5.7 | BN21: 12.5 | BO21: 61.2 | BP21: 54.4 | BQ21: 78.6
A22: 2008-09 | B22: 9095.9 | C22: 1034.8 | D22: 2206.1 | E22: 2520.4 | F22: 3200.6 | G22: 127 | I22: 7.1 | J22: 1487.4 | K22: 412.7 | L22: 662.9 | M22: 293.2 | N22: 254 | O22: 370.8 | P22: 464.8 | Q22: 324.9 | R22: 148.7 | S22: 234.6 | T22: 104.5 | U22: 100.4 | V22: 129.4 | W22: 134.3 | X22: 150.6 | Y22: 100.1 | Z22: 250.3 | AA22: 53.6 | AB22: 170.7 | AC22: 46.1 | AD22: 111.4 | AE22: 120.7 | AF22: 42.4 | AG22: 33 | AH22: 53.6 | AI22: 60.4 | AJ22: 78.4 | AK22: 179.3 | AL22: 65.9 | AM22: 40.2 | AN22: 61.8 | AO22: 60.6 | AP22: 58.4 | AQ22: 60.7 | AR22: 50.7 | AS22: 59.8 | AT22: 33.7 | AU22: 40.5 | AV22: 51.5 | AW22: 32.8 | AX22: 55.4 | AY22: 33.8 | AZ22: 63.4 | BA22: 45.1 | BB22: 14.7 | BC22: 48 | BD22: 62.6 | BE22: 3.5 | BF22: 20.5 | BG22: 22.3 | BH22: 15.6 | BI22: 0 | BJ22: 23.7 | BK22: 5.5 | BL22: 10 | BM22: 10.3 | BN22: 17.3 | BO22: 43.9 | BP22: 50.3 | BQ22: 141.6
A23: 2009-10 | B23: 9151.9 | C23: 1081.8 | D23: 1987.6 | E23: 2311.6 | F23: 3660.1 | G23: 98.6 | I23: 12.1 | J23: 1212.9 | K23: 400.3 | L23: 639.3 | M23: 378.2 | N23: 276 | O23: 311.4 | P23: 416.4 | Q23: 265.3 | R23: 218.6 | S23: 207.9 | T23: 82.1 | U23: 86.6 | V23: 110.8 | W23: 109.3 | X23: 241 | Y23: 83.2 | Z23: 322.1 | AA23: 66.1 | AB23: 156.4 | AC23: 61.7 | AD23: 113.1 | AE23: 80.2 | AF23: 64.4 | AG23: 31.4 | AH23: 55.3 | AI23: 68.3 | AJ23: 89.9 | AK23: 152.8 | AL23: 62.9 | AM23: 41.1 | AN23: 74.1 | AO23: 72.6 | AP23: 60.9 | AQ23: 62.1 | AR23: 53.5 | AS23: 71 | AT23: 27.7 | AU23: 32.7 | AV23: 39.2 | AW23: 22.7 | AX23: 64.7 | AY23: 30.1 | AZ23: 77.1 | BA23: 34.5 | BB23: 21.6 | BC23: 41.1 | BD23: 60.6 | BE23: 3.3 | BF23: 33.9 | BG23: 21.4 | BH23: 12 | BI23: 0.4 | BJ23: 25.5 | BK23: 8.2 | BL23: 10.8 | BM23: 23.9 | BN23: 20.3 | BO23: 37.8 | BP23: 53.1 | BQ23: 227.5
A24: 2010-11 | B24: 12621.1 | C24: 1392 | D24: 2947.7 | E24: 3117.8 | F24: 5014.8 | G24: 130.3 | I24: 18.6 | J24: 1749.9 | K24: 786.1 | L24: 764 | M24: 572.6 | N24: 376 | O24: 385.2 | P24: 525.1 | Q24: 364.9 | R24: 443.8 | S24: 334.6 | T24: 108.6 | U24: 129.1 | V24: 115.6 | W24: 170.2 | X24: 347 | Y24: 100.7 | Z24: 472.2 | AA24: 63.6 | AB24: 206 | AC24: 66.1 | AD24: 200.4 | AE24: 138.1 | AF24: 97.8 | AG24: 55.1 | AH24: 92 | AI24: 98 | AJ24: 135.2 | AK24: 192.2 | AL24: 116.3 | AM24: 59.1 | AN24: 96.3 | AO24: 123 | AP24: 66.1 | AQ24: 64.8 | AR24: 94 | AS24: 190.4 | AT24: 53.4 | AU24: 37.3 | AV24: 46.4 | AW24: 32.9 | AX24: 90.4 | AY24: 38.4 | AZ24: 65.6 | BA24: 62 | BB24: 34.9 | BC24: 66.3 | BD24: 64.7 | BE24: 6 | BF24: 40.9 | BG24: 33 | BH24: 16.3 | BI24: 0.3 | BJ24: 24.2 | BK24: 9.4 | BL24: 11.2 | BM24: 12.9 | BN24: 23.7 | BO24: 29.5 | BP24: 39.5 | BQ24: 183.4
A25: 2011-12 | B25: 14327.3 | C25: 1977.2 | D25: 3448.6 | E25: 3465.7 | F25: 5257.7 | G25: 173.8 | I25: 4.3 | J25: 2086 | K25: 810.5 | L25: 746.7 | M25: 616.6 | N25: 418.3 | O25: 469 | P25: 595.3 | Q25: 402.8 | R25: 726.9 | S25: 559 | T25: 148 | U25: 151.8 | V25: 148.2 | W25: 184.9 | X25: 261.8 | Y25: 145.3 | Z25: 404.7 | AA25: 65.4 | AB25: 219.1 | AC25: 77.8 | AD25: 178 | AE25: 161.3 | AF25: 119.1 | AG25: 82.2 | AH25: 115.8 | AI25: 123.6 | AJ25: 179.4 | AK25: 233 | AL25: 138 | AM25: 120.3 | AN25: 113.7 | AO25: 178.6 | AP25: 64.7 | AQ25: 81.5 | AR25: 97.7 | AS25: 145.4 | AT25: 62.7 | AU25: 44.5 | AV25: 63.1 | AW25: 48.9 | AX25: 158.3 | AY25: 43.8 | AZ25: 85.8 | BA25: 68.6 | BB25: 38.5 | BC25: 60.7 | BD25: 75.3 | BE25: 12.3 | BF25: 34.8 | BG25: 37.7 | BH25: 19.4 | BI25: 0 | BJ25: 35.2 | BK25: 11.2 | BL25: 20 | BM25: 25.3 | BN25: 27.3 | BO25: 24 | BP25: 30.5 | BQ25: 136.7
A26: 2012-13 | B26: 14424 | C26: 1592 | D26: 3607.5 | E26: 3189.1 | F26: 5860 | G26: 172.6 | I26: 2.7 | J26: 2296.2 | K26: 1103.5 | L26: 640.2 | M26: 601.6 | N26: 395.8 | O26: 490 | P26: 497.4 | Q26: 309.7 | R26: 1291.6 | S26: 401.2 | T26: 146.6 | U26: 135.1 | V26: 129.9 | W26: 157.2 | X26: 244.9 | Y26: 139.4 | Z26: 384.3 | AA26: 77.6 | AB26: 183.3 | AC26: 77.2 | AD26: 190 | AE26: 138.2 | AF26: 125.7 | AG26: 77.2 | AH26: 114.3 | AI26: 117.8 | AJ26: 174.1 | AK26: 188.8 | AL26: 166 | AM26: 139.3 | AN26: 102.8 | AO26: 159.5 | AP26: 51.3 | AQ26: 70.6 | AR26: 88.4 | AS26: 144 | AT26: 68.6 | AU26: 59.6 | AV26: 55.9 | AW26: 46.1 | AX26: 111.7 | AY26: 41.5 | AZ26: 50.4 | BA26: 72.4 | BB26: 52.3 | BC26: 55.5 | BD26: 46.5 | BE26: 15 | BF26: 48.8 | BG26: 35.9 | BH26: 19.4 | BI26: 6.1 | BJ26: 33.8 | BK26: 17.8 | BL26: 27.3 | BM26: 21.9 | BN26: 25.8 | BO26: 19.2 | BP26: 54.7 | BQ26: 148.2
A27: 2013-14 | B27: 17993.8 | C27: 1853.1 | D27: 4417.5 | E27: 3921 | F27: 7484.3 | G27: 225.7 | H27: 0 | I27: 92.2 | J27: 3032.6 | K27: 1188.2 | L27: 862 | M27: 730.8 | N27: 501.1 | O27: 576.2 | P27: 583.6 | Q27: 387.5 | R27: 2099.8 | S27: 390.8 | T27: 187.9 | U27: 181 | V27: 187.7 | W27: 206 | X27: 279.3 | Y27: 193.2 | Z27: 397.6 | AA27: 79.5 | AB27: 212 | AC27: 87.2 | AD27: 213.1 | AE27: 179.2 | AF27: 211.2 | AG27: 101.7 | AH27: 108.1 | AI27: 121.9 | AJ27: 186.6 | AK27: 128.5 | AL27: 145.4 | AM27: 130.7 | AN27: 115.2 | AO27: 164.9 | AP27: 76.5 | AQ27: 90.6 | AR27: 117.3 | AS27: 158.1 | AT27: 71.7 | AU27: 63.7 | AV27: 70.9 | AW27: 58 | AX27: 154.5 | AY27: 57.9 | AZ27: 76.9 | BA27: 70.5 | BB27: 41.6 | BC27: 66.6 | BD27: 44.8 | BE27: 22.1 | BF27: 50 | BG27: 48.4 | BH27: 29.3 | BI27: 12.8 | BJ27: 37 | BK27: 46.3 | BL27: 41.3 | BM27: 21.3 | BN27: 22.6 | BO27: 23.2 | BP27: 67.3 | BQ27: 204.1
A28: 2014-15 | B28: 18020.4 | C28: 1872 | D28: 4720.6 | E28: 3838.4 | F28: 7344.5 | G28: 244.4 | I28: 0.5 | J28: 3361.5 | K28: 1338.9 | L28: 1046.4 | M28: 630 | N28: 490.3 | O28: 598.4 | P28: 566.9 | Q28: 383.2 | R28: 1772 | S28: 418.3 | T28: 201 | U28: 195 | V28: 193.5 | W28: 216.2 | X28: 314.2 | Y28: 193.1 | Z28: 309.3 | AA28: 86.5 | AB28: 230.1 | AC28: 96.2 | AD28: 185.5 | AE28: 185.2 | AF28: 295.1 | AG28: 108.6 | AH28: 125.9 | AI28: 85.9 | AJ28: 196.6 | AK28: 115.4 | AL28: 137 | AM28: 93.1 | AN28: 102.8 | AO28: 172.3 | AP28: 77.9 | AQ28: 90.7 | AR28: 108.8 | AS28: 131.7 | AT28: 69.9 | AU28: 77.6 | AV28: 85.7 | AW28: 52.4 | AX28: 151.9 | AY28: 65.2 | AZ28: 68 | BA28: 55.5 | BB28: 53.3 | BC28: 59.7 | BD28: 58.9 | BE28: 20.1 | BF28: 48.2 | BG28: 49.7 | BH28: 35.1 | BI28: 21.3 | BJ28: 43.7 | BK28: 49.9 | BL28: 26.9 | BM28: 23.6 | BN28: 12.8 | BO28: 24.7 | BP28: 59.7 | BQ28: 166
A29: 2015-16 | B29: 16656.9 | C29: 1641.1 | D29: 4495.2 | E29: 3467.4 | F29: 6807.8 | G29: 245.1 | I29: 0.3 | J29: 3404.2 | K29: 1344 | L29: 888.8 | M29: 541.5 | N29: 485.2 | O29: 564.4 | P29: 537.1 | Q29: 353.7 | R29: 1683.5 | S29: 348.8 | T29: 205.6 | U29: 173.4 | V29: 180.5 | W29: 209.6 | X29: 300.1 | Y29: 186.2 | Z29: 174 | AA29: 82.3 | AB29: 188.8 | AC29: 105 | AD29: 177.2 | AE29: 167 | AF29: 190.5 | AG29: 102.6 | AH29: 135.3 | AI29: 82.2 | AJ29: 152.6 | AK29: 105.9 | AL29: 123.6 | AM29: 103.5 | AN29: 104.9 | AO29: 139.7 | AP29: 77.3 | AQ29: 81.4 | AR29: 101.4 | AS29: 116.2 | AT29: 71 | AU29: 72.1 | AV29: 71.2 | AW29: 58.6 | AX29: 127.6 | AY29: 60.3 | AZ29: 68.4 | BA29: 64.3 | BB29: 46.4 | BC29: 57.9 | BD29: 45.4 | BE29: 19.6 | BF29: 36.9 | BG29: 38.3 | BH29: 31.3 | BI29: 19.3 | BJ29: 41.1 | BK29: 57.2 | BL29: 22.8 | BM29: 29.5 | BN29: 15.6 | BO29: 24.6 | BP29: 44.6 | BQ29: 116.8
A30: 2016-17 | B30: 16402 | C30: 1477 | D30: 4704.6 | E30: 3603.9 | F30: 6358.8 | G30: 256.8 | I30: 0.9 | J30: 3471.4 | K30: 1373.8 | L30: 683.7 | M30: 540.8 | N30: 495.4 | O30: 523.9 | P30: 566.3 | Q30: 373.6 | R30: 1303.1 | S30: 290.5 | T30: 213.9 | U30: 221.5 | V30: 188 | W30: 215.7 | X30: 317.8 | Y30: 202.7 | Z30: 313.7 | AA30: 104.7 | AB30: 186.4 | AC30: 110.9 | AD30: 194 | AE30: 165.8 | AF30: 198.9 | AG30: 74 | AH30: 128.4 | AI30: 85.8 | AJ30: 160.9 | AK30: 109.8 | AL30: 128.3 | AM30: 119.9 | AN30: 97.6 | AO30: 146.4 | AP30: 88.1 | AQ30: 79.7 | AR30: 115.7 | AS30: 105.6 | AT30: 70.7 | AU30: 84.8 | AV30: 76.7 | AW30: 54 | AX30: 91.2 | AY30: 59.2 | AZ30: 51 | BA30: 51.1 | BB30: 44.2 | BC30: 58 | BD30: 45.4 | BE30: 22.7 | BF30: 43.9 | BG30: 39.7 | BH30: 33.2 | BI30: 14.9 | BJ30: 38.7 | BK30: 51.4 | BL30: 19.8 | BM30: 20.9 | BN30: 15.4 | BO30: 26.6 | BP30: 56.6 | BQ30: 89.7
A31: 2017-18 | B31: 17078.4 | C31: 1653.8 | D31: 4971.8 | E31: 3918.4 | F31: 6252.8 | G31: 281.3 | H31: 0.1 | I31: 0 | J31: 3563.4 | K31: 1519.4 | L31: 498.7 | M31: 708.2 | N31: 496.6 | O31: 523.3 | P31: 578.1 | Q31: 409.2 | R31: 1144.7 | S31: 352.4 | T31: 227.1 | U31: 198.5 | V31: 206.3 | W31: 236.1 | X31: 329 | Y31: 204 | Z31: 403.7 | AA31: 123.1 | AB31: 195.2 | AC31: 134.2 | AD31: 222.3 | AE31: 171 | AF31: 212.8 | AG31: 88.9 | AH31: 131.4 | AI31: 98.7 | AJ31: 198.7 | AK31: 136.2 | AL31: 130.6 | AM31: 130.5 | AN31: 99.7 | AO31: 134.8 | AP31: 85.1 | AQ31: 77.9 | AR31: 117.5 | AS31: 92.4 | AT31: 88.2 | AU31: 89 | AV31: 88.3 | AW31: 54.4 | AX31: 78.1 | AY31: 70.4 | AZ31: 35.5 | BA31: 64.2 | BB31: 54 | BC31: 69.7 | BD31: 51.7 | BE31: 34.9 | BF31: 45.5 | BG31: 47.6 | BH31: 45.5 | BI31: 18.2 | BJ31: 40.4 | BK31: 62.7 | BL31: 21.5 | BM31: 32.1 | BN31: 14.1 | BO31: 28.1 | BP31: 57.6 | BQ31: 101
A32: 2018-19 | B32: 18286.7 | C32: 1814.5 | D32: 5405.5 | E32: 3794 | F32: 6968.6 | G32: 302.1 | I32: 2 | J32: 3923.7 | K32: 1630.9 | L32: 446.5 | M32: 568.3 | N32: 545.4 | O32: 570 | P32: 526.6 | Q32: 401 | R32: 1565.6 | S32: 400.4 | T32: 234.4 | U32: 219 | V32: 210.5 | W32: 250.5 | X32: 388.4 | Y32: 209.5 | Z32: 368.2 | AA32: 126.7 | AB32: 192.3 | AC32: 189.7 | AD32: 209.5 | AE32: 190.5 | AF32: 273.7 | AG32: 80.7 | AH32: 160.3 | AI32: 106.6 | AJ32: 206.8 | AK32: 116 | AL32: 166.8 | AM32: 193.9 | AN32: 108.3 | AO32: 171.1 | AP32: 94.8 | AQ32: 79.7 | AR32: 114.8 | AS32: 109.7 | AT32: 109.7 | AU32: 68.5 | AV32: 81.1 | AW32: 59.8 | AX32: 93.9 | AY32: 79.2 | AZ32: 37.4 | BA32: 45.6 | BB32: 66.2 | BC32: 65.1 | BD32: 58.6 | BE32: 52.5 | BF32: 59.2 | BG32: 52.8 | BH32: 57.4 | BI32: 22.8 | BJ32: 42.9 | BK32: 62.7 | BL32: 25.3 | BM32: 28.6 | BN32: 14.1 | BO32: 25.8 | BP32: 57.2 | BQ32: 93.1
A33: 2019-20 | B33: 16836.5 | C33: 1873.6 | D33: 5135.3 | E33: 3493.1 | F33: 6049.6 | G33: 284.7 | I33: 0.2 | J33: 3820.7 | K33: 1492.1 | L33: 480 | M33: 571.8 | N33: 569.1 | O33: 527.9 | P33: 481.9 | Q33: 321.6 | R33: 822.9 | S33: 378.8 | T33: 220.6 | U33: 220.3 | V33: 215.5 | W33: 202.6 | X33: 321.4 | Y33: 210.6 | Z33: 293.6 | AA33: 135.6 | AB33: 168.1 | AC33: 175.8 | AD33: 207.5 | AE33: 173.4 | AF33: 233.8 | AG33: 121.1 | AH33: 135.9 | AI33: 101.9 | AJ33: 195.8 | AK33: 151.1 | AL33: 155.4 | AM33: 178.3 | AN33: 105.6 | AO33: 156.5 | AP33: 97 | AQ33: 84 | AR33: 96.4 | AS33: 108.6 | AT33: 101.5 | AU33: 111.7 | AV33: 77.7 | AW33: 60.7 | AX33: 92.2 | AY33: 76.3 | AZ33: 32.1 | BA33: 60.8 | BB33: 47.9 | BC33: 57.3 | BD33: 42.9 | BE33: 59.9 | BF33: 44.4 | BG33: 47.4 | BH33: 54.7 | BI33: 16.3 | BJ33: 40.2 | BK33: 62.9 | BL33: 30.6 | BM33: 33.6 | BN33: 16 | BO33: 25.7 | BP33: 51.6 | BQ33: 314.9
A34: 2020-21 | B34: 15872.5 | C34: 1622.7 | D34: 5635.4 | E34: 3227.2 | F34: 5044.8 | G34: 342.3 | I34: 0 | J34: 4423.8 | K34: 1301 | L34: 452.5 | M34: 417 | N34: 502.8 | O34: 477.1 | P34: 460.9 | Q34: 271.4 | R34: 897.6 | S34: 276.8 | T34: 279.1 | U34: 247.3 | V34: 239.2 | W34: 181.1 | X34: 310.2 | Y34: 227.2 | Z34: 234.9 | AA34: 111.9 | AB34: 156.7 | AC34: 185.5 | AD34: 174 | AE34: 133.8 | AF34: 238.7 | AG34: 141.4 | AH34: 93.9 | AI34: 79.6 | AJ34: 201.5 | AK34: 91.8 | AL34: 79.5 | AM34: 109 | AN34: 88.5 | AO34: 135.8 | AP34: 107 | AQ34: 64.6 | AR34: 102.6 | AS34: 81.9 | AT34: 92.2 | AU34: 95.3 | AV34: 90 | AW34: 81.4 | AX34: 81.6 | AY34: 84 | AZ34: 15 | BA34: 75.7 | BB34: 55.7 | BC34: 52.4 | BD34: 43.2 | BE34: 52.1 | BF34: 20.6 | BG34: 52.9 | BH34: 54.5 | BI34: 13.1 | BJ34: 29.5 | BK34: 45.9 | BL34: 22.6 | BM34: 38.8 | BN34: 17.4 | BO34: 24.9 | BP34: 56.9 | BQ34: 101.9
A35: 2021-22 | B35: 23790.6 | C35: 2390.2 | D35: 7692.4 | E35: 4951.6 | F35: 8366 | G35: 390.4 | I35: 0 | J35: 5709.1 | K35: 3496.1 | L35: 619.5 | M35: 895.7 | N35: 780 | O35: 621.7 | P35: 567.3 | Q35: 440.8 | R35: 1086.1 | S35: 543.9 | T35: 312.9 | U35: 330.7 | V35: 332.9 | W35: 332.6 | X35: 414.1 | Y35: 301.8 | Z35: 336.7 | AA35: 185.9 | AB35: 253.8 | AC35: 260.2 | AD35: 353.7 | AE35: 183.9 | AF35: 288.6 | AG35: 198.2 | AH35: 181.4 | AI35: 173.3 | AJ35: 265.1 | AK35: 115.2 | AL35: 129.2 | AM35: 132.2 | AN35: 127.9 | AO35: 245.6 | AP35: 142.3 | AQ35: 138.8 | AR35: 145.5 | AS35: 111.4 | AT35: 133.4 | AU35: 84.9 | AV35: 126.7 | AW35: 87.2 | AX35: 99.3 | AY35: 105.5 | AZ35: 42.1 | BA35: 121.1 | BB35: 146.8 | BC35: 68.3 | BD35: 66.2 | BE35: 53.5 | BF35: 42.4 | BG35: 61.7 | BH35: 66.8 | BI35: 31.7 | BJ35: 43.3 | BK35: 55.9 | BL35: 48 | BM35: 39.9 | BN35: 43.4 | BO35: 37.8 | BP35: 77.5 | BQ35: 58.6
A36: 2022-23 | B36: 18136.1 | C36: 2152.7 | D36: 5825.7 | E36: 4061.6 | F36: 5709.9 | G36: 386.3 | I36: 0.1 | J36: 4487.9 | K36: 1944.3 | L36: 682.4 | M36: 676.5 | N36: 669.6 | O36: 534 | P36: 509.9 | Q36: 450.6 | R36: 405.5 | S36: 324.6 | T36: 316.1 | U36: 287.7 | V36: 286.4 | W36: 271.2 | X36: 257.8 | Y36: 253.4 | Z36: 215.3 | AA36: 212.6 | AB36: 202.9 | AC36: 200.3 | AD36: 189.7 | AE36: 182.2 | AF36: 180.7 | AG36: 174.2 | AH36: 161.6 | AI36: 161.1 | AJ36: 154.9 | AK36: 143.1 | AL36: 139.6 | AM36: 137.2 | AN36: 133.9 | AO36: 129.2 | AP36: 126.8 | AQ36: 125.5 | AR36: 113.7 | AS36: 111.9 | AT36: 98.9 | AU36: 98.8 | AV36: 94.2 | AW36: 84.5 | AX36: 79.3 | AY36: 79 | AZ36: 77.7 | BA36: 75.3 | BB36: 67.3 | BC36: 66.1 | BD36: 60.8 | BE36: 59.7 | BF36: 56.9 | BG36: 56.4 | BH36: 56 | BI36: 54.8 | BJ36: 53.3 | BK36: 46.7 | BL36: 46.6 | BM36: 45 | BN36: 43.6 | BO36: 42.1 | BP36: 42 | BQ36: 38.9
A40: Year | B40: World | C40: Africa | D40: America | E40: Europe | F40: Asia | G40: Oceania
A41: 2020-21 | B41: 15872.5 | C41: 1622.7 | D41: 5635.4 | E41: 3227.2 | F41: 5044.8 | G41: 342.3
A42: 2021-22 | B42: 23790.6 | C42: 2390.2 | D42: 7692.4 | E42: 4951.6 | F42: 8366 | G42: 390.4
A43: 2022-23 | B43: 18136.1 | C43: 2152.7 | D43: 5825.7 | E43: 4061.6 | F43: 5709.9 | G43: 386.3

Sheet Trade Balance
A1: Quarter ended | B1: Trade Balance | C1: Exports | D1: Imports
A2: 39965 | B2: -24016.7 | C2: 38468.5 | D2: 62485.2
A3: 40057 | B3: -23143.5 | C3: 42551 | D3: 65694.5 | I3: 44986 | J3: 45352 | K3: Export Y-o-Y % change
A4: 40148 | B4: -32952.4 | C4: 46230.7 | D4: 79183.1 | H4: Cotton yarn/fabrics/made-ups, handloom products etc | I4: 1024.1 | J4: 1093.9 | K4: 6.82
A5: 40238 | B5: -29503.2 | C5: 51535.6 | D5: 81038.8 | H5: Man-made yarn/fabrics/made-ups etc. | I5: 476.7 | J5: 439.4 | K5: -7.83
A6: 40330 | B6: -29345.9 | C6: 54093 | D6: 83438.9 | H6: RMG of all textiles | I6: 1447.9 | J6: 1472.9 | K6: 1.73
A7: 40422 | B7: -35200.1 | C7: 51102.9 | D7: 86303 | H7: Jute manufacturing including floor covering | I7: 37.5 | J7: 28.4 | K7: -24.1
A8: 40513 | B8: -26965.2 | C8: 65835.1 | D8: 92800.2 | H8: Carpet | I8: 110.9 | J8: 129 | K8: 16.27
A9: 40603 | B9: -24281.2 | C9: 76313.6 | D9: 100594.8
A10: 40695 | B10: -46220.2 | C10: 76506.1 | D10: 122726.3
A11: 40787 | B11: -43040.1 | C11: 77807.7 | D11: 120847.8
A12: 40878 | B12: -47883.6 | C12: 72214.5 | D12: 120098.1
A13: 40969 | B13: -46062.4 | C13: 79366.1 | D13: 125428.5
A14: 41061 | B14: -41780 | C14: 73346.1 | D14: 115126
A15: 41153 | B15: -48807.7 | C15: 71090.8 | D15: 119898.5
A16: 41244 | B16: -54957.3 | C16: 72757.8 | D16: 127715.1
A17: 41334 | B17: -43502.2 | C17: 82992.4 | D17: 126494.6
A18: 41426 | B18: -47457.6 | C18: 72281.4 | D18: 119738.9
A19: 41518 | B19: -29173.8 | C19: 80521.8 | D19: 109695.5
A20: 41609 | B20: -30355.6 | C20: 78075.8 | D20: 108431.4
... A61: 45352 | B61: -50345.6 | C61: 120379.5 | D61: 170725

Sheet WPI-Textiles
A1: Wholesale Price Index (WPI): Item-level Indices: Manufacture of Textiles: Base Year: 2011-12
C2: Total | D2: Total | E2: Total | F2: Total | G2: total
A3: Weight | B3: 4.88068 | C3: 2.58154 | D3: 1.50903 | E3: 0.19296 | F3: 0.09776 | G3: 0.20089
A4: Y-o-Y % change : April 2019 to March 2024
A5: Month | B5: WPI (Textiles) Inflation Total | C5: Preparation and spinning of textile fibres | D5: Weaving & finishing of textiles | E5: Manufacture of knitted and crocheted fabrics | F5: Manufacture of cordage, rope, twine and netting | G5: Manufacture of other textiles | H5: WPI (Apparel) Total | I5: Manufacture of wearing apparel (woven), except fur apparel | J5: Manufacture of knitted and crocheted apparel
A6: 43556 | B6: 3.92 | C6: 4.1 | D6: 4.49 | E6: 0.72 | F6: 2.05 | G6: -2.36 | H6: -1.07 | I6: -0.43 | J6: -2.87
A7: 43586 | B7: 3.37 | C7: 2.4 | D7: 4.47 | E7: 2.42 | F7: 1.82 | G7: 0.6 | H7: -1.07 | I7: -0.21 | J7: -3.3
A8: 43617 | B8: 2.75 | C8: 1.56 | D8: 4.31 | E8: 2.5 | F8: 1.31 | G8: 0.51 | H8: -1.22 | I8: -0.85 | J8: -2.25
A9: 43647 | B9: 1.02 | C9: -0.27 | D9: 2.76 | E9: 1.05 | F9: 1.16 | G9: -0.94 | H9: -0.65 | I9: -0.79 | J9: -0.29
A10: 43678 | B10: -0.17 | C10: -2.15 | D10: 2.05 | E10: 0.35 | F10: 2.03 | G10: -1.19 | H10: -0.86 | I10: -0.86 | J10: -0.95
A11: 43709 | B11: -0.84 | C11: -4.09 | D11: 2.22 | E11: 2.11 | F11: 1.57 | G11: -0.25 | H11: 0.51 | I11: 0.36 | J11: 0.74
A12: 43739 | B12: -1.59 | C12: -4.62 | D12: 1.17 | E12: 1.41 | F12: 1.63 | G12: -2.16 | H12: 0 | I12: -0.29 | J12: 0.44
A13: 43770 | B13: -2.1 | C13: -6.07 | D13: 1.64 | E13: 0.79 | F13: 2.31 | G13: -2 | H13: 0.14 | I13: 0.65 | J13: -1.09
A14: 43800 | B14: -2.44 | C14: -5.23 | D14: 0.7 | E14: 0.88 | F14: 4.59 | G14: -3.73 | H14: 0.36 | I14: 0.65 | J14: -0.36
A15: 43831 | B15: -2.18 | C15: -5.21 | D15: 1.09 | E15: 1.86 | F15: 4.99 | G15: -2.76 | H15: -0.36 | I15: -0.5 | J15: 0
A16: 43862 | B16: -1.93 | C16: -4.86 | D16: 0.93 | E16: 1.34 | F16: 6.03 | G16: -1.1 | H16: 0.44 | I16: 0.36 | J16: 0.52
A17: 43891 | B17: -1.6 | C17: -4.35 | D17: 0.85 | E17: 2.44 | F17: 9 | G17: 1.03 | H17: 0.07 | I17: 0.07 | J17: 0.15
... A65: 45352 | B65: -1.68 | C65: -2.36 | D65: -1.88 | E65: -2.19 | F65: -5.17 | G65: 2.58 | H65: 0.87 | I65: 0.13 | J65: 2.59
A66: Cumulative | B66: Apr-Mar | C66: Apr-Mar | D66: Apr-Mar | E66: Apr-Mar | F66: Apr-Mar | G66: Apr-Mar
A67: 2019-20 | B67: -0.18 | C67: -2.44 | D67: 2.21 | E67: 1.48 | F67: 3.2 | G67: -1.21
A68: 2020-21 | B68: -0.1 | C68: -1.24 | D68: 1.2 | E68: 0.54 | F68: 8.74 | G68: -0.42
A69: 2021-22 | B69: 14.94 | C69: 20.25 | D69: 11.48 | E69: 9.01 | F69: 8.26 | G69: 8.5
A70: 2022-23 | B70: 5.55 | C70: 3.91 | D70: 8.29 | E70: 3.51 | F70: -6.91 | G70: 4.74
A71: 2023-24 | B71: -5.63 | C71: -9.81 | D71: -0.84 | E71: -7.67 | F71: -11.36 | G71: -2.21

Sheet Inflation-Clothing
A1: Consumer Price Index (CPI): Combined (Urban + Rural): Item-level Indices : Clothing and Footwear: Base Year 2012
C2: Total | D2: Dhoti (no.) | E2: Saree (no.) | F2: Shawl, chaddar (no.) | G2: Lungi (no.) | H2: Kurta-pajama suits males (no.) | I2: Shirts, T-shirts (no.) | J2: Shorts, trousers, bermudas (no.) | K2: Baniyan, socks, other hosiery and undergarments, etc.(no.) | L2: Kurta-pajama suits females (no.) | M2: Frocks, skirts, etc. (no.) | N2: School / college uniform boys | O2: School / college uniform girls | P2: Coat, jacket, sweater, windcheater (no.) | Q2: Knitting wool (gm) | R2: Cloth for shirt, pyjama, kurta, salwar, etc. (metre) | S2: Cloth for coat, trousers, suit, etc. (metre) | T2: Clothing (first- hand) | U2: Clothing second-hand | V2: Gamchha, towel, handkerchief (no.) | W2: Headwear, belts, ties (no.) | X2: Washerman, laundry, ironing | Y2: Tailor | Z2: Total | AA2: Leather boots, shoes | AB2: Leather sandals, chappals, etc. | AC2: Other leather footwear | AD2: Rubber / PVC footwear | AE2: Other footwear
A3: Weight | B3: 6.53 | C3: 5.58 | D3: 0.07465 | E3: 0.89661 | F3: 0.0823 | G3: 0.11463 | H3: 0.0553 | I3: 0.56646 | J3: 0.55365 | K3: 0.49077 | L3: 0.22295 | M3: 0.15122 | N3: 0.1697 | O3: 0.1353 | P3: 0.19627 | Q3: 0.00029 | R3: 0.67661 | S3: 0.42346 | T3: 0.05151 | U3: 0.01268 | V3: 0.17775 | W3: 0.01145 | X3: 0.12458 | Y3: 0.38901 | Z3: 0.95 | AA3: 0.20891 | AB3: 0.18209 | AC3: 0.07541 | AD3: 0.31248 | AE3: 0.17108
A4: Y-o-Y % change : April 2019 to March 2024
A5: Month | B5: Total | C5: Clothing | D5: Clothing | E5: Clothing | F5: Clothing | G5: Clothing | H5: Clothing | I5: Clothing | J5: Clothing | K5: Clothing | L5: Clothing | M5: Clothing | N5: Clothing | O5: Clothing | P5: Clothing | Q5: Clothing | R5: Clothing | S5: Clothing | T5: Clothing | U5: Clothing | V5: Clothing | W5: Clothing | X5: Clothing | Y5: Clothing | Z5: Footwear | AA5: Footwear | AB5: Footwear | AC5: Footwear | AD5: Footwear | AE5: Footwear
A6: 43556 | B6: 2.01 | C6: 1.93 | D6: 1.21 | E6: 2.27 | F6: 2.2 | G6: -2.54 | H6: 2.98 | I6: 0.95 | J6: 4.47 | K6: -1.47 | L6: 2.19 | M6: 2.75 | N6: 0.56 | O6: 0.98 | P6: 1.44 | Q6: 6.41 | R6: 1.84 | S6: 4.9 | T6: 5.16 | U6: 11.36 | V6: -0.28 | W6: 11.56 | X6: 3.88 | Y6: 1.87 | Z6: 2.49 | AA6: 3.31 | AB6: 1.9 | AC6: 7.99 | AD6: -0.14 | AE6: 4.71
A7: 43586 | B7: 1.8 | C7: 1.64 | D7: 0.8 | E7: 1.7 | F7: 1.44 | G7: -2.81 | H7: 2.54 | I7: 0.68 | J7: 4.4 | K7: -1.74 | L7: 2.04 | M7: 2.94 | N7: -0.34 | O7: 0.28 | P7: 3.9 | Q7: 11.88 | R7: 1.76 | S7: 4.45 | T7: 4.55 | U7: 8.38 | V7: -0.9 | W7: 8.84 | X7: 3.12 | Y7: 1.98 | Z7: 2.18 | AA7: 2.86 | AB7: 1.45 | AC7: 8.1 | AD7: -0.42 | AE7: 4.46
A8: 43617 | B8: 1.52 | C8: 1.5 | D8: 0.94 | E8: 1.49 | F8: 1.09 | G8: -3.47 | H8: 2.32 | I8: 0.47 | J8: 3.87 | K8: -1.6 | L8: 1.62 | M8: 2.47 | N8: -0.55 | O8: -0.21 | P8: 4.88 | Q8: 11.6 | R8: 1.69 | S8: 4.08 | T8: 4.69 | U8: 7.35 | V8: -0.76 | W8: 7.95 | X8: 3.17 | Y8: 1.67 | Z8: 1.67 | AA8: 2.55 | AB8: 1.16 | AC8: 6.98 | AD8: -0.98 | AE8: 3.91
A9: 43647 | B9: 1.37 | C9: 1.43 | D9: 1 | E9: 1.69 | F9: 1.36 | G9: -3.34 | H9: 2.61 | I9: 0.47 | J9: 4.25 | K9: -1.6 | L9: 1.33 | M9: 2.27 | N9: -1.16 | O9: -0.96 | P9: 3.64 | Q9: 8.7 | R9: 1.35 | S9: 3.78 | T9: 4.15 | U9: 4.86 | V9: -1.03 | W9: 9.58 | X9: 3.22 | Y9: 1.43 | Z9: 1.52 | AA9: 2.1 | AB9: 0.72 | AC9: 7.05 | AD9: -0.98 | AE9: 4.14
A10: 43678 | B10: 1.23 | C10: 1.22 | D10: 0.33 | E10: 1.42 | F10: 1.29 | G10: -4.37 | H10: 3.18 | I10: 0.2 | J10: 4.01 | K10: -1.93 | L10: 0.91 | M10: 1.87 | N10: -1.49 | O10: -1.3 | P10: 6.72 | Q10: 10.54 | R10: 0.94 | S10: 3.34 | T10: 3.4 | U10: 6.5 | V10: -1.3 | W10: 8.64 | X10: 3.08 | Y10: 1.3 | Z10: 1.3 | AA10: 1.59 | AB10: 0.36 | AC10: 6.14 | AD10: -0.91 | AE10: 3.9
A11: 43709 | B11: 0.96 | C11: 1.02 | D11: 0.07 | E11: 1.55 | F11: 1.35 | G11: -4.12 | H11: 2.89 | I11: 0.34 | J11: 4.08 | K11: -1.72 | L11: 1.4 | M11: 2.06 | N11: -1.02 | O11: -0.82 | P11: 0.57 | Q11: 11.71 | R11: 0.67 | S11: 2.55 | T11: 3.93 | U11: 8.48 | V11: -1.7 | W11: 8.4 | X11: 3.37 | Y11: 1.24 | Z11: 1.08 | AA11: 1.23 | AB11: 0 | AC11: 5.92 | AD11: -1.19 | AE11: 4.36
A12: 43739 | B12: 1.65 | C12: 1.56 | D12: -0.26 | E12: 2.09 | F12: 2.23 | G12: -2 | H12: 1.04 | I12: 1.36 | J12: 3.15 | K12: 0.35 | L12: 1.82 | M12: 1.67 | N12: 0.07 | O12: 1.19 | P12: 1.65 | Q12: 6.45 | R12: 1.42 | S12: 1.4 | T12: 5.19 | U12: 7.91 | V12: -0.55 | W12: 5.87 | X12: 3.67 | Y12: 2.32 | Z12: 1.73 | AA12: 1.66 | AB12: 0.79 | AC12: 5 | AD12: -0.07 | AE12: 4.66
A13: 43770 | B13: 1.3 | C13: 1.28 | D13: -0.2 | E13: 2.57 | F13: 0.53 | G13: -0.9 | H13: -4.4 | I13: 1.97 | J13: 2.76 | K13: 1.85 | L13: 0.48 | M13: 0.7 | N13: -0.68 | O13: -0.14 | P13: -0.28 | Q13: -2.79 | R13: 1 | S13: -0.96 | T13: 2.2 | U13: 10.62 | V13: 0.48 | W13: -1.19 | X13: 2.55 | Y13: 1.83 | Z13: 1.37 | AA13: 0.93 | AB13: 0.14 | AC13: 3.46 | AD13: 0.71 | AE13: 3.47
A14: 43800 | B14: 1.5 | C14: 1.49 | D14: -0.26 | E14: 2.98 | F14: 0.53 | G14: -0.42 | H14: -4.14 | I14: 2.18 | J14: 2.53 | K14: 2.35 | L14: 0.97 | M14: 0.38 | N14: -1.16 | O14: -0.21 | P14: 0.41 | Q14: -3.93 | R14: 1.54 | S14: -1.36 | T14: 0.84 | U14: 0.52 | V14: 0.48 | W14: -0.54 | X14: 3.52 | Y14: 2.43 | Z14: 1.36 | AA14: 1.36 | AB14: 0.5 | AC14: 4.31 | AD14: 1.14 | AE14: 1.48
A15: 43831 | B15: 1.91 | C15: 1.96 | D15: 1.2 | E15: 3.53 | F15: 1.26 | G15: 0.35 | H15: -3.12 | I15: 2.39 | J15: 2.67 | K15: 3.15 | L15: 0.97 | M15: 1.08 | N15: -1.09 | O15: -0.55 | P15: 0.83 | Q15: 4.29 | R15: 2.02 | S15: -0.82 | T15: 1.27 | U15: 0 | V15: 0.97 | W15: -1.83 | X15: 4.13 | Y15: 3.34 | Z15: 1.8 | AA15: 1.65 | AB15: 0.5 | AC15: 3.78 | AD15: 1.65 | AE15: 2.53
A16: 43862 | B16: 2.05 | C16: 2.1 | D16: 1.88 | E16: 3.79 | F16: 2.01 | G16: 1.49 | H16: -1.34 | I16: 2.31 | J16: 2.37 | K16: 2.86 | L16: 1.67 | M16: 1.79 | N16: -0.07 | O16: 0.76 | P16: 1.54 | Q16: 3.37 | R16: 1.94 | S16: -1.09 | T16: 0.63 | U16: -0.25 | V16: 1.96 | W16: -1.36 | X16: 3.75 | Y16: 3.15 | Z16: 1.43 | AA16: 1.36 | AB16: 0.21 | AC16: 3.14 | AD16: 1.21 | AE16: 2
A17: 43891 | B17: 2.11 | C17: 2.23 | Z17: 1.43
A18: 43922 | B18: 3.47 | C18: 3.58 | Z18: 2.78
A19: 43952 | B19: 3.39 | C19: 3.5 | Z19: 2.71
A20: 43983 | B20: 2.71 | C20: 2.62 | D20: 2.65 | E20: 2.54 | F20: 4.46 | G20: 1.62 | H20: 6.95 | I20: 2.01 | J20: 4.44 | K20: 3.32 | L20: 3.04 | M20: 0.44 | N20: 1.04 | O20: 1.04 | P20: -2.36 | Q20: 11.06 | R20: 2.99 | S20: 2.2 | T20: -0.7 | U20: -1.54 | V20: 3.33 | W20: -17.77 | X20: 4.96 | Y20: 3.47 | Z20: 2.85 | AA20: 2.49 | AB20: 2.58 | AC20: 0.27 | AD20: 4.46 | AE20: 2.14
A21: 44013 | B21: 2.78 | C21: 2.82 | D21: 2.71 | E21: 3.53 | F21: 3.16 | G21: 3.1 | H21: 6.04 | I21: 2.42 | J21: 4.86 | K21: 3.66 | L21: 3.04 | M21: 1.77 | N21: 1.66 | O21: 1.25 | P21: -3.58 | Q21: 8.89 | R21: 2.79 | S21: 1.44 | T21: 0.14 | U21: -10.06 | V21: 3.18 | W21: -13.95 | X21: 5.6 | Y21: 3.34 | Z21: 2.06 | AA21: 2.2 | AB21: 1.79 | AC21: -3.23 | AD21: 3.61 | AE21: 2.14
A22: 44044 | B22: 2.77 | C22: 2.88 | D22: 2.72 | E22: 3.86 | F22: 1.67 | G22: 3.31 | H22: 6.1 | I22: 2.08 | J22: 4.86 | K22: 3.59 | L22: 3.25 | M22: 2.02 | N22: 1.3 | O22: 1.66 | P22: -4.79 | Q22: 9.02 | R22: 2.99 | S22: 1.51 | T22: -0.77 | U22: -8.44 | V22: 3.46 | W22: -11.6 | X22: 4.86 | Y22: 3.09 | Z22: 2.63 | AA22: 2.2 | AB22: 2.15 | AC22: 0.07 | AD22: 3.67 | AE22: 2.72
A23: 44075 | B23: 2.97 | C23: 3.02 | D23: 2.92 | E23: 3.65 | F23: 1.8 | G23: 4.02 | H23: 3.98 | I23: 2.07 | J23: 4.84 | K23: 3.44 | L23: 3.11 | M23: 1.83 | N23: 1.65 | O23: 1.31 | P23: 0.28 | Q23: 8.24 | R23: 3.39 | S23: 2.55 | T23: -0.7 | U23: -14.6 | V23: 3.59 | W23: -10.58 | X23: 4.08 | Y23: 2.67 | Z23: 2.84 | AA23: 2.78 | AB23: 2.72 | AC23: -1.68 | AD23: 4.09 | AE23: 2.56
A24: 44105 | B24: 3.1 | C24: 3.28 | D24: 3.18 | E24: 3.77 | F24: 1.32 | G24: 4.02 | H24: 4.13 | I24: 2.34 | J24: 4.97 | K24: 3.71 | L24: 3.31 | M24: 1.96 | N24: 3.17 | O24: 2.14 | P24: 1.27 | Q24: 8.94 | R24: 3.79 | S24: 2.49 | T24: -0.7 | U24: -13.12 | V24: 3.66 | W24: -10.97 | X24: 4.06 | Y24: 2.9 | Z24: 2.91 | AA24: 2.84 | AB24: 3.01 | AC24: -2.15 | AD24: 4.59 | AE24: 2.56
A25: 44136 | B25: 3.36 | C25: 3.4 | D25: 2.9 | E25: 3.62 | F25: 1.99 | G25: 3.92 | H25: 4.95 | I25: 2.33 | J25: 4.73 | K25: 3.84 | L25: 3.71 | M25: 2.01 | N25: 3.79 | O25: 2.75 | P25: 4.75 | Q25: 9.76 | R25: 3.71 | S25: 2.27 | T25: 0 | U25: -12.18 | V25: 3.86 | W25: -9.48 | X25: 4.63 | Y25: 3.13 | Z25: 3.12 | AA25: 2.98 | AB25: 3.15 | AC25: -2.47 | AD25: 4.66 | AE25: 2.91
A26: 44166 | B26: 3.49 | C26: 3.46 | D26: 3.55 | E26: 3.75 | F26: 2.11 | G26: 4.2 | H26: 4.53 | I26: 2.6 | J26: 4.79 | K26: 3.97 | L26: 3.7 | M26: 2.26 | N26: 3.58 | O26: 2.68 | P26: 3.85 | Q26: 13.06 | R26: 3.76 | S26: 2.13 | T26: 2.51 | U26: -18.52 | V26: 4.2 | W26: -8.17 | X26: 5.02 | Y26: 3.47 | Z26: 3.4 | AA26: 3.11 | AB26: 3.43 | AC26: -2.53 | AD26: 5.07 | AE26: 3.35
A27: 44197 | B27: 3.82 | C27: 3.85 | D27: 4.34 | E27: 4.13 | F27: 2.76 | G27: 4.83 | H27: 4.38 | I27: 3 | J27: 5.13 | K27: 4.17 | L27: 3.83 | M27: 2.7 | N27: 4.21 | O27: 3.66 | P27: 3.9 | Q27: 12.56 | R27: 4.15 | S27: 2.34 | T27: 3.06 | U27: -17.69 | V27: 4.68 | W27: -8.25 | X27: 5.92 | Y27: 3.64 | Z27: 3.75 | AA27: 3.46 | AB27: 3.78 | AC27: -2.32 | AD27: 5.71 | AE27: 3.48
A28: 44228 | B28: 4.21 | C28: 4.31 | D28: 5.06 | E28: 4.31 | F28: 3.41 | G28: 5.45 | H28: 4.7 | I28: 3.59 | J28: 5.61 | K28: 4.65 | L28: 4.23 | M28: 3.07 | N28: 3.8 | O28: 3.31 | P28: 3.65 | Q28: 11.5 | R28: 4.87 | S28: 3.03 | T28: 3.7 | U28: -18.44 | V28: 5.22 | W28: -7.92 | X28: 6.54 | Y28: 4.04 | Z28: 4.09 | AA28: 3.52 | AB28: 3.99 | AC28: -1.79 | AD28: 5.99 | AE28: 4.13
A29: 44256 | B29: 4.41 | C29: 4.37 | Z29: 4.23
A30: 44287 | B30: 3.49 | C30: 3.52 | Z30: 3.13
A31: 44317 | B31: 5.32 | C31: 5.34 | Z31: 5.48
A32: 44348 | B32: 6.14 | C32: 6.36 | D32: 6.59 | E32: 7.04 | F32: 5.11 | G32: 8.26 | H32: 5.47 | I32: 6.32 | J32: 7.07 | K32: 6.43 | L32: 5.7 | M32: 6.01 | N32: 5.33 | O32: 6.98 | P32: 6.76 | Q32: 2.66 | R32: 6.65 | S32: 4.18 | T32: 10.22 | U32: 0.52 | V32: 8.87 | W32: 13.76 | X32: 5.74 | Y32: 4.09 | Z32: 5.12 | AA32: 4.58 | AB32: 5.1 | AC32: 0.6 | AD32: 5.76 | AE32: 6.93
A33: 44378 | B33: 6.39 | C33: 6.34 | D33: 6.76 | E33: 6.24 | F33: 6.71 | G33: 6.77 | H33: 5.18 | I33: 6.16 | J33: 6.96 | K33: 6.25 | L33: 6.11 | M33: 5.16 | N33: 4.82 | O33: 6.5 | P33: 8.36 | Q33: 4.83 | R33: 7.96 | S33: 4.67 | T33: 9.29 | U33: 12.42 | V33: 8.52 | W33: 9.26 | X33: 4.74 | Y33: 4.2 | Z33: 6.76 | AA33: 5.7 | AB33: 7.03 | AC33: 5.9 | AD33: 7.1 | AE33: 7.35
A34: 44409 | B34: 6.84 | C34: 6.78 | D34: 7.93 | E34: 6.47 | F34: 8.1 | G34: 8.24 | H34: 5.62 | I34: 7.03 | J34: 7.22 | K34: 7 | L34: 6.36 | M34: 5.64 | N34: 5.02 | O34: 6.48 | P34: 9.12 | Q34: 4.41 | R34: 8.52 | S34: 5.28 | T34: 11.22 | U34: 8.3 | V34: 8.76 | W34: 6.9 | X34: 5.7 | Y34: 4.47 | Z34: 7 | AA34: 6.4 | AB34: 7.28 | AC34: 3.02 | AD34: 7.76 | AE34: 7.89
A35: 44440 | B35: 7.22 | C35: 7.09 | D35: 8.31 | E35: 7.11 | F35: 8.66 | G35: 8.47 | H35: 6.27 | I35: 7.34 | J35: 7.68 | K35: 7.73 | L35: 6.63 | M35: 6.39 | N35: 4.25 | O35: 6.34 | P35: 7.52 | Q35: 3.87 | R35: 8.67 | S35: 4.98 | T35: 10.57 | U35: 14.45 | V35: 9.07 | W35: 6.18 | X35: 6.44 | Y35: 4.87 | Z35: 7.4 | AA35: 6.51 | AB35: 7.46 | AC35: 5.34 | AD35: 8.2 | AE35: 7.93
A36: 44470 | B36: 7.53 | C36: 7.39 | D36: 8.61 | E36: 7.39 | F36: 9.2 | G36: 8.94 | H36: 7.07 | I36: 7.64 | J36: 7.85 | K36: 7.97 | L36: 6.73 | M36: 6.87 | N36: 4.34 | O36: 6.15 | P36: 6.88 | Q36: 2.91 | R36: 9.22 | S36: 5.73 | T36: 10.64 | U36: 13.18 | V36: 9.39 | W36: 6.84 | X36: 6.41 | Y36: 4.97 | Z36: 7.87 | AA36: 6.77 | AB36: 7.92 | AC36: 6.31 | AD36: 8.72 | AE36: 8.12
A37: 44501 | B37: 7.94 | C37: 7.87 | D37: 9.36 | E37: 8.07 | F37: 11.84 | G37: 8.56 | H37: 6.88 | I37: 8.01 | J37: 8.16 | K37: 8.34 | L37: 6.83 | M37: 7.34 | N37: 4.25 | O37: 6.17 | P37: 8.99 | Q37: 5.76 | R37: 9.77 | S37: 6.4 | T37: 10.08 | U37: 12.91 | V37: 9.55 | W37: 6.8 | X37: 6.53 | Y37: 4.89 | Z37: 8.25 | AA37: 7.24 | AB37: 8.32 | AC37: 6.93 | AD37: 9.24 | AE37: 8.28
A38: 44531 | B38: 8.3 | C38: 8.36 | D38: 9.98 | E38: 8.61 | F38: 12 | G38: 9.54 | H38: 7.74 | I38: 8.38 | J38: 8.46 | K38: 8.84 | L38: 7.27 | M38: 7.68 | N38: 4.98 | O38: 6.36 | P38: 8.74 | Q38: 4.89 | R38: 10.24 | S38: 7.48 | T38: 8.42 | U38: 22.49 | V38: 9.91 | W38: 6.19 | X38: 6.48 | Y38: 5.2 | Z38: 8.62 | AA38: 7.61 | AB38: 8.91 | AC38: 7.31 | AD38: 9.65 | AE38: 8.45
A39: 44562 | B39: 8.78 | C39: 8.7 | D39: 10.28 | E39: 8.94 | F39: 12.07 | G39: 9.81 | H39: 8.86 | I39: 8.79 | J39: 8.95 | K39: 9.33 | L39: 7.77 | M39: 8.01 | N39: 5.36 | O39: 6.93 | P39: 9.02 | Q39: 5.17 | R39: 10.63 | S39: 8.09 | T39: 8.9 | U39: 20.71 | V39: 10.32 | W39: 7.81 | X39: 6.08 | Y39: 5.07 | Z39: 9.47 | AA39: 8.4 | AB39: 9.63 | AC39: 8.14 | AD39: 10.54 | AE39: 8.97
A40: 44593 | B40: 8.86 | C40: 8.58 | D40: 10.45 | E40: 9.01 | F40: 11.94 | G40: 9.81 | H40: 9.1 | I40: 8.54 | J40: 8.63 | K40: 9.55 | L40: 7.53 | M40: 8.09 | N40: 6.13 | O40: 7.27 | P40: 9.76 | Q40: 6.43 | R40: 10.41 | S40: 7.96 | T40: 9.7 | U40: 22.45 | V40: 10.31 | W40: 7.04 | X40: 5.82 | Y40: 4.99 | Z40: 10.1 | AA40: 9.11 | AB40: 10.56 | AC40: 8.77 | AD40: 11.56 | AE40: 9.26
A41: 44621 | B41: 9.4 | C41: 9.06 | D41: 11.38 | E41: 9.25 | F41: 12.25 | G41: 10.15 | H41: 9.44 | I41: 9.07 | J41: 9.34 | K41: 10.24 | L41: 8.17 | M41: 8.6 | N41: 6.91 | O41: 7.3 | P41: 10.18 | Q41: 5.53 | R41: 10.53 | S41: 8.61 | T41: 9.29 | U41: 24.12 | V41: 10.51 | W41: 6.61 | X41: 6.29 | Y41: 5.08 | Z41: 11.29 | AA41: 10.19 | AB41: 11.4 | AC41: 10.98 | AD41: 12.71 | AE41: 10.49
A42: 44652 | B42: 9.85 | C42: 9.51 | D42: 11.77 | E42: 9.61 | F42: 12.56 | G42: 11.14 | H42: 8.98 | I42: 9.85 | J42: 9.54 | K42: 11.05 | L42: 8.85 | M42: 9.34 | N42: 7.33 | O42: 7.37 | P42: 9.22 | Q42: 2.55 | R42: 10.98 | S42: 8.88 | T42: 8.95 | U42: 20.55 | V42: 11.15 | W42: 7.16 | X42: 6.63 | Y42: 5.51 | Z42: 12.12 | AA42: 10.83 | AB42: 12.17 | AC42: 11.51 | AD42: 13.56 | AE42: 11.19
A43: 44682 | B43: 8.85 | C43: 8.53 | D43: 11.67 | E43: 9.02 | F43: 9.96 | G43: 11.05 | H43: 8.38 | I43: 8.24 | J43: 8.73 | K43: 10.46 | L43: 7.24 | M43: 8.65 | N43: 6.84 | O43: 6.08 | P43: 9.12 | Q43: 7.18 | R43: 9.37 | S43: 8.98 | T43: 5.42 | U43: 13.47 | V43: 9.07 | W43: 8.27 | X43: 8.98 | Y43: 4.96 | Z43: 10.72 | AA43: 9.39 | AB43: 10.19 | AC43: 10.41 | AD43: 12.4 | AE43: 9.95
... A65: 45352 | B65: 2.97 | C65: 3.12 | D65: 2.46 | E65: 2.67 | F65: 4.52 | G65: 2.61 | H65: 3.4 | I65: 2.39 | J65: 2.58 | K65: 1.43 | L65: 3.04 | M65: 3.26 | N65: 3 | O65: 3.06 | P65: 4.03 | Q65: -0.06 | R65: 3.95 | S65: 3.72 | T65: 0.68 | U65: -1.17 | V65: 2.55 | W65: 0.92 | X65: 4.93 | Y65: 4.54 | Z65: 2.57 | AA65: 3.02 | AB65: 2.59 | AC65: 3.27 | AD65: 1.56 | AE65: 3.79
A66: Cumulative | B66: Apr-Mar | C66: Apr-Mar | D66: Apr-Mar | E66: Apr-Mar | F66: Apr-Mar | G66: Apr-Mar | H66: Apr-Mar | I66: Apr-Mar | J66: Apr-Mar | K66: Apr-Mar | L66: Apr-Mar | M66: Apr-Mar | N66: Apr-Mar | O66: Apr-Mar | P66: Apr-Mar | Q66: Apr-Mar | R66: Apr-Mar | S66: Apr-Mar | T66: Apr-Mar | U66: Apr-Mar | V66: Apr-Mar | W66: Apr-Mar | X66: Apr-Mar | Y66: Apr-Mar | Z66: Apr-Mar | AA66: Apr-Mar | AB66: Apr-Mar | AC66: Apr-Mar | AD66: Apr-Mar | AE66: Apr-Mar
A67: 2019-20 | B67: 1.62 | C67: 1.61 | Z67: 1.61
A68: 2020-21 | B68: 3.38 | C68: 3.43 | Z68: 3.12
A69: 2021-22 | B69: 7.2 | C69: 7.13 | Z69: 7.56
A70: 2022-23 | B70: 9.47 | C70: 9.19 | D70: 11.55 | E70: 10.03 | F70: 9.78 | G70: 11.18 | H70: 8.74 | I70: 9.16 | J70: 8.88 | K70: 10.86 | L70: 8.09 | M70: 9.17 | N70: 8.37 | O70: 7.69 | P70: 5.83 | Q70: 4.36 | R70: 10.8 | S70: 8.6 | T70: 7.37 | U70: 6.12 | V70: 9.5 | W70: 10.99 | X70: 8.59 | Y70: 6.12 | Z70: 11.25 | AA70: 10.22 | AB70: 10.97 | AC70: 11.07 | AD70: 12.72 | AE70: 10.05
A71: 2023-24 | B71: 4.71 | C71: 4.79 | D71: 4.83 | E71: 4.46 | F71: 5.66 | G71: 5.11 | H71: 4.93 | I71: 4.24 | J71: 4.6 | K71: 3.91 | L71: 4.3 | M71: 4.78 | N71: 4.61 | O71: 4.72 | P71: 4.58 | Q71: 0.47 | R71: 5.68 | S71: 4.91 | T71: 4 | U71: -0.37 | V71: 4.4 | W71: 10.93 | X71: 6.44 | Y71: 5.57 | Z71: 4.36 | AA71: 4.68 | AB71: 4.75 | AC71: 4.9 | AD71: 3.64 | AE71: 4.7

Sheet InstitutionalCredit-Industry
B1: 2018-19 | C1: 2019-20 | D1: 2020-21 | E1: 2021-22 | F1: 2022-23
A2: Total | B2: 100 | C2: 100 | D2: 100 | E2: 100 | F2: 100
A3: Infrastructure | B3: 29.83 | C3: 30.94 | D3: 28.64 | E3: 23.69 | F3: 24.68
A4: Other Services | B4: 27.63 | C4: 22.5 | D4: 14.09 | E4: 19.7 | F4: 20.48
A5: Roads & Bridges | B5: 3.91 | C5: 11.25 | D5: 7.73 | E5: 7.48 | F5: 12.61
A6: Metal & Metal Products | B6: 3.91 | C6: 4.38 | D6: 2.73 | E6: 6.73 | F6: 10.97
A7: Power | B7: 19.07 | C7: 14.69 | D7: 15.91 | E7: 14.46 | F7: 9.69
A8: Textiles | B8: 6.6 | C8: 3.44 | D8: 6.82 | E8: 13.97 | F8: 7.68
A9: Food Products | B9: 6.85 | C9: 10 | D9: 9.09 | E9: 6.23 | F9: 7.31
A10: Construction | B10: 6.36 | C10: 13.75 | D10: 12.27 | E10: 5.49 | F10: 6.4
A11: Pharmaceuticals | B11: 5.62 | C11: 2.81 | D11: 3.18 | E11: 4.99 | F11: 5.48
A12: Others
A14: Hospitals & Health Services | B14: 3.67 | C14: 3.75 | D14: 3.18 | E14: 4.74 | F14: 3.66
A15: Coke and Petroleum Products | C15: 0.94 | E15: 1.75 | F15: 3.11
A16: Chemicals, Pesticides & Fertilisers | B16: 4.65 | C16: 3.75 | D16: 4.09 | E16: 4.99 | F16: 2.93
A17: Rubber & Plastic products | B17: 1.22 | C17: 1.56 | D17: 7.73 | E17: 2.99 | F17: 2.38
A18: Electrical Equipments & electronics | B18: 0.24 | C18: 1.25 | D18: 0.45 | E18: 1.25 | F18: 1.65
A19: SEZ, Industrial, Biotech and IT Park | B19: 2.69 | C19: 2.5 | D19: 2.27 | E19: 0.75 | F19: 1.46
A20: Mining and Quarrying | B20: 1.71 | C20: 1.88 | D20: 0.91 | E20: 0.25 | F20: 1.28
A21: Glass & Pottery | B21: 0.49 | D21: 5.45 | E21: 2 | F21: 0.91
A22: IT Software | B22: 0.49 | C22: 0.31 | E22: 0.5 | F22: 0.73
A23: Storage & Water Management | B23: 3.18 | C23: 1.25 | D23: 2.27 | E23: 0.5 | F23: 0.55
A24: Cement | B24: 2.44 | C24: 0.63 | D24: 2.27 | E24: 0.75 | F24: 0.37
A25: Ports & Airports | B25: 0.98 | C25: 1.25 | D25: 0.45 | E25: 0.5 | F25: 0.37
A26: Industry-wise Distribution of Institutionally Assisted Projects
A27: % share in total : 2003-04 to 2022-23
A28: Of which,
A29: Sugar
A30: Petroleum products
A31: Printing & Publishing | C31: 0.31 | E31: 0.25
A32: Non-electrical Machinery | B32: 4.89 | C32: 0.94 | D32: 1.36 | E32: 1.75
A33: Transport Equipments & Parts | B33: 1.22 | C33: 1.56 | D33: 0.91
A34: Other Manufacturing | B34: 4.89
A35: Hotels and Restaurants | B35: 6.36 | C35: 5 | D35: 1.82
A36: Entertainment
A37: Transport Services | B37: 1.22 | C37: 4.38 | D37: 0.45 | E37: 4.74
A38: Telecom

Sheet GDP growth rate
A1: Data Source | B1: World Development Indicators
A2: Last Updated Date | B2: 44917
A4: Country Name | B4: Country Code | C4: Indicator Name | D4: Indicator Code | E4: 1960 | F4: 1961 | G4: 1962 | H4: 1963 | I4: 1964 | J4: 1965 | K4: 1966 | L4: 1967 | M4: 1968 | N4: 1969 | O4: 1970 | P4: 1971 | Q4: 1972 | R4: 1973 | S4: 1974 | T4: 1975 | U4: 1976 | V4: 1977 | W4: 1978 | X4: 1979 | Y4: 1980 | Z4: 1981 | AA4: 1982 | AB4: 1983 | AC4: 1984 | AD4: 1985 | AE4: 1986 | AF4: 1987 | AG4: 1988 | AH4: 1989 | AI4: 1990 | AJ4: 1991 | AK4: 1992 | AL4: 1993 | AM4: 1994 | AN4: 1995 | AO4: 1996 | AP4: 1997 | AQ4: 1998 | AR4: 1999 | AS4: 2000 | AT4: 2001 | AU4: 2002 | AV4: 2003 | AW4: 2004 | AX4: 2005 | AY4: 2006 | AZ4: 2007 | BA4: 2008 | BB4: 2009 | BC4: 2010 | BD4: 2011 | BE4: 2012 | BF4: 2013 | BG4: 2014 | BH4: 2015 | BI4: 2016 | BJ4: 2017 | BK4: 2018 | BL4: 2019 | BM4: 2020 | BN4: 2021
A5: Aruba | B5: ABW | C5: GDP growth (annual %) | D5: NY.GDP.MKTP.KD.ZG | AF5: 16.078431 | AG5: 18.648649 | AH5: 12.129841 | AI5: 3.9614017 | AJ5: 7.9628717 | AK5: 5.882354 | AL5: 7.3076932 | AM5: 8.2039013 | AN5: 2.5471437 | AO5: 1.1857885 | AP5: 7.046875 | AQ5: 1.9919844 | AR5: 1.2380418 | AS5: 7.6165891 | AT5: 4.1959628 | AU5: -0.95777101 | AV5: 1.1208791 | AW5: 7.2810259 | AX5: -0.38492707 | AY5: 1.1389058 | AZ5: 3.0967223 | BA5: 1.8334309 | BB5: -11.683586 | BC5: -2.732596 | BD5: 3.3667781 | BE5: -1.0353753 | BF5: 6.4298169 | BG5: -0.020479214 | BH5: 3.5436297 | BI5: 2.1167161 | BJ5: 5.4823712 | BK5: 5.2578557 | BL5: 0.63502927 | BM5: -18.5891 | BN5: 17.172509
A6: Africa Eastern and Southern | B6: AFE | C6: GDP growth (annual %) | D6: NY.GDP.MKTP.KD.ZG | F6: 0.2373043 | G6: 7.9844605 | H6: 5.1638734 | I6: 4.5836768 | J6: 5.3280442 | K6: 3.9139086 | L6: 5.2553088 | M6: 4.0263021 | N6: 5.2783662 | O6: 4.6936986 | P6: 5.3750049 | Q6: 2.1541889 | R6: 4.4455362 | S6: 5.8895561 | T6: 1.7360267 | U6: 2.8520219 | V6: 1.2433832 | W6: 1.0447364 | X6: 2.802146 | Y6: 5.4153244 | Z6: 4.3296942 | AA6: 0.51670529 | AB6: 0.16207946 | AC6: 3.0142996 | AD6: -0.4433523 | AE6: 2.2939893 | AF6: 4.2438513 | AG6: 4.0144748 | AH6: 2.9099175 | AI6: -0.032630147 | AJ6: 0.11402982 | AK6: -1.9638181 | AL6: -0.38773294 | AM6: 2.0244878 | AN6: 4.2986524 | AO6: 5.434043 | AP6: 4.4328721 | AQ6: 1.8460084 | AR6: 2.6522826 | AS6: 3.3539775 | AT6: 3.6532242 | AU6: 3.9052503 | AV6: 3.0960449 | AW6: 5.5073149 | AX6: 6.1169245 | AY6: 6.5613182 | AZ6: 6.5687768 | BA6: 4.3024819 | BB6: 0.64542333 | BC6: 5.1971373 | BD6: 3.7001905 | BE6: 0.83883577 | BF6: 4.2213583 | BG6: 3.9906373 | BH6: 2.9764213 | BI6: 2.2240159 | BJ6: 2.54602 | BK6: 2.5107971 | BL6: 2.078473 | BM6: -2.9004898 | BN6: 4.2933954
A7: Afghanistan | B7: AFG | C7: GDP growth (annual %) | D7: NY.GDP.MKTP.KD.ZG | AV7: 8.8322778 | AW7: 1.414118 | AX7: 11.229715 | AY7: 5.3574033 | AZ7: 13.82632 | BA7: 3.9249838 | BB7: 21.390528 | BC7: 14.362441 | BD7: 0.42635478 | BE7: 12.752287 | BF7: 5.6007447 | BG7: 2.7245434 | BH7: 1.4513147 | BI7: 2.2603142 | BJ7: 2.6470032 | BK7: 1.1892281 | BL7: 3.9116034 | BM7: -2.3511007 | BN7: -20.737146
A8: Africa Western and Central | B8: AFW | C8: GDP growth (annual %) | D8: NY.GDP.MKTP.KD.ZG | F8: 1.8350562 | G8: 3.7728981 | H8: 7.2829855 | I8: 5.3927055 | J8: 4.0565884 | K8: -1.807283 | L8: -9.5959248 | M8: 1.4459408 | N8: 15.553815 | O8: 17.963209 | P8: 10.83522 | Q8: 3.1478018 | R8: 4.2232607 | S8: 10.257529 | T8: -2.1903408 | U8: 8.5824984 | V8: 4.7368785 | W8: -2.2241092 | X8: 5.2431649 | Y8: 2.0135315 | Z8: -6.9844199 | AA8: -3.3772504 | AB8: -6.5671545 | AC8: 0.54739861 | AD8: 5.5541632 | AE8: 1.405076 | AF8: 1.460462 | AG8: 4.8617271 | AH8: 2.2695815 | AI8: 6.6001986 | AJ8: 1.1153547 | AK8: 2.7083926 | AL8: -1.1671056 | AM8: -0.31108767 | AN8: 1.9122269 | AO8: 4.6258978 | AP8: 4.2252676 | AQ8: 3.4999053 | AR8: 1.4150749 | AS8: 3.7436666 | AT8: 5.2176628 | AU8: 9.9381488 | AV8: 5.5321126 | AW8: 8.0228375 | AX8: 5.8528919 | AY8: 5.3797655 | AZ8: 5.5391308 | BA8: 6.2830287 | BB8: 6.2883813 | BC8: 6.9654266 | BD8: 4.8520484 | BE8: 5.1355837 | BF8: 6.108758 | BG8: 5.9304497 | BH8: 2.7451374 | BI8: 0.11368699 | BJ8: 2.3056235 | BK8: 2.9461746 | BL8: 3.1908789 | BM8: -0.90038189 | BN8: 3.9653986
A9: Angola | B9: AGO | C9: GDP growth (annual %) | D9: NY.GDP.MKTP.KD.ZG | Z9: -4.4000012 | AA9: 0 | AB9: 4.2000014 | AC9: 6.0000022 | AD9: 3.4999995 | AE9: 2.9000017 | AF9: 4.0827486 | AG9: 6.1288905 | AH9: 0.041621462 | AI9: -3.4500987 | AJ9: 0.9913593 | AK9: -5.8382807 | AL9: -23.983417 | AM9: 1.3393634 | AN9: 15 | AO9: 13.54437 | AP9: 7.2742774 | AQ9: 4.6911465 | AR9: 2.1814897 | AS9: 3.0546242 | AT9: 4.2059986 | AU9: 13.665689 | AV9: 2.99 | AW9: 10.95 | AX9: 15.03 | AY9: 11.55 | AZ9: 14.01 | BA9: 11.17 | BB9: 0.86 | BC9: 4.86 | BD9: 3.47 | BE9: 8.54 | BF9: 4.95 | BG9: 4.82 | BH9: 0.94 | BI9: -2.58 | BJ9: -0.15 | BK9: -1.3163121 | BL9: -0.7 | BM9: -5.6 | BN9: 1.1
A10: Albania | B10: ALB | C10: GDP growth (annual %) | D10: NY.GDP.MKTP.KD.ZG | Z10: 5.7456353 | AA10: 2.9485968 | AB10: 1.1049383 | AC10: -1.2515966 | AD10: 1.780644 | AE10: 5.6372432 | AF10: -0.78784265 | AG10: -1.4200397 | AH10: 9.836549 | AI10: -9.5756402 | AJ10: -28.002142 | AK10: -7.1871109 | AL10: 9.5594117 | AM10: 8.3028666 | AN10: 13.322333 | AO10: 9.0999994 | AP10: -10.919984 | AQ10: 8.8294238 | AR10: 12.890804 | AS10: 6.9462166 | AT10: 8.2933126 | AU10: 4.5365242 | AV10: 5.5286375 | AW10: 5.5146679 | AX10: 5.5264242 | AY10: 5.902659 | AZ10: 5.9832595 | BA10: 7.5000414 | BB10: 3.3542893 | BC10: 3.7069382 | BD10: 2.5454061 | BE10: 1.4172428 | BF10: 1.0020175 | BG10: 1.7744489 | BH10: 2.2187264 | BI10: 3.3149807 | BJ10: 3.8022274 | BK10: 4.0193597 | BL10: 2.0880634 | BM10: -3.4816304 | BN10: 8.5155011
A11: Andorra | B11: AND | C11: GDP growth (annual %) | D11: NY.GDP.MKTP.KD.ZG | P11: 4.6494654 | Q11: 8.1497435 | R11: 7.7884672 | S11: 5.6187897 | T11: 0.54220566 | U11: 3.303787 | V11: 2.8385756 | W11: 1.4630002 | X11: 0.041557195 | Y11: 2.2087276 | Z11: -0.13247451 | AA11: 1.2464611 | AB11: 1.7701183 | AC11: 1.7846867 | AD11: 2.321433 | AE11: 3.2533218 | AF11: 5.5471222 | AG11: 5.0943262 | AH11: 4.8270343 | AI11: 3.7813876 | AJ11: 2.5460035 | AK11: 0.92921404 | AL11: -1.0314844 | AM11: 2.3831822 | AN11: 2.7575016 | AO11: 4.6497387 | AP11: 9.0676721 | AQ11: 3.1947934 | AR11: 4.0990789 | AS11: 3.5283624 | AT11: 8.1193577 | AU11: 4.5463622 | AV11: 8.6942037 | AW11: 8.1356763 | AX11: 5.397796 | AY11: 4.8086887 | AZ11: 1.5531881 | BA11: -5.5591864 | BB11: -5.3028465 | BC11: -1.974958 | BD11: -0.0080697534 | BE11: -4.9744437 | BF11: -3.5475965 | BG11: 2.5044655 | BH11: 1.4341404 | BI11: 3.7096781 | BJ11: 0.34607189 | BK11: 1.5887655 | BL11: 2.0155476 | BM11: -11.18394 | BN11: 8.949418
A12: Arab World | B12: ARB | C12: GDP growth (annual %) | D12: NY.GDP.MKTP.KD.ZG | U12: 15.761152 | V12: 8.1303362 | W12: -0.60034899 | X12: 11.02672 | Y12: 9.0816452 | Z12: 3.3996797 | AA12: -8.3398875 | AB12: -6.2349263 | AC12: 1.3057011 | AD12: -2.052495 | AE12: 4.4404799 | AF12: -0.073272662 | AG12: 5.7679727 | AH12: 2.1923879 | AI12: 12.111035 | AJ12: 2.3916931 | AK12: 5.1996946 | AL12: 3.1670779 | AM12: 3.2807572 | AN12: 3.0614165 | AO12: 4.6966103 | AP12: 4.758653 | AQ12: 5.1166325 | AR12: 1.8367374 | AS12: 6.5656753 | AT12: 1.7004449 | AU12: 0.67728528 | AV12: 4.8751439 | AW12: 8.8671324 | AX12: 5.5231168 | AY12: 6.0873403 | AZ12: 4.5705739 | BA12: 5.5555331 | BB12: 0.38833354 | BC12: 4.7478107 | BD12: 3.2475137 | BE12: 5.1478333 | BF12: 2.5857974 | BG12: 2.9355393 | BH12: 3.2940682 | BI12: 3.5182523 | BJ12: 1.0563326 | BK12: 2.3839248 | BL12: 1.2562786 | BM12: -4.8447743 | BN12: 3.6068165
A13: United Arab Emirates | B13: ARE | C13: GDP growth (annual %) | D13: NY.GDP.MKTP.KD.ZG | U13: 16.526857 | V13: 21.43933 | W13: -1.5896033 | X13: 20.923573 | Y13: 23.874775 | Z13: 4.6591767 | AA13: -6.7193162 | AB13: -4.7458207 | AC13: 4.0169513 | AD13: -3.5944765 | AE13: -14.958137 | AF13: 3.3819817 | AG13: -2.6189077 | AH13: 12.337891 | AI13: 18.327986 | AJ13: 0.86008195 | AK13: 3.3449449 | AL13: 1.261191 | AM13: 6.8961486 | AN13: 6.6878865 | AO13: 5.7984041 | AP13: 8.1903986 | AQ13: 0.29199435 | AR13: 2.9022136 | AS13: 10.852704 | AT13: 1.399085 | AU13: 2.4334568 | AV13: 8.8005408 | AW13: 9.5664366 | AX13: 4.8551412 | AY13: 9.8373198 | AZ13: 3.1843902 | BA13: 3.1918363 | BB13: -5.2429219 | BC13: 1.60285 | BD13: 6.9285086 | BE13: 4.7766257 | BF13: 5.0555597 | BG13: 4.1656918 | BH13: 6.7867729 | BI13: 5.5614908 | BJ13: 0.73506871 | BK13: 1.3139139 | BL13: 1.1083481 | BM13: -4.9570524 | BN13: 3.9162961
A14: Argentina | B14: ARG | C14: GDP growth (annual %) | D14: NY.GDP.MKTP.KD.ZG | F14: 5.4278429 | G14: -0.85202152 | H14: -5.3081968 | I14: 10.130298 | J14: 10.569433 | K14: -0.65972617 | L14: 3.1919966 | M14: 4.8225008 | N14: 9.679526 | O14: 3.0456433 | P14: 5.6581311 | Q14: 1.6284165 | R14: 2.811754 | S14: 5.5338044 | T14: -0.028412104 | U14: -2.0182515 | V14: 6.9341478 | W14: -4.5061248 | X14: 10.222763 | Y14: 1.5187839 | Z14: -5.1897891 | AA14: -0.73565916 | AB14: 4.3490933 | AC14: 1.5707387 | AD14: -5.1890244 | AE14: 6.1533771 | AF14: 2.7048688 | AG14: -1.0899333 | AH14: -7.1569497 | AI14: -2.4672138 | AJ14: 9.1331106 | AK14: 7.9372916 | AL14: 8.2069791 | AM14: 5.8362007 | AN14: -2.8452096 | AO14: 5.5266898 | AP14: 8.1110468 | AQ14: 3.8501789 | AR14: -3.385457 | AS14: -0.78899894 | AT14: -4.4088397 | AU14: -10.894485 | AV14: 8.8370408 | AW14: 9.0295733 | AX14: 8.8516599 | AY14: 8.0471515 | AZ14: 9.0076509 | BA14: 4.0572331 | BB14: -5.9185251 | BC14: 10.125398 | BD14: 6.0039517 | BE14: -1.0264205 | BF14: 2.4053238 | BG14: -2.5126153 | BH14: 2.7311598 | BI14: -2.0803278 | BJ14: 2.818503 | BK14: -2.6173965 | BL14: -2.000861 | BM14: -9.9432351 | BN14: 10.398249
A15: Armenia | B15: ARM | C15: GDP growth (annual %) | D15: NY.GDP.MKTP.KD.ZG | AJ15: -11.699998 | AK15: -41.800003 | AL15: -8.7999988 | AM15: 5.4000028 | AN15: 6.8999984 | AO15: 5.8654007 | AP15: 3.3210797 | AQ15: 7.3 | AR15: 3.3 | AS15: 5.9 | AT15: 9.6 | AU15: 13.2 | AV15: 14 | AW15: 10.5 | AX15: 13.9 | AY15: 13.2 | AZ15: 13.7 | BA15: 6.9 | BB15: -14.1 | BC15: 2.2 | BD15: 4.7 | BE15: 7.2 | BF15: 3.3 | BG15: 3.6 | BH15: 3.2 | BI15: 0.2 | BJ15: 7.5 | BK15: 5.2 | BL15: 7.6 | BM15: -7.2 | BN15: 5.7
A16: American Samoa | B16: ASM | C16: GDP growth (annual %) | D16: NY.GDP.MKTP.KD.ZG | AV16: 0.96551724 | AW16: 0.40983607 | AX16: -0.40816327 | AY16: -4.0983607 | AZ16: 1.8518519 | BA16: -2.6573427 | BB16: -4.1666667 | BC16: 0.29985007 | BD16: 0 | BE16: -4.3348281 | BF16: -2.5 | BG16: 1.7628205 | BH16: 3.1496063 | BI16: -1.6793893 | BJ16: -6.9875776 | BK16: 2.6711185 | BL16: -0.48780488 | BM16: 5.0653595 | BN16: -1.8662519
A17: Antigua and Barbuda | B17: ATG | C17: GDP growth (annual %) | D17: NY.GDP.MKTP.KD.ZG | W17: 4.3836279 | X17: 8.0797453 | Y17: 8.1614308 | Z17: 3.8149162 | AA17: -0.084012264 | AB17: 5.3640163 | AC17: 10.164996 | AD17: 7.6437936 | AE17: 11.493829 | AF17: 6.6263688 | AG17: 5.2132729 | AH17: 5.2522747 | AI17: 3.0117147 | AJ17: 2.1765786 | AK17: 1.1584752 | AL17: 5.2798787 | AM17: 6.6767071 | AN17: -4.3595874 | AO17: 6.6044597 | AP17: 5.4716085 | AQ17: 4.7311251 | AR17: 3.7076179 | AS17: 6.2034313 | AT17: -4.5480035 | AU17: 1.027442 | AV17: 6.0765437 | AW17: 5.7670286 | AX17: 6.4738313 | AY17: 12.708149 | AZ17: 9.3153832 | BA17: -0.014340652 | BB17: -11.962697 | BC17: -7.8405947 | BD17: -1.9586126 | BE17: 3.3728662 | BF17: -0.6008764 | BG17: 3.7957276 | BH17: 3.8252931 | BI17: 5.4964592 | BJ17: 3.1443232 | BK17: 6.8836408 | BL17: 4.8622362 | BM17: -20.192371 | BN17: 5.2708488
A18: Australia | B18: AUS | C18: GDP growth (annual %) | D18: NY.GDP.MKTP.KD.ZG | F18: 2.4826561 | G18: 1.2946113 | H18: 6.2161073 | I18: 6.9800611 | J18: 5.9804379 | K18: 2.3790395 | L18: 6.3049452 | M18: 5.0940338 | N18: 7.0455841 | O18: 7.1759162 | P18: 4.0009325 | Q18: 3.9102845 | R18: 2.619376 | S18: 4.1069731 | T18: 1.33631 | U18: 2.5887708 | V18: 3.5948329 | W18: 0.89314972 | X18: 4.0500266 | Y18: 3.0355888 | Z18: 3.3394948 | AA18: 3.3248523 | AB18: -2.2245419 | AC18: 4.5917386 | AD18: 5.2782439 | AE18: 3.9662743 | AF18: 2.5592576 | AG18: 5.7573411 | AH18: 3.8754255 | AI18: 3.5764858 | AJ18: -0.38307189 | AK18: 0.42861957 | AL18: 4.0474253 | AM18: 3.9809233 | AN18: 3.8871063 | AO18: 3.8568412 | AP18: 3.9128355 | AQ18: 4.6133569 | AR18: 4.9563245 | AS18: 3.9011714 | AT18: 2.0414173 | AU18: 3.9935899 | AV18: 3.1113982 | AW18: 4.2166333 | AX18: 3.1537527 | AY18: 2.7406357 | AZ18: 3.7779168 | BA18: 3.56827 | BB18: 1.870487 | BC18: 2.2065663 | BD18: 2.3913851 | BE18: 3.9020078 | BF18: 2.5787543 | BG18: 2.5790171 | BH18: 2.1527359 | BI18: 2.730548 | BJ18: 2.2821836 | BK18: 2.8830451 | BL18: 2.1713962 | BM18: -0.050885336 | BN18: 2.2362124
A19: Austria | B19: AUT | C19: GDP growth (annual %) | D19: NY.GDP.MKTP.KD.ZG | F19: 5.5379793 | G19: 2.6486751 | H19: 4.1382676 | I19: 6.1243537 | J19: 3.4801749 | K19: 5.6428614 | L19: 3.0080478 | M19: 4.4723128 | N19: 6.2758672 | O19: 6.3211426 | P19: 5.1149686 | Q19: 6.2078611 | R19: 4.8904353 | S19: 3.9421381 | T19: -0.36373543 | U19: 4.5784454 | V19: 5.0799806 | W19: -0.2106537 | X19: 5.3566999 | Y19: 1.7314856 | Z19: -0.14429469 | AA19: 2.0112547 | AB19: 2.973088 | AC19: 0.051274763 | AD19: 2.4986785 | AE19: 2.3013932 | AF19: 1.3571681 | AG19: 3.2958799 | AH19: 3.8870748 | AI19: 4.3456414 | AJ19: 3.4416278 | AK19: 2.0935246 | AL19: 0.5268092 | AM19: 2.4021191 | AN19: 2.6679835 | AO19: 2.3495339 | AP19: 2.0935994 | AQ19: 3.5814258 | AR19: 3.5563312 | AS19: 3.3757221 | AT19: 1.2671682 | AU19: 1.6515539 | AV19: 0.94147092 | AW19: 2.7351202 | AX19: 2.2440653 | AY19: 3.4540418 | AZ19: 3.7274153 | BA19: 1.4604237 | BB19: -3.7645782 | BC19: 1.8370937 | BD19: 2.9227973 | BE19: 0.68044558 | BF19: 0.025504712 | BG19: 0.66127285 | BH19: 1.0145016 | BI19: 1.9894372 | BJ19: 2.2585724 | BK19: 2.4253854 | BL19: 1.5173886 | BM19: -6.4539685 | BN19: 4.5568509
A20: Azerbaijan | B20: AZE | C20: GDP growth (annual %) | D20: NY.GDP.MKTP.KD.ZG | AJ20: -0.70000018 | AK20: -22.6 | AL20: -23.099999 | AM20: -19.700001 | AN20: -11.799999 | AO20: 1.2999994 | AP20: 5.8000001 | AQ20: 9.9999996 | AR20: 7.4000013 | AS20: 11.099999 | AT20: 9.8999999 | AU20: 9.4389163 | AV20: 10.208299 | AW20: 9.2538018 | AX20: 27.961538 | AY20: 34.5 | AZ20: 25 | BA20: 10.758978 | BB20: 9.2963637 | BC20: 5.0489445 | BD20: 0.10000014 | BE20: 2.1652395 | BF20: 5.8098008 | BG20: 2.7505068 | BH20: 1.0939759 | BI20: -3.0999999 | BJ20: 0.19999994 | BK20: 1.5 | BL20: 2.5000001 | BM20: -4.3000001 | BN20: 5.6000373
A21: Burundi | B21: BDI | C21: GDP growth (annual %) | D21: NY.GDP.MKTP.KD.ZG | F21: -13.746135 | G21: 9.0631579 | H21: 4.1354074 | I21: 6.2730379 | J21: 3.9672256 | K21: 4.6129929 | L21: 13.821519 | M21: -0.29788367 | N21: -1.4595411 | O21: 21.325671 | P21: 2.7468287 | Q21: -6.4039649 | R21: 6.8890507 | S21: -0.72683956 | T21: 0.69792024 | U21: 7.942661 | V21: 11.469453 | W21: -0.94057599 | X21: 1.664955 | Y21: 0.99105573 | Z21: 12.163276 | AA21: -1.0535998 | AB21: 3.715327 | AC21: 0.155544 | AD21: 11.78318 | AE21: 3.2501805 | AF21: 5.5030961 | AG21: 5.0310244 | AH21: 1.3495022 | AI21: 3.4998221 | AJ21: 4.9968364 | AK21: 1.0099984 | AL21: -6.24 | AM21: -3.83 | AN21: -7.92 | AO21: -8 | AP21: -1.59 | AQ21: 4.75 | AR21: -1.01 | AS21: -0.85686406 | AT21: 2.0558071 | AU21: 4.4465194 | AV21: -1.223728 | AW21: 4.8336578 | AX21: 0.9 | AY21: 5.4138071 | AZ21: 3.4519486 | BA21: 4.8617164 | BB21: 3.8127454 | BC21: 5.12416 | BD21: 4.0326 | BE21: 4.4467063 | BF21: 4.9241899 | BG21: 4.2406502 | BH21: -3.9000001 | BI21: -0.60000091 | BJ21: 0.50000126 | BK21: 1.6099354 | BL21: 1.8125653 | BM21: 0.32715689 | BN21: 1.7953
A22: Belgium | B22: BEL | C22: GDP growth (annual %) | D22: NY.GDP.MKTP.KD.ZG | F22: 4.9784231 | G22: 5.2120035 | H22: 4.3515843 | I22: 6.9566847 | J22: 3.5606598 | K22: 3.155895 | L22: 3.8681469 | M22: 4.1941296 | N22: 6.6297998 | O22: 5.5828583 | P22: 3.9858271 | Q22: 5.2956047 | R22: 6.381702 | S22: 4.565258 | T22: -1.9659416 | U22: 5.6527459 | V22: 0.62615485 | W22: 2.8418965 | X22: 2.341073 | Y22: 4.4440539 | Z22: -0.27928328 | AA22: 0.59498677 | AB22: 0.3118427 | AC22: 2.4663828 | AD22: 1.6517929 | AE22: 1.8227618 | AF22: 2.3066596 | AG22: 4.7232089 | AH22: 3.469167 | AI22: 3.1374023 | AJ22: 1.8330743 | AK22: 1.5306549 | AL22: -0.96187331 | AM22: 3.2269715 | AN22: 2.3847573 | AO22: 1.3214509 | AP22: 3.7936576 | AQ22: 1.9618083 | AR22: 3.5427435 | AS22: 3.7166794 | AT22: 1.0996189 | AU22: 1.7068846 | AV22: 1.0379825 | AW22: 3.5712043 | AX22: 2.3217371 | AY22: 2.5523499 | AZ22: 3.6768811 | BA22: 0.44692874 | BB22: -2.0207431 | BC22: 2.8642927 | BD22: 1.6945139 | BE22: 0.73921728 | BF22: 0.45924219 | BG22: 1.5785331 | BH22: 2.041459 | BI22: 1.2666864 | BJ22: 1.6195803 | BK22: 1.7929452 | BL22: 2.2408582 | BM22: -5.3613866 | BN22: 6.133866
A23: Benin | B23: BEN | C23: GDP growth (annual %) | D23: NY.GDP.MKTP.KD.ZG | F23: 3.1412805 | G23: -3.4264098 | H23: 4.730028 | I23: 6.6507591 | J23: 5.2938628 | K23: 3.5758627 | L23: 1.0783987 | M23: 3.8423356 | N23: 2.877498 | O23: 2.0977576 | P23: -1.4968418 | Q23: 6.4263675 | R23: 3.7061653 | S23: 3.3393122 | T23: -4.8953454 | U23: 0.88435633 | V23: 4.9836637 | W23: 1.255078 | X23: 6.5357474 | Y23: 6.7817639 | Z23: 9.9542312 | AA23: 2.2350663 | AB23: -4.3478227 | AC23: 7.9298396 | AD23: 7.5303248 | AE23: 2.1711416 | AF23: -1.500003 | AG23: 3.4052453 | AH23: -2.8541605 | AI23: 8.9761344 | AJ23: 4.2257994 | AK23: 2.9577108 | AL23: 5.8361721 | AM23: 2.0204004 | AN23: 6.0451987 | AO23: 4.324284 | AP23: 5.7346884 | AQ23: 3.9610121 | AR23: 5.3414494 | AS23: 5.8577142 | AT23: 5.3331357 | AU23: 4.6430309 | AV23: 3.4435768 | AW23: 4.4296846 | AX23: 1.7131646 | AY23: 3.9437388 | AZ23: 5.9863493 | BA23: 4.8965771 | BB23: 2.3192921 | BC23: 2.1140647 | BD23: 2.9637529 | BE23: 4.8112233 | BF23: 7.1914337 | BG23: 6.3576791 | BH23: 1.7781511 | BI23: 3.3396734 | BJ23: 5.6715555 | BK23: 6.6972595 | BL23: 6.8656873 | BM23: 3.8485231 | BN23: 7.1557295
A24: Burkina Faso | B24: BFA | C24: GDP growth (annual %) | D24: NY.GDP.MKTP.KD.ZG | F24: 4.043928 | G24: 6.1287988 | H24: -1.2680164 | I24: 2.2828192 | J24: 3.7645454 | K24: 0.53761308 | L24: 8.823315 | M24: 3.0707739 | N24: 2.026081 | O24: 0.11701961 | P24: 1.4133399 | Q24: 2.3114987 | R24: 0.4493274 | S24: 8.2864265 | T24: 2.9983829 | U24: 8.534895 | V24: 0.37035356 | W24: 4.607825 | X24: 3.6646215 | Y24: 0.79687888 | Z24: 4.2553034 | AA24: 9.5621966 | AB24: 0.34598474 | AC24: -1.7786967 | AD24: 8.517365 | AE24: 7.9553627 | AF24: -0.23633679 | AG24: 5.795593 | AH24: 2.1502673 | AI24: -0.60292848 | AJ24: 9.0699845 | AK24: 0.23271076 | AL24: 3.4613849 | AM24: 1.3150073 | AN24: 5.7163739 | AO24: 11.014744 | AP24: 6.3168347 | AQ24: 7.3077196 | AR24: 7.3952378 | AS24: 1.8884739 | AT24: 6.6134057 | AU24: 4.3529638 | AV24: 7.8024939 | AW24: 4.4784521 | AX24: 8.6618732 | AY24: 6.2531647 | AZ24: 4.111379 | BA24: 5.7999917 | BB24: 2.9619509 | BC24: 8.4462816 | BD24: 6.6225626 | BE24: 6.4526724 | BF24: 5.7925848 | BG24: 4.3268456 | BH24: 3.9212288 | BI24: 5.9579767 | BJ24: 6.2034894 | BK24: 6.6045691 | BL24: 5.6881151 | BM24: 1.9303249 | BN24: 6.9063417
A25: Bangladesh | B25: BGD | C25: GDP growth (annual %) | D25: NY.GDP.MKTP.KD.ZG | F25: 6.0581608 | G25: 5.453031 | H25: -0.45589429 | I25: 10.952789 | J25: 1.6062582 | K25: 2.566812 | L25: -1.8758639 | M25: 9.489454 | N25: 1.2208579 | O25: 5.6198523 | P25: -5.479483 | Q25: -13.973729 | R25: 3.3256802 | S25: 9.5919563 | T25: -4.0882141 | U25: 5.6613612 | V25: 2.6730561 | W25: 7.0738377 | X25: 4.8016346 | Y25: 0.81914187 | Z25: 7.2339437 | AA25: 2.1343278 | AB25: 3.8810464 | AC25: 4.80331 | AD25: 3.3420147 | AE25: 4.1733826 | AF25: 3.7724019 | AG25: 2.4162569 | AH25: 2.8365821 | AI25: 5.6222582 | AJ25: 3.4852278 | AK25: 5.4426855 | AL25: 4.7115617 | AM25: 3.8901264 | AN25: 5.1212779 | AO25: 4.5229192 | AP25: 4.4898965 | AQ25: 5.1770269 | AR25: 4.6701564 | AS25: 5.2932947 | AT25: 5.0772878 | AU25: 3.8331239 | AV25: 4.7395674 | AW25: 5.2395329 | AX25: 6.5359449 | AY25: 6.671905 | AZ25: 7.0585994 | BA25: 6.0137898 | BB25: 5.0451248 | BC25: 5.5717882 | BD25: 6.4643791 | BE25: 6.5214588 | BF25: 6.0136057 | BG25: 6.0610594 | BH25: 6.5526399 | BI25: 7.1134782 | BJ25: 6.59025 | BK25: 7.3194126 | BL25: 7.8819152 | BM25: 3.4480215 | BN25: 6.9386751
A26: Bulgaria | B26: BGR | C26: GDP growth (annual %) | D26: NY.GDP.MKTP.KD.ZG | Z26: 4.9001619 | AA26: 2.3345656 | AB26: 3.4303059 | AC26: 3.3964436 | AD26: 2.6834407 | AE26: 4.207602 | AF26: 6.0545138 | AG26: 10.944692 | AH26: -3.2898821 | AI26: -9.1173771 | AJ26: -8.4453552 | AK26: -7.272388 | AL26: -1.4802149 | AM26: 1.8180113 | AN26: 2.8612328 | AO26: 5.2053941 | AP26: -14.115382 | AQ26: 3.7891206 | AR26: -8.3960907 | AS26: 4.5872248 | AT26: 3.8237034 | AU26: 5.8719314 | AV26: 5.2371552 | AW26: 6.5104253 | AX26: 7.0563489 | AY26: 6.8025892 | AZ26: 6.6543868 | BA26: 6.1295597 | BB26: -3.3471421 | BC26: 1.5418014 | BD26: 2.1012058 | BE26: 0.75493039 | BF26: -0.56049397 | BG26: 0.96686903 | BH26: 3.4280549 | BI26: 3.0398253 | BJ26: 2.762171 | BK26: 2.6847606 | BL26: 4.0381422 | BM26: -3.9586146 | BN26: 7.6346097
A27: Bahrain | B27: BHR | C27: GDP growth (annual %) | D27: NY.GDP.MKTP.KD.ZG | Z27: -5.3166974 | AA27: -7.5562177 | AB27: 6.3763768 | AC27: 5.003646 | AD27: -4.7582685 | AE27: 1.1829939 | AF27: 10.399009 | AG27: 6.9999916 | AH27: 0.36400714 | AI27: 4.4379972 | AJ27: 11.229999 | AK27: 6.6899984 | AL27: 12.870007 | AM27: -0.25000148 | AN27: 3.9299915 | AO27: 4.1100061 | AP27: 3.0929998 | AQ27: 4.7900028 | AR27: 4.299999 | AS27: 5.3000701 | AT27: 2.4909481 | AU27: 3.3485507 | AV27: 6.296442 | AW27: 6.9809606 | AX27: 6.7689979 | AY27: 6.4670001 | AZ27: 8.2939604 | BA27: 6.2450108 | BB27: 2.5398859 | BC27: 4.3342992 | BD27: 1.983515 | BE27: 3.7281084 | BF27: 5.4168398 | BG27: 4.3503909 | BH27: 2.4853786 | BI27: 3.5581281 | BJ27: 4.2909498 | BK27: 2.1111305 | BL27: 2.1669647 | BM27: -4.935855 | BN27: 2.2253512
A28: Bahamas, The | B28: BHS | C28: GDP growth (annual %) | D28: NY.GDP.MKTP.KD.ZG | F28: 10.667097 | G28: 10.451972 | H28: 10.524055 | I28: 10.501567 | J28: 10.425596 | K28: 9.0719287 | L28: 9.5981139 | M28: 8.4217636 | N28: 8.9816626 | O28: -5.6496495 | P28: 1.6265087 | Q28: -3.4973359 | R28: 7.5675688 | S28: -16.754229 | T28: -14.803126 | U28: 5.185185 | V28: 9.1549292 | W28: 14.17952 | X28: 26.139296 | Y28: 6.4952819 | Z28: -9.2264051 | AA28: 6.6988978 | AB28: 3.5970519 | AC28: 14.171149 | AD28: 4.8291801 | AE28: 1.7970002 | AF28: 2.9845193 | AG28: 2.3097077 | AH28: 6.7273298 | AI28: -1.5962491 | AJ28: -4.1817848 | AK28: -3.825582 | AL28: 0.30780629 | AM28: 3.1489156 | AN28: 4.3787521 | AO28: 4.2235304 | AP28: 6.8757394 | AQ28: -4.5035966 | AR28: 12.197518 | AS28: 4.149234 | AT28: 2.6251596 | AU28: 2.704671 | AV28: -1.2645263 | AW28: 0.88274019 | AX28: 3.3952601 | AY28: 2.5168539 | AZ28: 1.4467339 | BA28: -2.3235072 | BB28: -4.1758056 | BC28: 1.538386 | BD28: 0.61338416 | BE28: 3.0868792 | BF28: -2.8632939 | BG28: 1.8473029 | BH28: 0.99680085 | BI28: -0.85766432 | BJ28: 3.0501573 | BK28: 1.8310078 | BL28: 1.8961637 | BM28: -23.822608 | BN28: 13.719735
A29: Bosnia and Herzegovina | B29: BIH | C29: GDP growth (annual %) | D29: NY.GDP.MKTP.KD.ZG | AN29: 20.799998 | AO29: 88.957666 | AP29: 34.389574 | AQ29: 15.599997 | AR29: 9.5999997 | AS29: 12.765469 | AT29: 2.4233132 | AU29: 5.0274442 | AV29: 3.8671388 | AW29: 6.3252662 | AX29: 3.897178 | AY29: 5.4140036 | AZ29: 5.8571263 | BA29: 5.443831 | BB29: -3.0044559 | BC29: 0.86566926 | BD29: 0.95951125 | BE29: -0.82183647 | BF29: 2.3498567 | BG29: 1.1538511 | BH29: 3.0891627 | BI29: 3.1498073 | BJ29: 3.1714349 | BK29: 3.7400731 | BL29: 2.8310013 | BM29: -3.1192905 | BN29: 7.5455911
A30: Belarus | B30: BLR | C30: GDP growth (annual %) | D30: NY.GDP.MKTP.KD.ZG | AJ30: -1.1999956 | AK30: -9.6000014 | AL30: -7.6000018 | AM30: -11.700004 | AN30: -10.4 | AO30: 2.8000047 | AP30: 11.400005 | AQ30: 8.3999914 | AR30: 3.3999992 | AS30: 5.8000034 | AT30: 4.725306 | AU30: 5.0452675 | AV30: 7.0431926 | AW30: 11.449743 | AX30: 9.4000015 | AY30: 9.9999948 | AZ30: 8.6000065 | BA30: 10.199999 | BB30: 0.19999531 | BC30: 7.7982668 | BD30: 5.3787074 | BE30: 1.6871355 | BF30: 1.0034708 | BG30: 1.7263849 | BH30: -3.8295706 | BI30: -2.5264464 | BJ30: 2.5321835 | BK30: 3.1491976 | BL30: 1.4 | BM30: -0.69960761 | BN30: 2.2998794
A31: Belize | B31: BLZ | C31: GDP growth (annual %) | D31: NY.GDP.MKTP.KD.ZG | F31: 4.8922772 | G31: 4.8926522 | H31: 4.9564342 | I31: 4.9998799 | J31: 4.930541 | K31: 4.7708451 | L31: 4.9131232 | M31: 7.3672255 | N31: 5.1063748 | O31: 4.8076934 | P31: 3.9594411 | Q31: 10.218304 | R31: 5.3518941 | S31: 13.559985 | T31: 3.5928244 | U31: -0.034020943 | V31: 6.4965943 | W31: 7.9208072 | X31: 7.5170215 | Y31: 13.436682 | Z31: 1.1337708 | AA31: -0.10771043 | AB31: -2.14318 | AC31: 1.972065 | AD31: 1.0125139 | AE31: 4.539457 | AF31: 10.735304 | AG31: 9.7877114 | AH31: 13.009221 | AI31: 11.443389 | AJ31: 11.45288 | AK31: 12.037581 | AL31: 6.2368973 | AM31: 0.19733596 | AN31: 0.64007878 | AO31: 1.0273973 | AP31: 3.5835351 | AQ31: 3.9270687 | AR31: 8.9518668 | AS31: 13.00578 | AT31: 5.0420168 | AU31: 5.1130435 | AV31: 9.3315685 | AW31: 4.6307506 | AX31: 2.198438 | AY31: 4.5853382 | AZ31: 3.2746955 | BA31: -1.5199161 | BB31: -0.45236828 | BC31: 1.2563486 | BD31: -0.10559662 | BE31: 3.858351 | BF31: 4.5292621 | BG31: 4.0895813 | BH31: 3.3676333 | BI31: 0.11312217 | BJ31: -1.6949153 | BK31: 1.1034483 | BL31: 4.5020464 | BM31: -13.402959 | BN31: 15.226131
A32: Bermuda | B32: BMU | C32: GDP growth (annual %) | D32: NY.GDP.MKTP.KD.ZG | F32: 4.68 | G32: 4.47 | H32: 1.07 | I32: 11.11 | J32: 4.76 | K32: 14.363636 | L32: 13.27504 | M32: 2.1052632 | N32: 3.4364261 | O32: 6.3122924 | P32: 3.4375 | Q32: 1.8126888 | R32: 1.4836795 | S32: 0.87719298 | T32: 3.7681159 | U32: 8.9385475 | V32: 5.8974359 | W32: 1.4527845 | X32: 2.1479714 | Y32: 7.9439252 | Z32: 2.3809524 | AA32: -5.2854123 | AB32: 2.0089286 | AC32: 0.48140044 | AD32: -2.0034843 | AE32: 6.6666667 | AF32: 3.75 | AG32: 4.0562249 | AH32: 0.44384408 | AI32: 0.019212297 | AJ32: -3.5343821 | AK32: -0.059738214 | AL32: 3.0085671 | AM32: 0.59961337 | AN32: 4.3991483 | AO32: 2.6004754 | AP32: 4.6000008 | AQ32: 3.9000001 | AR32: 3.382647 | AS32: 9.3171564 | AT32: 7.2224355 | AU32: -1.4777906 | AV32: 3.4107067 | AW32: 2.3212672 | AX32: 1.6742061 | AY32: 5.5438664 | AZ32: 3.3451397 | BA32: -1.8659558 | BB32: -5.6266977 | BC32: -2.5028783 | BD32: -3.7427443 | BE32: -5.3052991 | BF32: -0.27970855 | BG32: -3.7010676 | BH32: 0.7755297 | BI32: -0.6572063 | BJ32: 3.6114198 | BK32: -0.4328013 | BL32: 0.30626674 | BM32: -6.8379552 | BN32: 5.4135338
A33: Bolivia | B33: BOL | C33: GDP growth (annual %) | D33: NY.GDP.MKTP.KD.ZG | F33: 2.0892959 | G33: 5.5789179 | H33: 6.7976258 | I33: 3.9565965 | J33: 4.913442 | K33: 7.1705897 | L33: 6.3172195 | M33: 8.5294431 | N33: 4.4740973 | O33: 5.2310293 | P33: 5.0633364 | Q33: 7.9674852 | R33: 5.7391615 | S33: 2.9395678 | T33: 7.3110177 | U33: 4.6145675 | V33: 4.9712157 | W33: 2.0526946 | X33: 0.13334405 | Y33: -1.3717729 | Z33: 0.27561638 | AA33: -3.9387379 | AB33: -4.0421214 | AC33: -0.2006657 | AD33: -1.6763898 | AE33: -2.5738842 | AF33: 2.4634846 | AG33: 2.909498 | AH33: 3.790131 | AI33: 4.6357874 | AJ33: 5.2665267 | AK33: 1.6464982 | AL33: 4.2692961 | AM33: 4.6672651 | AN33: 4.6782766 | AO33: 4.361342 | AP33: 4.9542087 | AQ33: 5.0293548 | AR33: 0.42688542 | AS33: 2.5078108 | AT33: 1.6837991 | AU33: 2.4855657 | AV33: 2.7113398 | AW33: 4.1732956 | AX33: 4.4214331 | AY33: 4.7970088 | AZ33: 4.5643843 | BA33: 6.1484979 | BB33: 3.3569996 | BC33: 4.1267226 | BD33: 5.2040924 | BE33: 5.1222756 | BF33: 6.7960114 | BG33: 5.4605695 | BH33: 4.8571873 | BI33: 4.2639208 | BJ33: 4.1952063 | BK33: 4.2236235 | BL33: 2.2167058 | BM33: -8.7378844 | BN33: 6.1058042
A34: Brazil | B34: BRA | C34: GDP growth (annual %) | D34: NY.GDP.MKTP.KD.ZG | F34: 8.6 | G34: 6.6 | H34: 0.6 | I34: 3.4 | J34: 2.4 | K34: 6.7 | L34: 4.2 | M34: 9.8 | N34: 9.5 | O34: 10.4 | P34: 11.342922 | Q34: 11.940348 | R34: 13.968722 | S34: 8.1539387 | T34: 5.1666491 | U34: 10.25713 | V34: 4.9343281 | W34: 4.9698977 | X34: 6.7595601 | Y34: 9.2 | Z34: -4.25 | AA34: 0.83 | AB34: -2.93 | AC34: 5.4 | AD34: 7.85 | AE34: 7.49 | AF34: 3.53 | AG34: -0.06 | AH34: 3.16 | AI34: -4.35 | AJ34: 1.0321896 | AK34: -0.54407205 | AL34: 4.92469 | AM34: 5.8528704 | AN34: 4.2237936 | AO34: 2.2088641 | AP34: 3.394846 | AQ34: 0.3380979 | AR34: 0.46793757 | AS34: 4.3879494 | AT34: 1.3898964 | AU34: 3.0534619 | AV34: 1.140829 | AW34: 5.7599646 | AX34: 3.2021321 | AY34: 3.9619887 | AZ34: 6.0698706 | BA34: 5.0941954 | BB34: -0.125812 | BC34: 7.5282258 | BD34: 3.9744231 | BE34: 1.921176 | BF34: 3.0048227 | BG34: 0.50395574 | BH34: -3.5457634 | BI34: -3.2759169 | BJ34: 1.3228691 | BK34: 1.7836668 | BL34: 1.2207778 | BM34: -3.8786763 | BN34: 4.6194216
A35: Barbados | B35: BRB | C35: GDP growth (annual %) | D35: NY.GDP.MKTP.KD.ZG | T35: -1.9 | U35: 4.360211 | V35: 3.6422058 | W35: 4.8769393 | X35: 7.8930081 | Y35: 4.3730648 | Z35: -1.8997516 | AA35: -4.9009385 | AB35: 0.50125313 | AC35: 3.6003741 | AD35: 1.0982398 | AE35: 5.1041667 | AF35: 2.590967 | AG35: 3.5053823 | AH35: 3.6 | AI35: -3.3075933 | AJ35: -3.8999068 | AK35: -5.6925208 | AL35: 0.793068 | AM35: 2.0107825 | AN35: 2.013998 | AO35: 3.9764772 | AP35: 4.7401023 | AQ35: 3.7284649 | AR35: 0.33465543 | AS35: 4.4471896 | AT35: -2.3654642 | AU35: 0.78740157 | AV35: 2.1754808 | AW35: 1.4115986 | AX35: 3.9554576 | AY35: 6.1127126 | AZ35: 2.0776489 | BA35: 0.64009814 | BB35: -5.0177445 | BC35: -2.3651647 | BD35: -0.68777907 | BE35: -0.43267913 | BF35: -1.4474068 | BG35: -0.087262953 | BH35: 2.4726199 | BI35: 2.5330249 | BJ35: 0.45629051 | BK35: -1.0271391 | BL35: -0.13114725 | BM35: -13.311022 | BN35: -0.18927287
A36: Brunei Darussalam | B36: BRN | C36: GDP growth (annual %) | D36: NY.GDP.MKTP.KD.ZG | T36: 0.35546307 | U36: 20.155394 | V36: 10.916697 | W36: 6.7758344 | X36: 22.562429 | Y36: -6.996703 | Z36: -19.826716 | AA36: 3.9566549 | AB36: 0.50146597 | AC36: 0.59987654 | AD36: -1.4907491 | AE36: -2.71547 | AF36: 2.0091298 | AG36: 1.0973672 | AH36: -1.0741786 | AI36: 1.0894205 | AJ36: 3.1459414 | AK36: 4.7585808 | AL36: 0.30457287 | AM36: 3.1453974 | AN36: 4.4787073 | AO36: 2.8783177 | AP36: -1.4711716 | AQ36: -0.55850885 | AR36: 3.0521571 | AS36: 2.8494219 | AT36: 2.7440405 | AU36: 3.872097 | AV36: 2.9039555 | AW36: 0.50431825 | AX36: 0.38750721 | AY36: 4.3977197 | AZ36: 0.15458181 | BA36: -1.9397146 | BB36: -1.7645355 | BC36: 2.5989657 | BD36: 3.7453184 | BE36: 0.91284167 | BF36: -2.1260285 | BG36: -2.5083526 | BH36: -0.39238375 | BI36: -2.4779177 | BJ36: 1.3286026 | BK36: 0.052237791 | BL36: 3.8691099 | BM36: 1.1335733 | BN36: -1.5907625
A37: Bhutan | B37: BTN | C37: GDP growth (annual %) | D37: NY.GDP.MKTP.KD.ZG | Z37: 15.122295 | AA37: 3.4397738 | AB37: 10.431016 | AC37: 4.556659 | AD37: 4.028533 | AE37: 11.392198 | AF37: 29.054324 | AG37: 4.767373 | AH37: 7.3555673 | AI37: 10.383118 | AJ37: -0.40787569 | AK37: 4.6008914 | AL37: 1.9863666 | AM37: 4.9515037 | AN37: 7.0741173 | AO37: 5.5651729 | AP37: 5.3738385 | AQ37: 5.9140308 | AR37: 7.983972 | AS37: 3.3550683 | AT37: 8.3489545 | AU37: 10.992282 | AV37: 7.8233024 | AW37: 6.0087422 | AX37: 7.2872494 | AY37: 6.9997381 | AZ37: 18.360854 | BA37: 4.7994606 | BB37: 6.7483337 | BC37: 11.945896 | BD37: 7.982617 | BE37: 5.1184009 | BF37: 2.1199726 | BG37: 5.7764957 | BH37: 6.6422321 | BI37: 8.1270335 | BJ37: 4.6518347 | BK37: 3.0551298 | BL37: 5.75517 | BM37: -10.009699 | BN37: 4.0876188
A38: Botswana | B38: BWA | C38: GDP growth (annual %) | D38: NY.GDP.MKTP.KD.ZG | F38: 6.3432837 | G38: 6.6666678 | H38: 5.9210451 | I38: 6.8323009 | J38: 5.8139551 | K38: 6.3440191 | L38: 5.9245599 | M38: 10.567057 | N38: 15.123405 | O38: 17.120268 | P38: 25.821107 | Q38: 26.361941 | R38: 21.303184 | S38: 8.7977952 | T38: 8.4462504 | U38: 10.647377 | V38: 12.01204 | W38: 14.332802 | X38: 12.148589 | Y38: 11.986901 | Z38: 9.0648575 | AA38: 12.165532 | AB38: 13.146729 | AC38: 8.5453836 | AD38: 7.1252713 | AE38: 8.1729243 | AF38: 11.881928 | AG38: 19.44997 | AH38: 13.059406 | AI38: 6.7728219 | AJ38: 7.4587092 | AK38: 2.9170703 | AL38: 1.916107 | AM38: 3.6279161 | AN38: 7.0304103 | AO38: 5.8298 | AP38: 8.3258909 | AQ38: 0.44366352 | AR38: 9.6672408 | AS38: 1.9876958 | AT38: 0.25057396 | AU38: 6.0695309 | AV38: 4.6258947 | AW38: 2.7058217 | AX38: 4.5566457 | AY38: 8.3638711 | AZ38: 5.7925558 | BA38: 3.252073 | BB38: -14.144235 | BC38: 10.122209 | BD38: 6.8385297 | BE38: -0.17090076 | BF38: 11.102824 | BG38: 5.6969645 | BH38: -4.8509918 | BI38: 7.201819 | BJ38: 4.1130561 | BK38: 4.1898341 | BL38: 3.0325987 | BM38: -8.7264086 | BN38: 11.370022
A39: Central African Republic | B39: CAF | C39: GDP growth (annual %) | D39: NY.GDP.MKTP.KD.ZG | F39: 4.9535538 | G39: -3.7138002 | H39: -0.70701075 | I39: 2.0803246 | J39: 0.94757871 | K39: 0.64478372 | L39: 4.6766131 | M39: 1.4041132 | N39: 7.0915425 | O39: 2.3328809 | P39: 1.1302024 | Q39: -0.00086717483 | R39: 1.88894 | S39: 6.3390336 | T39: 0.4049871 | U39: 5.432519 | V39: 3.8062349 | W39: 1.2092354 | X39: -2.4651378 | Y39: -4.4786388 | Z39: -1.5444657 | AA39: 7.7157836 | AB39: -8.1265136 | AC39: 9.4817267 | AD39: 3.9272195 | AE39: 3.5779793 | AF39: -4.9389879 | AG39: 1.7101653 | AH39: 1.9772704 | AI39: -2.1475281 | AJ39: -0.55254301 | AK39: -6.4240782 | AL39: 0.33527568 | AM39: 4.8999494 | AN39: 7.2000456 | AO39: -4.000093 | AP39: 5.299936 | AQ39: 4.7001424 | AR39: 3.5999749 | AS39: -2.4894324 | AT39: 4.464739 | AU39: 3.6165422 | AV39: -5.3974852 | AW39: 5.9948842 | AX39: 0.90821051 | AY39: 4.7710854 | AZ39: 4.6075349 | BA39: 2.054131 | BB39: 8.5872604 | BC39: 4.6308184 | BD39: 4.1946153 | BE39: 5.0537613 | BF39: -36.391977 | BG39: 0.081070515 | BH39: 4.337121 | BI39: 4.7503168 | BJ39: 4.5272782 | BK39: 3.7894436 | BL39: 3.1 | BM39: 0.9 | BN39: 0.90000001
A40: Canada | B40: CAN | C40: GDP growth (annual %) | D40: NY.GDP.MKTP.KD.ZG | F40: 3.1632917 | G40: 7.4253848 | H40: 5.3495465 | I40: 6.6428944 | J40: 6.3167142 | K40: 6.7049918 | L40: 3.091206 | M40: 4.9956666 | N40: 5.0454564 | AQ40: 3.8961518 | AR40: 5.1629136 | AS40: 5.1776357 | AT40: 1.7899729 | AU40: 3.0180505 | AV40: 1.8015181 | AW40: 3.0869808 | AX40: 3.2042004 | AY40: 2.6343038 | AZ40: 2.0694099 | BA40: 1.0076227 | BB40: -2.9284002 | BC40: 3.0894946 | BD40: 3.1468814 | BE40: 1.7622225 | BF40: 2.3291225 | BG40: 2.8700361 | BH40: 0.65917686 | BI40: 1.0013944 | BJ40: 3.0398802 | BK40: 2.7770406 | BL40: 1.879592 | BM40: -5.2330243 | BN40: 4.5408873
A41: Central Europe and the Baltics | B41: CEB | C41: GDP growth (annual %) | D41: NY.GDP.MKTP.KD.ZG | AJ41: -9.7709513 | AK41: -1.9596003 | AL41: 1.546239 | AM41: 4.1050638 | AN41: 5.71251 | AO41: 4.556041 | AP41: 2.3128637 | AQ41: 2.6842497 | AR41: 1.9140517 | AS41: 3.9526317 | AT41: 3.0783451 | AU41: 3.6109487 | AV41: 4.0845855 | AW41: 5.8394135 | AX41: 5.0170657 | AY41: 6.5861081 | AZ41: 6.4301436 | BA41: 3.9358441 | BB41: -3.503286 | BC41: 1.437277 | BD41: 3.5154589 | BE41: 0.82629347 | BF41: 0.66380776 | BG41: 3.2150237 | BH41: 4.0273672 | BI41: 2.7496808 | BJ41: 5.1049203 | BK41: 4.9402078 | BL41: 3.9397671 | BM41: -3.3937589 | BN41: 6.1474372
A42: Switzerland | B42: CHE | C42: GDP growth (annual %) | D42: NY.GDP.MKTP.KD.ZG | Z42: 1.6013359 | AA42: -1.3094175 | AB42: 0.63907954 | AC42: 3.0084563 | AD42: 3.6735959 | AE42: 1.8586329 | AF42: 1.585478 | AG42: 3.2775964 | AH42: 4.330794 | AI42: 3.4745521 | AJ42: -0.91581667 | AK42: -0.043733003 | AL42: -0.12598339 | AM42: 1.2697577 | AN42: 0.48086645 | AO42: 0.47128002 | AP42: 2.2613252 | AQ42: 3.0299692 | AR42: 1.6627013 | AS42: 3.9587197 | AT42: 1.575662 | AU42: -0.073217084 | AV42: -0.032398477 | AW42: 2.7017092 | AX42: 2.749699 | AY42: 4.0736284 | AZ42: 3.9163758 | BA42: 2.8079836 | BB42: -2.2973746 | BC42: 3.2433973 | BD42: 1.8131082 | BE42: 1.1792538 | BF42: 1.7921441 | BG42: 2.3498813 | BH42: 1.6446277 | BI42: 2.0686897 | BJ42: 1.3627996 | BK42: 2.8604458 | BL42: 1.1419823 | BM42: -2.3755633 | BN42: 4.2217166
A43: Channel Islands | B43: CHI | C43: GDP growth (annual %) | D43: NY.GDP.MKTP.KD.ZG | AR43: 3.7702643 | AS43: 5.8266411 | AT43: -1.5129612 | AU43: -1.6322067 | AV43: -3.2021556 | AW43: 0.22419656 | AX43: 1.3777343 | AY43: 4.8822998 | AZ43: 5.898329
A44: Chile | B44: CHL | C44: GDP growth (annual %) | D44: NY.GDP.MKTP.KD.ZG | F44: 5.2452719 | G44: 4.0266856 | H44: 5.8401401 | I44: 2.5572205 | J44: 0.95027251 | K44: 11.236242 | L44: 3.6159999 | M44: 3.5920133 | N44: 3.9379833 | O44: 1.828967 | P44: 9.4226862 | Q44: -1.0199478 | R44: -5.0292484 | S44: 2.3821493 | T44: -12.912101 | U44: 3.832584 | V44: 10.444686 | W44: 7.7011036 | X44: 8.4183047 | Y44: 7.9866208 | Z44: 6.5253704 | AA44: -11.014305 | AB44: -5.0174205 | AC44: 4.1036832 | AD44: 4.0099162 | AE44: 5.3776923 | AF44: 6.4604685 | AG44: 7.3451105 | AH44: 9.9233829 | AI44: 3.3335655 | AJ44: 7.8043922 | AK44: 11.166708 | AL44: 6.5887838 | AM44: 5.030198 | AN44: 8.9332959 | AO44: 6.8029166 | AP44: 7.3917393 | AQ44: 4.1808866 | AR44: -0.2736314 | AS44: 4.9716215 | AT44: 3.1540349 | AU44: 3.2027991 | AV44: 4.7232453 | AW44: 6.6742542 | AX44: 5.8370457 | AY44: 6.0499908 | AZ44: 5.168231 | BA44: 3.7893928 | BB44: -1.1180372 | BC44: 5.851651 | BD44: 6.2238968 | BE44: 6.15534 | BF44: 3.3085082 | BG44: 1.7926495 | BH44: 2.1519425 | BI44: 1.7530387 | BJ44: 1.3576954 | BK44: 3.9900295 | BL44: 0.77053958 | BM44: -5.9782241 | BN44: 11.668225
A45: China | B45: CHN | C45: GDP growth (annual %) | D45: NY.GDP.MKTP.KD.ZG | F45: -27.27 | G45: -5.58 | H45: 10.3 | I45: 18.18 | J45: 16.95 | K45: 10.65 | L45: -5.77 | M45: -4.1 | N45: 16.94 | O45: 19.3 | P45: 7.06 | Q45: 3.81 | R45: 7.76 | S45: 2.31 | T45: 8.72 | U45: -1.57 | V45: 7.57 | W45: 11.325978 | X45: 7.5913247 | Y45: 7.834145 | Z45: 5.1127611 | AA45: 9.0171139 | AB45: 10.770203 | AC45: 15.19154 | AD45: 13.430678 | AE45: 8.9499618 | AF45: 11.657428 | AG45: 11.222595 | AH45: 4.2063344 | AI45: 3.9202514 | AJ45: 9.2627861 | AK45: 14.22453 | AL45: 13.883729 | AM45: 13.036807 | AN45: 10.953954 | AO45: 9.9225568 | AP45: 9.2367799 | AQ45: 7.8459518 | AR45: 7.6616515 | AS45: 8.4900934 | AT45: 8.3357335 | AU45: 9.1336308 | AV45: 10.03803 | AW45: 10.113621 | AX45: 11.394592 | AY45: 12.720956 | AZ45: 14.230861 | BA45: 9.6506789 | BB45: 9.3987256 | BC45: 10.635871 | BD45: 9.5508322 | BE45: 7.8637364 | BF45: 7.7661501 | BG45: 7.4257637 | BH45: 7.0413289 | BI45: 6.8487622 | BJ45: 6.9472008 | BK45: 6.7497738 | BL45: 5.9505008 | BM45: 2.2397019 | BN45: 8.1097926
A46: Cote d'Ivoire | B46: CIV | C46: GDP growth (annual %) | D46: NY.GDP.MKTP.KD.ZG | F46: 9.9325552 | G46: 1.2269945 | H46: 14.490356 | I46: 17.613088 | J46: -3.1096543 | K46: 11.57736 | L46: 4.5981518 | M46: 12.548249 | N46: 9.5392188 | O46: 10.375032 | P46: 9.4566377 | Q46: 4.236625 | R46: 5.9391975 | S46: 4.3273809 | T46: 8.2528864 | U46: 12.916397 | V46: 7.3144592 | W46: 10.909454 | X46: 2.3944075 | Y46: -10.957697 | Z46: 3.5004989 | AA46: 0.20082235 | AB46: -3.9002404 | AC46: -2.7012614 | AD46: 4.5012232 | AE46: 3.2593488 | AF46: -0.34897291 | AG46: 1.136484 | AH46: 2.9480049 | AI46: -1.0959084 | AJ46: 0.040925172 | AK46: -0.24456061 | AL46: -0.1924851 | AM46: 0.81120668 | AN46: 7.1257447 | AO46: 7.7293274 | AP46: 9.64884 | AQ46: 4.2639059 | AR46: 1.16686 | AS46: -0.26578946 | AT46: -2.1540125 | AU46: -2.7305265 | AV46: -4.7258666 | AW46: 3.1850382 | AX46: 0.99606556 | AY46: 2.8155786 | AZ46: 1.1014298 | BA46: 4.782666 | BB46: 3.6033216 | BC46: 6.8480494 | BD46: -5.3704472 | BE46: 7.6204118 | BF46: 10.760213 | BG46: 9.3719999 | BH46: 7.1940906 | BI46: 7.1792078 | BJ46: 7.3596381 | BK46: 6.8902843 | BL46: 6.2317095 | BM46: 1.9788212 | BN46: 7.03796
A47: Cameroon | B47: CMR | C47: GDP growth (annual %) | D47: NY.GDP.MKTP.KD.ZG | F47: 1.1836808 | G47: 3.0415591 | H47: 3.7425503 | I47: 3.5471597 | J47: 2.0260537 | K47: 4.6149556 | L47: -10.912066 | M47: 6.3463239 | N47: 4.9014795 | O47: 3.0920682 | P47: 3.4797078 | Q47: 2.6738433 | R47: 5.3556808 | S47: 10.734262 | T47: 11.245059 | U47: -5.4951384 | V47: 13.739872 | W47: 22.003005 | X47: 6.0351188 | Y47: -1.9652917 | Z47: 17.082682 | AA47: 7.5162026 | AB47: 6.8668306 | AC47: 7.4745725 | AD47: 8.0631617 | AE47: 6.7716631 | AF47: -2.1466502 | AG47: -7.823632 | AH47: -1.8191205 | AI47: -6.1056976 | AJ47: -3.8085994 | AK47: -3.1000032 | AL47: -7.9320666 | AM47: 1.8768092 | AN47: 2.8940014 | AO47: 4.2150721 | AP47: 4.5273138 | AQ47: 4.7255348 | AR47: 4.5113042 | AS47: 3.8324178 | AT47: 4.3242612 | AU47: 4.4770268 | AV47: 5.4531537 | AW47: 7.0488628 | AX47: 2.2282702 | AY47: 3.8095833 | AZ47: 4.327589 | BA47: 2.8476779 | BB47: 2.5792518 | BC47: 2.8990247 | BD47: 3.3792113 | BE47: 4.6259787 | BF47: 4.9955292 | BG47: 5.7198181 | BH47: 5.666953 | BI47: 4.5357942 | BJ47: 3.5411765 | BK47: 3.9555142 | BL47: 3.47506 | BM47: 0.25993292 | BN47: 3.6499169
A48: Congo, Dem. Rep. | B48: COD | C48: GDP growth (annual %) | D48: NY.GDP.MKTP.KD.ZG | F48: -10.851376 | G48: 21.200698 | H48: 5.2139901 | I48: -2.4402236 | J48: 0.99734879 | K48: 6.7754853 | L48: -0.98573866 | M48: 4.3326985 | N48: 9.3288374 | O48: -0.24505658 | P48: 6.0050181 | Q48: 0.15113551 | R48: 8.1372759 | S48: 3.1305859 | T48: -4.981631 | U48: -5.3090021 | V48: 0.7607936 | W48: -5.3452915 | X48: 0.43008826 | Y48: 2.1949129 | Z48: 2.3505241 | AA48: -0.45767761 | AB48: 1.4117037 | AC48: 5.541074 | AD48: 0.46785095 | AE48: 4.7172097 | AF48: 2.6756425 | AG48: 0.47038134 | AH48: -1.2660506 | AI48: -6.5683107 | AJ48: -8.4210515 | AK48: -10.500009 | AL48: -13.469051 | AM48: -3.8999968 | AN48: 0.69999883 | AO48: -1.0231726 | AP48: -5.6170466 | AQ48: -1.624154 | AR48: -4.2701408 | AS48: -6.9109273 | AT48: -2.100173 | AU48: 2.9477652 | AV48: 5.5778223 | AW48: 6.7383739 | AX48: 6.1351512 | AY48: 5.3209796 | AZ48: 6.2594778 | BA48: 6.2258943 | BB48: 2.855064 | BC48: 7.1079766 | BD48: 6.8746709 | BE48: 7.0868989 | BF48: 8.4819566 | BG48: 9.4702881 | BH48: 6.9161671 | BI48: 2.3993989 | BJ48: 3.7269477 | BK48: 5.8211211 | BL48: 4.3845289 | BM48: 1.7354228 | BN48: 6.200154
A49: Congo, Rep. | B49: COG | C49: GDP growth (annual %) | D49: NY.GDP.MKTP.KD.ZG | F49: 8.3507267 | G49: 5.2023088 | H49: -4.0293004 | I49: 3.8167963 | J49: 3.6764677 | K49: 1.3589825 | L49: 2.1162721 | M49: 7.6313262 | N49: 7.5485252 | O49: 6.3584702 | P49: 7.7530359 | Q49: 8.6175508 | R49: 8.2311889 | S49: 7.8855208 | T49: 7.7315968 | U49: 0.91628675 | V49: -8.953428 | W49: 6.359747 | X49: 9.8132247 | Y49: 17.636605 | Z49: 17.619722 | AA49: 23.5977 | AB49: 5.8539628 | AC49: 6.9761311 | AD49: -1.1856609 | AE49: -6.8615264 | AF49: 0.18937664 | AG49: 1.7662634 | AH49: 2.5998765 | AI49: 1.0000036 | AJ49: 2.3953675 | AK49: 2.6119481 | AL49: -0.97968321 | AM49: -5.4930757 | AN49: 3.9853244 | AO49: 4.2904816 | AP49: -0.62481215 | AQ49: 3.7375528 | AR49: -2.5821994 | AS49: 7.5759804 | AT49: 3.8026019 | AU49: 4.5818701 | AV49: 0.81326408 | AW49: 3.4766316 | AX49: 7.755759 | AY49: 7.9862384 | AZ49: -6.6139948 | BA49: 6.306376 | BB49: 11.637289 | BC49: 9.9312654 | BD49: 2.2059194 | BE49: 9.9471531 | BF49: -0.71243445 | BG49: 6.7166793 | BH49: -3.5505818 | BI49: -10.783238 | BJ49: -4.3825309 | BK49: -4.8053516 | BL49: -0.086885958 | BM49: -6.2393196 | BN49: -2.2000026
A50: Colombia | B50: COL | C50: GDP growth (annual %) | D50: NY.GDP.MKTP.KD.ZG | F50: 5.089217 | G50: 5.4118896 | H50: 3.2867076 | I50: 6.1669413 | J50: 3.6000114 | K50: 5.2367359 | L50: 4.1348642 | M50: 5.933118 | N50: 6.1025173 | O50: 6.207797 | P50: 5.9607279 | Q50: 7.6691475 | R50: 6.722955 | S50: 5.7457572 | T50: 2.3232553 | U50: 4.7283687 | V50: 4.1585055 | W50: 8.4699008 | X50: 5.379119 | Y50: 4.0873537 | Z50: 2.2768727 | AA50: 0.94842079 | AB50: 1.573956 | AC50: 3.3506837 | AD50: 3.1071062 | AE50: 5.8240761 | AF50: 5.3689321 | AG50: 4.0641732 | AH50: 3.4140961 | AI50: 4.2819983 | AJ50: 2.0016076 | AK50: 4.0449294 | AL50: 5.3854099 | AM50: 5.8146619 | AN50: 5.2024376 | AO50: 2.0558547 | AP50: 3.4302937 | AQ50: 0.56978409 | AR50: -4.2040152 | AS50: 2.9248615 | AT50: 1.6778983 | AU50: 2.5039805 | AV50: 3.9182719 | AW50: 5.3330221 | AX50: 4.8287611 | AY50: 6.7168687 | AZ50: 6.7381947 | BA50: 3.2834462 | BB50: 1.1396486 | BC50: 4.494659 | BD50: 6.947892 | BE50: 3.9126358 | BF50: 5.1339935 | BG50: 4.49903 | BH50: 2.9559014 | BI50: 2.0873825 | BJ50: 1.3593609 | BK50: 2.5643243 | BL50: 3.1868554 | BM50: -7.0481512 | BN50: 10.677013
A51: Comoros | B51: COM | C51: GDP growth (annual %) | D51: NY.GDP.MKTP.KD.ZG | Z51: 3.864929 | AA51: 6.383317 | AB51: 4.8214019 | AC51: 4.1103 | AD51: 2.2799608 | AE51: 1.8676122 | AF51: 1.6377842 | AG51: 2.6873794 | AH51: -3.1802565 | AI51: 5.0912364 | AJ51: -5.3956371 | AK51: 8.5309818 | AL51: 3.0060613 | AM51: -5.276783 | AN51: 3.6102064 | AO51: -1.2916889 | AP51: 4.0301537 | AQ51: 1.2825158 | AR51: 1.9244087 | AS51: 10.847879 | AT51: 2.3329071 | AU51: 2.3249449 | AV51: 2.1038716 | AW51: 1.9196598 | AX51: 2.8375479 | AY51: 2.6469555 | AZ51: 0.80004235 | BA51: 3.9646112 | BB51: 3.2407407 | BC51: 3.7777667 | BD51: 4.1435067 | BE51: 3.1684099 | BF51: 4.4662473 | BG51: 2.1066576 | BH51: 1.1473508 | BI51: 3.3204466 | BJ51: 3.8157629 | BK51: 3.6424511 | BL51: 1.7607802 | BM51: -0.19555683 | BN51: 2.1121956
A52: Cabo Verde | B52: CPV | C52: GDP growth (annual %) | D52: NY.GDP.MKTP.KD.ZG | Z52: 8.4515624 | AA52: 2.8250301 | AB52: 9.5207498 | AC52: 3.7832707 | AD52: 8.6420866 | AE52: 2.8714554 | AF52: 4.3090637 | AG52: 5.9968549 | AH52: 5.6979494 | AI52: 0.69217187 | AJ52: 1.4041469 | AK52: 10.937647 | AL52: 8.7083114 | AM52: 19.182642 | AN52: 14.211636 | AO52: 11.346525 | AP52: 11.118426 | AQ52: 12.517286 | AR52: 11.222649 | AS52: 14.284869 | AT52: 2.2316545 | AU52: 5.2508912 | AV52: 4.1762593 | AW52: 10.197073 | AX52: 6.912458 | AY52: 7.9837504 | AZ52: 15.170688 | BA52: 6.6505205 | BB52: -1.270426 | BC52: 1.4667901 | BD52: 3.9688863 | BE52: 1.0819183 | BF52: 0.8027976 | BG52: 0.61121267 | BH52: 1.0068637 | BI52: 4.7057915 | BJ52: 3.7020392 | BK52: 4.5311617 | BL52: 5.6677525 | BM52: -14.783405 | BN52: 6.9524487
A53: Costa Rica | B53: CRI | C53: GDP growth (annual %) | D53: NY.GDP.MKTP.KD.ZG | F53: 1.8792766 | G53: 5.4423914 | H53: 6.8989234 | I53: 3.6590483 | J53: 8.1905276 | K53: 6.969319 | L53: 5.6501259 | M53: 8.4733043 | N53: 5.4917999 | O53: 7.5031343 | P53: 6.7785054 | Q53: 8.1780451 | R53: 7.7089158 | S53: 5.5449 | T53: 2.100071 | U53: 5.5175644 | V53: 8.9044744 | W53: 6.2676868 | X53: 4.939124 | Y53: 0.7518954 | Z53: -2.2616555 | AA53: -7.2855688 | AB53: 2.8629927 | AC53: 8.0241079 | AD53: 0.72160173 | AE53: 5.5362508 | AF53: 4.7645333 | AG53: 3.4321474 | AH53: 5.6659755 | AI53: 3.5530634 | AJ53: 2.265655 | AK53: 9.2011037 | AL53: 7.0971912 | AM53: 4.5190284 | AN53: 4.153953 | AO53: 1.3504595 | AP53: 5.4761658 | AQ53: 7.1553086 | AR53: 4.2148112 | AS53: 3.8687181 | AT53: 3.4911699 | AU53: 3.4168764 | AV53: 4.3171799 | AW53: 4.4245996 | AX53: 3.9766664 | AY53: 7.3266954 | AZ53: 8.215132 | BA53: 4.7381749 | BB53: -0.87345594 | BC53: 5.3603435 | BD53: 4.4031592 | BE53: 4.8825924 | BF53: 2.4947661 | BG53: 3.5421099 | BH53: 3.652081 | BI53: 4.2043233 | BJ53: 4.157699 | BK53: 2.6159044 | BL53: 2.4175118 | BM53: -4.0509082 | BN53: 7.5795653
A54: Caribbean small states | B54: CSS | C54: GDP growth (annual %) | D54: NY.GDP.MKTP.KD.ZG | F54: 10.101353 | G54: 4.5994374 | H54: 3.7796172 | I54: 8.732197 | J54: 6.2420056 | K54: 7.4835964 | L54: 4.454195 | M54: 5.9187341 | N54: 5.6011759 | O54: 4.4862174 | P54: 2.1638971 | Q54: 7.2312934 | R54: -0.58948946 | S54: -3.1913356 | T54: -1.2221457 | U54: 1.2116059 | V54: 3.8368785 | W54: 5.7714135 | X54: 5.1957324 | Y54: 2.4715084 | Z54: 0.935776 | AA54: 1.0251088 | AB54: -2.3870596 | AC54: 1.0157528 | AD54: 0.093785599 | AE54: 1.3526951 | AF54: 1.8898408 | AG54: 2.2272057 | AH54: 4.1951807 | AI54: 0.93848614 | AJ54: 1.3621474 | AK54: 2.2124805 | AL54: 2.9480074 | AM54: 2.7870605 | AN54: 2.910054 | AO54: 3.4665736 | AP54: 4.0510465 | AQ54: 1.1846572 | AR54: 5.0711363 | AS54: 3.7664301 | AT54: 2.0442741 | AU54: 3.5849822 | AV54: 5.5900201 | AW54: 3.9335769 | AX54: 3.6074284 | AY54: 6.7725935 | AZ54: 3.355791 | BA54: 1.1925918 | BB54: -3.5382996 | BC54: 1.316239 | BD54: 1.083137 | BE54: 3.1830538 | BF54: 1.4195281 | BG54: 2.1390373 | BH54: 0.23042085 | BI54: -1.8845739 | BJ54: -0.4292257 | BK54: 1.3252143 | BL54: 1.2651046 | BM54: -9.4283713 | BN54: 5.348923
A55: Cuba | B55: CUB | C55: GDP growth (annual %) | D55: NY.GDP.MKTP.KD.ZG | P55: 8.583859 | Q55: 4.8266858 | R55: 3.4344885 | S55: 0.98449182 | T55: 9.4764261 | U55: 5.4279605 | V55: 8.7095029 | W55: 6.5959986 | X55: 1.0881833 | Y55: -4.849443 | Z55: 19.688334 | AA55: 8.918235 | AB55: 5.4114707 | AC55: 7.9297165 | AD55: 1.5966746 | AE55: 0.095303386 | AF55: -2.4021725 | AG55: 3.7055399 | AH55: 0.68008323 | AI55: -2.9485649 | AJ55: -10.692697 | AK55: -11.580603 | AL55: -14.878181 | AM55: 0.71693031 | AN55: 2.4572012 | AO55: 7.8387497 | AP55: 2.783425 | AQ55: 0.15914605 | AR55: 6.1887553 | AS55: 5.9147602 | AT55: 3.1850299 | AU55: 1.4248213 | AV55: 3.7927402 | AW55: 5.7705381 | AX55: 11.201656 | AY55: 12.065863 | AZ55: 7.262137 | BA55: 4.116828 | BB55: 1.4513054 | BC55: 2.3903523 | BD55: 2.8023008 | BE55: 3.0149003 | BF55: 2.7476026 | BG55: 1.0475766 | BH55: 4.438142 | BI55: 0.51376147 | BJ55: 1.8090544 | BK55: 2.2484804 | BL55: -0.16483998 | BM55: -10.948341 | BN55: 1.2540929
A56: Curacao | B56: CUW | C56: GDP growth (annual %) | D56: NY.GDP.MKTP.KD.ZG | AT56: -0.6957537 | AU56: 0.39706522 | AV56: 0.28818668 | AW56: 0.20846107 | AX56: 0.67642535 | AY56: 1.6359347 | AZ56: 2.4699632 | BA56: 2.1880431 | BB56: -0.53130824 | BC56: 0.082306609 | BD56: 0.61260762 | BE56: -0.065889568 | BF56: -0.81168656 | BG56: -1.2013617 | BH56: 0.29094872 | BI56: -0.87300758 | BJ56: -1.7322257 | BK56: -2.1668815 | BL56: -3.3717992 | BM56: -18.438472 | BN56: 4.2324046
A57: Cayman Islands | B57: CYM | C57: GDP growth (annual %) | D57: NY.GDP.MKTP.KD.ZG | AZ57: 3.1626252 | BA57: -0.3574012 | BB57: -7.2004824 | BC57: -2.7156353 | BD57: 1.1690622 | BE57: 1.2297537 | BF57: 1.279331 | BG57: 2.654528 | BH57: 2.8331222 | BI57: 3.2399743 | BJ57: 3.1840459 | BK57: 4.2672675 | BL57: 3.8730759 | BM57: -5.6839756 | BN57: 1.8392564
A58: Cyprus | B58: CYP | C58: GDP growth (annual %) | D58: NY.GDP.MKTP.KD.ZG | U58: 20.266292 | V58: 16.362001 | W58: 7.7774034 | X58: 9.9055694 | Y58: 5.7532447 | Z58: 2.5169984 | AA58: 6.021709 | AB58: 5.5821817 | AC58: 8.7578944 | AD58: 4.8825408 | AE58: 3.7039503 | AF58: 7.0652508 | AG58: 8.6467778 | AH58: 7.9474255 | AI58: 7.4039995 | AJ58: 0.7395012 | AK58: 9.399999 | AL58: 0.70000049 | AM58: 5.8999987 | AN58: 8.3624693 | AO58: 1.2485816 | AP58: 2.6408946 | AQ58: 6.1108467 | AR58: 4.9979604 | AS58: 5.9653103 | AT58: 3.9525605 | AU58: 3.7229565 | AV58: 2.6232861 | AW58: 5.0263439 | AX58: 4.8530038 | AY58: 4.7138287 | AZ58: 5.0980685 | BA58: 3.646812 | BB58: -2.0152624 | BC58: 2.283545 | BD58: 0.41671276 | BE58: -3.4473814 | BF58: -6.5874823 | BG58: -1.7760619 | BH58: 3.4189232 | BI58: 6.5735802 | BJ58: 5.7334761 | BK58: 5.6478582 | BL58: 5.5294285 | BM58: -4.3724742 | BN58: 6.638927
A59: Czechia | B59: CZE | C59: GDP growth (annual %) | D59: NY.GDP.MKTP.KD.ZG | AJ59: -11.614942 | AK59: -0.50654237 | AL59: 0.061904269 | AM59: 2.9093094 | AN59: 6.5008135 | AO59: 4.2654166 | AP59: -0.51833104 | AQ59: -0.3565666 | AR59: 1.3841489 | AS59: 4.0010286 | AT59: 3.0429766 | AU59: 1.5698553 | AV59: 3.5836885 | AW59: 4.814261 | AX59: 6.6016175 | AY59: 6.7669327 | AZ59: 5.5703389 | BA59: 2.686412 | BB59: -4.6573311 | BC59: 2.4349022 | BD59: 1.7603596 | BE59: -0.7850043 | BF59: -0.045903674 | BG59: 2.2621029 | BH59: 5.3883808 | BI59: 2.5372845 | BJ59: 5.1687243 | BK59: 3.2200881 | BL59: 3.0298787 | BM59: -5.502968 | BN59: 3.5442234
A60: Germany | B60: DEU | C60: GDP growth (annual %) | D60: NY.GDP.MKTP.KD.ZG | P60: 3.1326997 | Q60: 4.3003413 | R60: 4.7774869 | S60: 0.89006874 | T60: -0.86673889 | U60: 4.9492584 | V60: 3.3472181 | W60: 3.0084929 | X60: 4.1503633 | Y60: 1.4088286 | Z60: 0.52924056 | AA60: -0.39484077 | AB60: 1.5724102 | AC60: 2.8229478 | AD60: 2.3279353 | AE60: 2.2873392 | AF60: 1.4021516 | AG60: 3.7072357 | AH60: 3.8965517 | AI60: 5.2550061 | AJ60: 5.1082615 | AK60: 1.9230766 | AL60: -0.97684982 | AM60: 2.3918921 | AN60: 1.5441465 | AO60: 0.80582289 | AP60: 1.7921608 | AQ60: 2.0139328 | AR60: 1.8872612 | AS60: 2.912503 | AT60: 1.6814685 | AU60: -0.19797383 | AV60: -0.70011669 | AW60: 1.1750881 | AX60: 0.73170716 | AY60: 3.8164419 | AZ60: 2.9764551 | BA60: 0.95987913 | BB60: -5.6938363 | BC60: 4.1798825 | BD60: 3.9251927 | BE60: 0.41849759 | BF60: 0.4375913 | BG60: 2.2095434 | BH60: 1.4919315 | BI60: 2.2299999 | BJ60: 2.6802311 | BK60: 0.98123261 | BL60: 1.0566039 | BM60: -3.6967887 | BN60: 2.6269873
A61: Djibouti | B61: DJI | C61: GDP growth (annual %) | D61: NY.GDP.MKTP.KD.ZG | BG61: 7.0615432 | BH61: 7.5261089 | BI61: 7.1234323 | BJ61: 5.4580915 | BK61: 4.7744169 | BL61: 5.5451306 | BM61: 1.202022 | BN61: 4.8124774
A62: Dominica | B62: DMA | C62: GDP growth (annual %) | D62: NY.GDP.MKTP.KD.ZG | W62: 10.535746 | X62: -18.359285 | Y62: 13.383182 | Z62: 10.829331 | AA62: 4.1276835 | AB62: 2.556318 | AC62: 4.1966468 | AD62: 1.4209332 | AE62: 7.0733565 | AF62: 6.3075611 | AG62: 7.816623 | AH62: -0.19113651 | AI62: 5.4179836 | AJ62: 1.347765 | AK62: 2.0294208 | AL62: 2.1614141 | AM62: 0.034481485 | AN62: 3.0308626 | AO62: 3.1042023 | AP62: 2.1856277 | AQ62: 3.7742268 | AR62: 0.35407901 | AS62: 2.3402193 | AT62: -0.06384473 | AU62: -2.8279989 | AV62: 6.3531371 | AW62: 3.0506903 | AX62: 0.65586227 | AY62: 4.6594555 | AZ62: 6.3529724 | BA62: 7.121058 | BB62: -1.1695906 | BC62: 0.6726344 | BD62: -0.22355069 | BE62: -1.0590002 | BF62: -0.99994063 | BG62: 4.7537866 | BH62: -2.7315031 | BI62: 2.763648 | BJ62: -6.6189946 | BK62: 3.5475844 | BL62: 5.5024834 | BM62: -16.604912 | BN62: 6.6819257
A63: Denmark | B63: DNK | C63: GDP growth (annual %) | D63: NY.GDP.MKTP.KD.ZG | F63: 6.3788325 | G63: 5.6668222 | H63: 0.63702123 | I63: 9.2699382 | J63: 4.5552548 | K63: 2.7409101 | L63: 5.53037 | M63: 5.5530766 | N63: 6.5092484 | O63: 1.5968418 | P63: 3.0049956 | Q63: 3.9293853 | R63: 4.0929461 | S63: -1.1223943 | T63: -1.4566449 | U63: 5.9246062 | V63: 1.870291 | W63: 2.2263085 | X63: 3.8691115 | Y63: -0.48298634 | Z63: -0.66612416 | AA63: 3.684573 | AB63: 2.5960719 | AC63: 4.1661379 | AD63: 4.0037518 | AE63: 4.9041784 | AF63: 0.25426631 | AG63: -0.013601205 | AH63: 0.64518743 | AI63: 1.4752443 | AJ63: 1.393634 | AK63: 1.9570067 | AL63: 0.010687631 | AM63: 5.3324627 | AN63: 3.0275873 | AO63: 2.9000998 | AP63: 3.2608902 | AQ63: 2.2181587 | AR63: 2.9480222 | AS63: 3.7468626 | AT63: 0.823153 | AU63: 0.46634557 | AV63: 0.39005856 | AW63: 2.6682193 | AX63: 2.3366413 | AY63: 3.913008 | AZ63: 0.90923893 | BA63: -0.51201674 | BB63: -4.9065477 | BC63: 1.8709911 | BD63: 1.3367778 | BE63: 0.22649979 | BF63: 0.93334097 | BG63: 1.6193938 | BH63: 2.3425911 | BI63: 3.245957 | BJ63: 2.8217363 | BK63: 1.9895373 | BL63: 1.493487 | BM63: -1.9946076 | BN63: 4.8557076
A64: Dominican Republic | B64: DOM | C64: GDP growth (annual %) | D64: NY.GDP.MKTP.KD.ZG | F64: -2.3132487 | G64: 17.047241 | H64: 6.5029026 | I64: 6.7648651 | J64: -12.481834 | K64: 13.463345 | L64: 3.3275423 | M64: 0.23886048 | N64: 10.891446 | O64: 18.226683 | P64: 10.871466 | Q64: 10.394164 | R64: 12.895764 | S64: 6.0019029 | T64: 5.1932534 | U64: 6.7281226 | V64: 4.981784 | W64: 2.1406847 | X64: 4.5313992 | Y64: 7.9687385 | Z64: 4.2798675 | AA64: 1.6987086 | AB64: 4.6279463 | AC64: 1.252896 | AD64: -2.122535 | AE64: 3.5219932 | AF64: 10.117367 | AG64: 2.1559633 | AH64: 4.4005388 | AI64: -5.4543124 | AJ64: 0.94413889 | AK64: 11.220933 | AL64: 7.364513 | AM64: 2.6003543 | AN64: 5.6854307 | AO64: 5.9778251 | AP64: 8.8852691 | AQ64: 6.7144777 | AR64: 5.9400491 | AS64: 4.6617623 | AT64: 2.4595164 | AU64: 4.4951034 | AV64: -1.3457062 | AW64: 2.5701343 | AX64: 9.4282369 | AY64: 9.1743554 | AZ64: 7.4159517 | BA64: 3.2095043 | BB64: 0.94615517 | BC64: 8.3396511 | BD64: 3.133423 | BE64: 2.7173679 | BF64: 4.8752051 | BG64: 7.0504637 | BH64: 6.9270188 | BI64: 6.6592003 | BJ64: 4.6667047 | BK64: 6.9825276 | BL64: 5.052168 | BM64: -6.7202394 | BN64: 12.27199
A65: Algeria | B65: DZA | C65: GDP growth (annual %) | D65: NY.GDP.MKTP.KD.ZG | F65: -13.605441 | G65: -19.685042 | H65: 34.313729 | I65: 5.839413 | J65: 6.2068982 | K65: -4.8049709 | L65: 9.4529626 | M65: 10.796239 | N65: 8.4332803 | O65: 8.8626571 | P65: -11.331719 | Q65: 27.423969 | R65: 3.8131763 | S65: 7.4949177 | T65: 5.0453416 | U65: 8.3867565 | V65: 5.258586 | W65: 9.2148357 | X65: 7.4778266 | Y65: 0.79060697 | Z65: 2.9999961 | AA65: 6.4000041 | AB65: 5.400003 | AC65: 5.5999965 | AD65: 3.6999973 | AE65: 0.400001 | AF65: -0.69999753 | AG65: -1.0000055 | AH65: 4.4000022 | AI65: 0.80000058 | AJ65: -1.2000006 | AK65: 1.8000023 | AL65: -2.1000008 | AM65: -0.89999655 | AN65: 3.7999948 | AO65: 4.0999985 | AP65: 1.0999999 | AQ65: 5.1000036 | AR65: 3.2000016 | AS65: 3.8 | AT65: 3 | AU65: 5.6 | AV65: 7.2 | AW65: 4.3 | AX65: 5.9 | AY65: 1.7 | AZ65: 3.4 | BA65: 2.4 | BB65: 1.6 | BC65: 3.6 | BD65: 2.9 | BE65: 3.4 | BF65: 2.8 | BG65: 3.8 | BH65: 3.7 | BI65: 3.2 | BJ65: 1.3 | BK65: 1.2 | BL65: 1 | BM65: -5.1 | BN65: 3.5
A66: East Asia & Pacific (excluding high income) | B66: EAP | C66: GDP growth (annual %) | D66: NY.GDP.MKTP.KD.ZG | F66: -13.471078 | G66: -0.65691587 | H66: 6.3865051 | I66: 10.89684 | J66: 10.668826 | K66: 8.0799297 | L66: -1.4217248 | M66: 1.6878639 | N66: 11.424277 | O66: 13.422794 | P66: 6.7714015 | Q66: 4.9137337 | R66: 8.2661726 | S66: 3.8406064 | T66: 6.8433527 | U66: 2.84024 | V66: 7.5724504 | W66: 9.2556745 | X66: 7.1056349 | Y66: 7.5552273 | Z66: 5.6053936 | AA66: 6.4403318 | AB66: 7.739043 | AC66: 9.9489382 | AD66: 7.902625 | AE66: 7.1404042 | AF66: 9.1442947 | AG66: 9.7363109 | AH66: 5.715542 | AI66: 5.1646292 | AJ66: 8.0076074 | AK66: 11.169812 | AL66: 11.291593 | AM66: 10.932434 | AN66: 9.8747656 | AO66: 9.0633824 | AP66: 7.3443428 | AQ66: 2.8957367 | AR66: 6.3820636 | AS66: 7.6359098 | AT66: 6.9848415 | AU66: 8.0598577 | AV66: 8.9407706 | AW66: 9.1215542 | AX66: 9.9763292 | AY66: 11.07753 | AZ66: 12.487274 | BA66: 8.6184324 | BB66: 7.9837046 | BC66: 9.9223862 | BD66: 8.6504805 | BE66: 7.5751048 | BF66: 7.2958007 | BG66: 6.9846484 | BH66: 6.6889024 | BI66: 6.5858857 | BJ66: 6.7046924 | BK66: 6.5252828 | BL66: 5.7837024 | BM66: 1.2974309 | BN66: 7.2630894
A67: Early-demographic dividend | B67: EAR | C67: GDP growth (annual %) | D67: NY.GDP.MKTP.KD.ZG | F67: 4.39698 | G67: 3.4334695 | H67: 4.7044774 | I67: 8.0532558 | J67: 5.4756755 | K67: 4.0478646 | L67: 5.4498177 | M67: 6.5003644 | N67: 6.5275435 | O67: 8.6181436 | P67: 5.9447312 | Q67: 6.9024432 | R67: 7.3693562 | S67: 6.7081845 | T67: 2.4323219 | U67: 7.180442 | V67: 4.0954399 | W67: 1.25841 | X67: 4.0198442 | Y67: 3.5193753 | Z67: 3.8335032 | AA67: -0.24832294 | AB67: 0.4352647 | AC67: 2.1891062 | AD67: 0.75621836 | AE67: 2.9559077 | AF67: 2.7118742 | AG67: 3.560025 | AH67: 2.3346735 | AI67: 5.423289 | AJ67: 4.6205341 | AK67: 4.0154583 | AL67: 3.3672635 | AM67: 3.4025688 | AN67: 2.4016478 | AO67: 5.8852707 | AP67: 4.7495325 | AQ67: 2.3212345 | AR67: 2.0866209 | AS67: 4.4036119 | AT67: 1.0490621 | AU67: 1.8184952 | AV67: 5.4280617 | AW67: 6.2361971 | AX67: 5.9084273 | AY67: 5.979579 | AZ67: 5.7757943 | BA67: 3.4939035 | BB67: 0.81453633 | BC67: 6.5452773 | BD67: 4.9085133 | BE67: 4.2315529 | BF67: 4.1380752 | BG67: 4.167329 | BH67: 4.4685129 | BI67: 4.5003292 | BJ67: 4.5396121 | BK67: 3.8030315 | BL67: 2.328333 | BM67: -4.2844313 | BN67: 6.7876194
A68: East Asia & Pacific | B68: EAS | C68: GDP growth (annual %) | D68: NY.GDP.MKTP.KD.ZG | F68: 3.7763572 | G68: 5.4918671 | H68: 7.8051421 | I68: 10.556852 | J68: 6.9930578 | K68: 8.6773992 | L68: 7.696201 | M68: 9.5419824 | N68: 11.500595 | O68: 5.3882738 | P68: 5.3172955 | Q68: 7.2131135 | R68: 7.6611568 | S68: 0.87955773 | T68: 3.7048858 | U68: 4.257544 | V68: 5.4228123 | W68: 5.7980194 | X68: 5.9149447 | Y68: 3.7865614 | Z68: 4.6738169 | AA68: 4.1528119 | AB68: 4.4272761 | AC68: 6.160051 | AD68: 5.7002521 | AE68: 4.924775 | AF68: 6.2549768 | AG68: 7.5998187 | AH68: 5.1512572 | AI68: 5.069706 | AJ68: 4.8525621 | AK68: 4.2359308 | AL68: 4.2008204 | AM68: 5.2370135 | AN68: 5.668728 | AO68: 5.6195886 | AP68: 4.0544847 | AQ68: 0.44784303 | AR68: 3.7336497 | AS68: 5.3910523 | AT68: 3.3031047 | AU68: 4.3781181 | AV68: 4.9466186 | AW68: 5.8670891 | AX68: 5.8994364 | AY68: 6.4531769 | AZ68: 7.4672878 | BA68: 4.3860552 | BB68: 2.5599635 | BC68: 7.6093027 | BD68: 5.4650006 | BE68: 5.1794453 | BF68: 5.2421218 | BG68: 4.7585089 | BH68: 4.7156321 | BI68: 4.6696786 | BJ68: 5.0535617 | BK68: 4.7488799 | BL68: 3.9866162 | BM68: -0.16893444 | BN68: 5.8077413
A69: Europe & Central Asia (excluding high income) | B69: ECA | C69: GDP growth (annual %) | D69: NY.GDP.MKTP.KD.ZG | AI69: -1.4568328 | AJ69: -4.9100286 | AK69: -10.667887 | AL69: -5.9317528 | AM69: -11.167117 | AN69: -1.8587486 | AO69: -0.11210396 | AP69: 2.8590356 | AQ69: -1.5629327 | AR69: 2.3564643 | AS69: 8.4236219 | AT69: 2.6492427 | AU69: 5.4884541 | AV69: 6.9402875 | AW69: 8.2892411 | AX69: 7.3583984 | AY69: 8.1858041 | AZ69: 7.8034315 | BA69: 4.2331355 | BB69: -5.7278133 | BC69: 5.6410867 | BD69: 6.2863577 | BE69: 3.9754465 | BF69: 4.0464394 | BG69: 2.0500263 | BH69: 0.90534175 | BI69: 1.5761198 | BJ69: 3.9277019 | BK69: 3.1472595 | BL69: 2.2327198 | BM69: -1.1831826 | BN69: 7.0682997
A70: Europe & Central Asia | B70: ECS | C70: GDP growth (annual %) | D70: NY.GDP.MKTP.KD.ZG | P70: 3.6826644 | Q70: 4.7398972 | R70: 6.0225818 | S70: 2.1592689 | T70: -0.53568898 | U70: 4.691076 | V70: 2.8470969 | W70: 3.2300144 | X70: 3.7638804 | Y70: 1.3362164 | Z70: 0.4755484 | AA70: 0.95009068 | AB70: 1.9734441 | AC70: 2.6457183 | AD70: 2.8039978 | AE70: 2.7565465 | AF70: 3.0877208 | AG70: 4.2495559 | AH70: 3.534104 | AI70: 2.3255108 | AJ70: 0.43281471 | AK70: -0.51738723 | AL70: -0.73174174 | AM70: 1.2338885 | AN70: 2.1386385 | AO70: 1.694835 | AP70: 2.9995585 | AQ70: 2.5910472 | AR70: 2.8699364 | AS70: 4.3247366 | AT70: 2.1976794 | AU70: 1.5825662 | AV70: 1.791316 | AW70: 3.1777291 | AX70: 2.660388 | AY70: 3.8303619 | AZ70: 3.6450558 | BA70: 1.0266198 | BB70: -4.4394075 | BC70: 2.6851162 | BD70: 2.3287544 | BE70: 0.3511863 | BF70: 0.84961603 | BG70: 1.9235184 | BH70: 2.0823601 | BI70: 1.9359582 | BJ70: 2.8716995 | BK70: 2.178142 | BL70: 1.7901837 | BM70: -5.5983925 | BN70: 5.8573983
A71: Ecuador | B71: ECU | C71: GDP growth (annual %) | D71: NY.GDP.MKTP.KD.ZG | F71: 5.1244149 | G71: 4.9191469 | H71: 2.1063682 | I71: 7.4072454 | J71: 3.2750825 | K71: -0.33952564 | L71: 4.6210739 | M71: 1.9094384 | N71: 4.669238 | O71: 6.8719293 | P71: 6.2926062 | Q71: 5.0176407 | R71: 13.950682 | S71: 11.20851 | T71: 10.972154 | U71: 7.3971876 | V71: 1.6048421 | W71: 5.7068249 | X71: 3.7340484 | Y71: 3.708683 | Z71: 5.6128641 | AA71: 0.61484535 | AB71: -0.33686877 | AC71: 2.6252733 | AD71: 3.9350014 | AE71: 3.4647825 | AF71: -0.25909871 | AG71: 5.8904673 | AH71: 1.0057779 | AI71: 3.6799141 | AJ71: 4.2913424 | AK71: 2.1143107 | AL71: 1.9732181 | AM71: 4.2582505 | AN71: 2.2525488 | AO71: 1.7317475 | AP71: 4.3278648 | AQ71: 3.2665294 | AR71: -4.7393858 | AS71: 1.0918016 | AT71: 4.0156299 | AU71: 4.0967767 | AV71: 2.7228773 | AW71: 8.2110209 | AX71: 5.2913083 | AY71: 4.4035264 | AZ71: 2.190064 | BA71: 6.3571306 | BB71: 0.56649159 | BC71: 3.5252987 | BD71: 7.8681409 | BE71: 5.6419621 | BF71: 4.9465113 | BG71: 3.7888685 | BH71: 0.098872608 | BI71: -1.226384 | BJ71: 2.3683865 | BK71: 1.2892919 | BL71: 0.012105103 | BM71: -7.7876071 | BN71: 4.2352512
A72: Egypt, Arab Rep. | B72: EGY | C72: GDP growth (annual %) | D72: NY.GDP.MKTP.KD.ZG | F72: 5.1611141 | G72: 3.8756167 | H72: 10.518093 | I72: 11.507577 | J72: 4.9140423 | K72: 5.0464037 | L72: 0.80526413 | M72: -1.6067923 | N72: 5.2795175 | O72: 5.598515 | P72: 4.0573463 | Q72: 3.0556806 | R72: 3.5068302 | S72: 1.5589386 | T72: 8.9391472 | U72: 13.279689 | V72: 9.0030443 | W72: 8.6287676 | X72: 4.5476896 | Y72: 10.011329 | Z72: 7.3485539 | AA72: 9.9071711 | AB72: 5.0944068 | AC72: 9.7457627 | AD72: 5.7915058 | AE72: 4.7445255 | AF72: 3.8327526 | AG72: 5.4613205 | AH72: 4.9208686 | AI72: 5.6670292 | AJ72: 1.1254046 | AK72: 4.4728592 | AL72: 2.9007908 | AM72: 3.9731722 | AN72: 4.6424588 | AO72: 4.9887306 | AP72: 5.4923547 | AQ72: 5.5754975 | AR72: 6.0534388 | AS72: 6.3700038 | AT72: 3.535252 | AU72: 2.390204 | AV72: 3.1934547 | AW72: 4.0920716 | AX72: 4.4717445 | AY72: 6.8438382 | AZ72: 7.0878274 | BA72: 7.1562836 | BB72: 4.6735998 | BC72: 5.1472349 | BD72: 1.7645719 | BE72: 2.2261998 | BF72: 2.1854661 | BG72: 2.9159119 | BH72: 4.3720191 | BI72: 4.3466435 | BJ72: 4.181221 | BK72: 5.314121 | BL72: 5.5576839 | BM72: 3.5696695 | BN72: 3.3267421
A73: Euro area | B73: EMU | C73: GDP growth (annual %) | D73: NY.GDP.MKTP.KD.ZG | P73: 3.7728898 | Q73: 4.8912763 | R73: 6.151607 | S73: 3.2137278 | T73: -0.77240182 | U73: 5.0270268 | V73: 3.0857827 | W73: 3.1236847 | X73: 3.8734541 | Y73: 2.1593481 | Z73: 0.52395861 | AA73: 0.7127527 | AB73: 1.390148 | AC73: 2.3787407 | AD73: 2.3128861 | AE73: 2.5075144 | AF73: 2.5335701 | AG73: 4.3059185 | AH73: 4.0995932 | AI73: 3.6038535 | AJ73: 2.6773778 | AK73: 1.4176834 | AL73: -0.66143727 | AM73: 2.4602013 | AN73: 2.4203529 | AO73: 1.6904393 | AP73: 2.7078229 | AQ73: 3.0363568 | AR73: 2.9649268 | AS73: 3.8651626 | AT73: 2.1957622 | AU73: 0.94035153 | AV73: 0.68220999 | AW73: 2.2939325 | AX73: 1.6814917 | AY73: 3.2308554 | AZ73: 3.0016469 | BA73: 0.41667174 | BB73: -4.5211395 | BC73: 2.1806788 | BD73: 1.7142289 | BE73: -0.84183247 | BF73: -0.21968232 | BG73: 1.4026054 | BH73: 2.0495685 | BI73: 1.8640243 | BJ73: 2.6177934 | BK73: 1.7833786 | BL73: 1.5820684 | BM73: -6.1385314 | BN73: 5.3250571
A74: Eritrea | B74: ERI | C74: GDP growth (annual %) | D74: NY.GDP.MKTP.KD.ZG | AL74: 13.454763 | AM74: 21.221411 | AN74: 2.8583791 | AO74: 9.2588386 | AP74: 7.9086846 | AQ74: 1.7725831 | AR74: 0.013480096 | AS74: -3.1419859 | AT74: 8.7554355 | AU74: 3.0054292 | AV74: -2.6555159 | AW74: 1.4517356 | AX74: 2.5744496 | AY74: -0.96921711 | AZ74: 1.4268222 | BA74: -9.78303 | BB74: 3.8765015 | BC74: 2.1941903 | BD74: 8.6798001
A75: Spain | B75: ESP | C75: GDP growth (annual %) | D75: NY.GDP.MKTP.KD.ZG | F75: 11.838674 | G75: 9.9534381 | H75: 9.5964989 | I75: 5.3085102 | J75: 6.2531349 | K75: 7.2460603 | L75: 4.3403384 | M75: 6.5970201 | N75: 8.9070156 | O75: 4.289183 | P75: 4.6494737 | Q75: 8.1497458 | R75: 7.7884654 | S75: 5.6187857 | T75: 0.54220321 | U75: 3.3037916 | V75: 2.8385743 | W75: 1.4630032 | X75: 0.041546515 | Y75: 2.2087281 | Z75: -0.13246845 | AA75: 1.2464616 | AB75: 1.7701157 | AC75: 1.7846875 | AD75: 2.3214359 | AE75: 3.2533217 | AF75: 5.5471226 | AG75: 5.0943242 | AH75: 4.8270303 | AI75: 3.7813936 | AJ75: 2.5460006 | AK75: 0.92921532 | AL75: -1.0314917 | AM75: 2.3831953 | AN75: 2.757494 | AO75: 2.6605616 | AP75: 3.7024946 | AQ75: 4.3931007 | AR75: 4.4905534 | AS75: 5.2459438 | AT75: 3.9330028 | AU75: 2.7309483 | AV75: 2.9819363 | AW75: 3.1227335 | AX75: 3.6520842 | AY75: 4.1026857 | AZ75: 3.6047385 | BA75: 0.88706705 | BB75: -3.763107 | BC75: 0.16291952 | BD75: -0.81438478 | BE75: -2.9589221 | BF75: -1.4033419 | BG75: 1.3957754 | BH75: 3.8385189 | BI75: 3.0377741 | BJ75: 2.9757607 | BK75: 2.2844694 | BL75: 1.9839662 | BM75: -11.325438 | BN75: 5.519595
A76: Estonia | B76: EST | C76: GDP growth (annual %) | D76: NY.GDP.MKTP.KD.ZG | AO76: 4.9430145 | AP76: 13.050015 | AQ76: 4.3398255 | AR76: -0.42502516 | AS76: 10.087634 | AT76: 6.0036743 | AU76: 6.7713679 | AV76: 7.6002652 | AW76: 6.8040078 | AX76: 9.526427 | AY76: 9.7655834 | AZ76: 7.5791405 | BA76: -5.132001 | BB76: -14.629055 | BC76: 2.4442651 | BD76: 7.2630846 | BE76: 3.2282005 | BF76: 1.4584286 | BG76: 3.0113666 | BH76: 1.85302 | BI76: 3.1555648 | BJ76: 5.7920447 | BK76: 3.7842008 | BL76: 3.7397067 | BM76: -0.55100126 | BN76: 8.0134629
A77: Ethiopia | B77: ETH | C77: GDP growth (annual %) | D77: NY.GDP.MKTP.KD.ZG | AA77: 0.91601386 | AB77: 8.2350057 | AC77: -2.8480215 | AD77: -11.144353 | AE77: 9.6616124 | AF77: 13.85933 | AG77: 0.50367488 | AH77: -0.36104418 | AI77: 2.7264518 | AJ77: -7.1374797 | AK77: -8.6724801 | AL77: 13.142834 | AM77: 3.1899646 | AN77: 6.1275114 | AO77: 12.426174 | AP77: 3.1339069 | AQ77: -3.4581391 | AR77: 5.1621458 | AS77: 6.0732175 | AT77: 8.3013063 | AU77: 1.5147257 | AV77: -2.1613597 | AW77: 13.572603 | AX77: 11.818766 | AY77: 10.834727 | AZ77: 11.456167 | BA77: 10.788522 | BB77: 8.8025532 | BC77: 12.550538 | BD77: 11.178296 | BE77: 8.6478116 | BF77: 10.58227 | BG77: 10.257493 | BH77: 10.392463 | BI77: 9.4334827 | BJ77: 9.5641896 | BK77: 6.8161478 | BL77: 8.3640857 | BM77: 6.0595309 | BN77: 5.637303
A78: European Union | B78: EUU | C78: GDP growth (annual %) | D78: NY.GDP.MKTP.KD.ZG | P78: 3.6345439 | Q78: 4.759788 | R78: 6.0090266 | S78: 3.0957386 | T78: -0.66186728 | U78: 4.8921294 | V78: 2.874604 | W78: 3.0502426 | X78: 3.8721314 | Y78: 2.0752371 | Z78: 0.51203529 | AA78: 0.81252977 | AB78: 1.4488316 | AC78: 2.4963301 | AD78: 2.3528951 | AE78: 2.5858338 | AF78: 2.5203482 | AG78: 4.1624341 | AH78: 3.9181729 | AI78: 3.3826375 | AJ78: 1.8589309 | AK78: 1.1601432 | AL78: -0.57368073 | AM78: 2.6523583 | AN78: 2.6630914 | AO78: 1.8821425 | AP78: 2.6535238 | AQ78: 3.0113925 | AR78: 2.9496343 | AS78: 3.9005296 | AT78: 2.1759015 | AU78: 1.1106872 | AV78: 0.90808574 | AW78: 2.5926098 | AX78: 1.9247201 | AY78: 3.4937154 | AZ78: 3.1558706 | BA78: 0.64072474 | BB78: -4.3485093 | BC78: 2.2252059 | BD78: 1.8936009 | BE78: -0.69988341 | BF78: -0.083821656 | BG78: 1.5975743 | BH78: 2.307057 | BI78: 1.977126 | BJ78: 2.8384813 | BK78: 2.065953 | BL78: 1.8051071 | BM78: -5.6775807 | BN78: 5.392521
A79: Fragile and conflict affected situations | B79: FCS | C79: GDP growth (annual %) | D79: NY.GDP.MKTP.KD.ZG | N79: 13.287384 | O79: 13.587765 | P79: 9.5522366 | Q79: 2.716377 | R79: 4.1677932 | S79: 9.6961505 | T79: -0.37444088 | U79: 7.438058 | V79: 4.3513367 | W79: -1.196893 | X79: 5.7257103 | Y79: 6.1200451 | Z79: -4.0535538 | AA79: -1.1575857 | AB79: -4.7568379 | AC79: -0.6522531 | AD79: 3.1950476 | AE79: 2.0652973 | AF79: 4.3131014 | AG79: 3.2306084 | AH79: 0.5968946 | AI79: 5.0369182 | AJ79: -7.5357464 | AK79: 0.63651326 | AL79: -1.5541918 | AM79: -3.8016765 | AN79: 0.067646837 | AO79: 3.6159067 | AP79: 4.9519683 | AQ79: 5.7501025 | AR79: 3.3184657 | AS79: 5.4414157 | AT79: 4.325458 | AU79: 4.643385 | AV79: 1.2321817 | AW79: 11.063512 | AX79: 5.8398122 | AY79: 5.860089 | AZ79: 6.0104889 | BA79: 5.0355853 | BB79: 2.882472 | BC79: 6.9452922 | BD79: 0.0039707493 | BE79: 4.8655524 | BF79: 3.4776112 | BG79: 2.1578779 | BH79: 0.92225179 | BI79: 2.3959841 | BJ79: 2.4821983 | BK79: 2.6202069 | BL79: 2.2063241 | BM79: -4.0832328 | BN79: 2.1558226
A80: Finland | B80: FIN | C80: GDP growth (annual %) | D80: NY.GDP.MKTP.KD.ZG | F80: 7.6046705 | G80: 2.9819455 | H80: 3.2850996 | I80: 5.2386866 | J80: 5.3028578 | K80: 2.372823 | L80: 2.1688289 | M80: 2.30329 | N80: 9.5932878 | O80: 4.8137368 | P80: 2.3569214 | Q80: 7.7354855 | R80: 6.9838278 | S80: 3.236533 | T80: 1.8048983 | U80: 0.34438249 | V80: 0.23951083 | W80: 2.9197074 | X80: 7.1219264 | Y80: 5.3890479 | Z80: 1.3158789 | AA80: 3.1080887 | AB80: 3.1165815 | AC80: 3.237692 | AD80: 3.5488966 | AE80: 2.7556335 | AF80: 3.5748261 | AG80: 5.2171503 | AH80: 5.0871437 | AI80: 0.67027584 | AJ80: -5.8863281 | AK80: -3.2946601 | AL80: -0.66199803 | AM80: 3.9630524 | AN80: 4.2168675 | AO80: 3.6671798 | AP80: 6.3337957 | AQ80: 5.4571805 | AR80: 4.3795757 | AS80: 5.7733625 | AT80: 2.6100191 | AU80: 1.707149 | AV80: 2.0037842 | AW80: 3.9920913 | AX80: 2.7798506 | AY80: 4.0274097 | AZ80: 5.2993365 | BA80: 0.78399506 | BB80: -8.0744474 | BC80: 3.1859587 | BD80: 2.5476648 | BE80: -1.3975457 | BF80: -0.90169632 | BG80: -0.36490816 | BH80: 0.54365921 | BI80: 2.8114578 | BJ80: 3.1924096 | BK80: 1.139718 | BL80: 1.2247489 | BM80: -2.2051394 | BN80: 2.9732294
A81: Fiji | B81: FJI | C81: GDP growth (annual %) | D81: NY.GDP.MKTP.KD.ZG | F81: 3.517582 | G81: 3.6061021 | H81: 6.358772 | I81: 4.8772807 | J81: -2.700267 | K81: 0 | L81: 13.351828 | M81: 7.9162216 | N81: 2.5964105 | O81: 12.702711 | P81: 6.8889867 | Q81: 7.4852767 | R81: 11.612869 | S81: 2.6011499 | T81: 0.53021119 | U81: 2.7361632 | V81: 5.9040118 | W81: 1.8634015 | X81: 12.22482 | Y81: -1.6034569 | Z81: 6.3299905 | AA81: -5.9784862 | AB81: -3.960123 | AC81: 8.3930245 | AD81: -4.6134749 | AE81: 7.749908 | AF81: -6.61502 | AG81: 0.95575487 | AH81: 7.4386324 | AI81: 5.8000027 | AJ81: -2.7000037 | AK81: 6.1000019 | AL81: 2.1300324 | AM81: 5.0999996 | AN81: 2.4999985 | AO81: 4.8000004 | AP81: -2.1999994 | AQ81: 1.3000005 | AR81: 8.7999987 | AS81: -1.6999984 | AT81: 2.0000001 | AU81: 3.1999991 | AV81: 0.99999934 | AW81: 5.2999997 | AX81: 0.7000004 | AY81: 1.8524839 | AZ81: -0.85065431 | BA81: 1.0327942 | BB81: -1.3860377 | BC81: 2.9546724 | BD81: 2.705143 | BE81: 1.4113144 | BF81: 4.7342195 | BG81: 5.6035149 | BH81: 4.5011994 | BI81: 2.445652 | BJ81: 5.3533649 | BK81: 3.812351 | BL81: -0.58194637 | BM81: -17.000235 | BN81: -5.1116074
A82: France | B82: FRA | C82: GDP growth (annual %) | D82: NY.GDP.MKTP.KD.ZG | F82: 4.9801118 | G82: 6.84347 | H82: 6.23368 | I82: 6.6520995 | J82: 4.8615077 | K82: 5.251837 | L82: 4.9211489 | M82: 4.4913089 | N82: 7.1094753 | O82: 6.1086798 | P82: 5.3167159 | Q82: 4.511374 | R82: 6.3445807 | S82: 4.3009191 | T82: -0.95988475 | U82: 4.3567589 | V82: 3.464312 | W82: 3.9785437 | X82: 3.5499892 | Y82: 1.5787453 | Z82: 1.0690198 | AA82: 2.5053966 | AB82: 1.2408649 | AC82: 1.5137216 | AD82: 1.6227814 | AE82: 2.3372763 | AF82: 2.5619003 | AG82: 4.7431422 | AH82: 4.3438611 | AI82: 2.9239351 | AJ82: 1.0481758 | AK82: 1.5993427 | AL82: -0.62866635 | AM82: 2.3583422 | AN82: 2.1066953 | AO82: 1.4129937 | AP82: 2.3362965 | AQ82: 3.5886594 | AR82: 3.4213738 | AS82: 3.9236692 | AT82: 1.9837214 | AU82: 1.1355315 | AV82: 0.82316076 | AW82: 2.8297529 | AX82: 1.66322 | AY82: 2.4493236 | AZ82: 2.4247362 | BA82: 0.25494596 | BB82: -2.8733138 | BC82: 1.9494376 | BD82: 2.1927006 | BE82: 0.31313475 | BF82: 0.57632667 | BG82: 0.95618305 | BH82: 1.1129123 | BI82: 1.0954644 | BJ82: 2.29142 | BK82: 1.8650661 | BL82: 1.8429718 | BM82: -7.7845865 | BN82: 6.8165891
A83: Faroe Islands | B83: FRO | C83: GDP growth (annual %) | D83: NY.GDP.MKTP.KD.ZG
A84: Micronesia, Fed. Sts. | B84: FSM | C84: GDP growth (annual %) | D84: NY.GDP.MKTP.KD.ZG | AF84: 1.19976 | AG84: 2.5489034 | AH84: 3.5260116 | AI84: 3.7409269 | AJ84: 7.4273412 | AK84: 4.008016 | AL84: 8.1406551 | AM84: -0.53452116 | AN84: 7.0144648 | AO84: -3.1823715 | AP84: -6.0609374 | AQ84: 2.8505159 | AR84: 1.3744384 | AS84: 4.8339038 | AT84: 2.1676024 | AU84: 0.54699767 | AV84: 1.5721151 | AW84: -3.080153 | AX84: 2.0418672 | AY84: -0.081055293 | AZ84: -1.8361853 | BA84: -2.4084926 | BB84: 1.0930992 | BC84: 2.25939 | BD84: 3.1885748 | BE84: -1.8668198 | BF84: -3.6797678 | BG84: -2.3057757 | BH84: 4.621884 | BI84: 0.90018042 | BJ84: 2.6821859 | BK84: 0.2116536 | BL84: 1.1747992 | BM84: -1.7654152 | BN84: -3.1881872
A85: Gabon | B85: GAB | C85: GDP growth (annual %) | D85: NY.GDP.MKTP.KD.ZG | F85: 14.766843 | G85: 7.4492116 | H85: 6.0924353 | I85: 4.5544536 | J85: 8.3333357 | K85: 4.5080046 | L85: 4.1151529 | M85: 2.5088009 | N85: 8.0829104 | O85: 8.6793422 | P85: 10.258731 | Q85: 11.336971 | R85: 10.182434 | S85: 39.487095 | T85: 19.190115 | U85: 35.625338 | V85: -12.582091 | W85: -24.049206 | X85: 0.47440528 | Y85: 2.5529372 | Z85: 5.0953293 | AA85: -3.0975204 | AB85: 5.6082407 | AC85: 7.5089023 | AD85: -2.3329493 | AE85: -0.80359773 | AF85: -17.146042 | AG85: 12.845353 | AH85: 8.54531 | AI85: 5.1922373 | AJ85: 6.1125035 | AK85: -3.0901457 | AL85: 3.946555 | AM85: 3.7127548 | AN85: 4.9738478 | AO85: 3.625049 | AP85: 5.7383674 | AQ85: 3.4778336 | AR85: -8.9326228 | AS85: -1.8829664 | AT85: 2.1352334 | AU85: -0.24903317 | AV85: 2.24733 | AW85: 0.68954306 | AX85: 2.6762033 | AY85: -2.8065784 | AZ85: 6.008108 | BA85: -3.3084306 | BB85: 0.13033112 | BC85: 7.0898873 | BD85: 7.0917533 | BE85: 5.2510769 | BF85: 5.638699 | BG85: 4.3149644 | BH85: 3.8788994 | BI85: 2.0914422 | BJ85: 0.47264203 | BK85: 0.83791658 | BL85: 3.9208088 | BM85: -1.8377611 | BN85: 1.4622865
A86: United Kingdom | B86: GBR | C86: GDP growth (annual %) | D86: NY.GDP.MKTP.KD.ZG | F86: 2.6771189 | G86: 1.1029096 | H86: 4.874384 | I86: 5.5336594 | J86: 2.1421765 | K86: 1.5731004 | L86: 2.7864746 | M86: 5.4410834 | N86: 1.9240968 | O86: 6.8409137 | P86: 3.5047174 | Q86: 4.3216676 | R86: 6.5238485 | S86: -2.4844041 | T86: -1.4736495 | U86: 2.9102662 | V86: 2.4577505 | W86: 4.2042605 | X86: 3.7490165 | Y86: -2.0313677 | Z86: -0.78774386 | AA86: 1.9948912 | AB86: 4.2218564 | AC86: 2.2691052 | AD86: 4.147415 | AE86: 3.1503405 | AF86: 5.3927383 | AG86: 5.7324137 | AH86: 2.5776027 | AI86: 0.7337555 | AJ86: -1.1031216 | AK86: 0.40108198 | AL86: 2.489831 | AM86: 3.8460092 | AN86: 2.53167 | AO86: 1.9078071 | AP86: 4.3665811 | AQ86: 3.1572873 | AR86: 3.0140705 | AS86: 4.0926535 | AT86: 2.1574282 | AU86: 1.7707653 | AV86: 3.1230533 | AW86: 2.3449715 | AX86: 2.6683377 | AY86: 2.1604053 | AZ86: 2.5634605 | BA86: -0.15434431 | BB86: -4.5104856 | BC86: 2.4300729 | BD86: 1.0676109 | BE86: 1.4484568 | BF86: 1.8198634 | BG86: 3.1997026 | BH86: 2.3931032 | BI86: 2.1652062 | BJ86: 2.4435705 | BK86: 1.705021 | BL86: 1.6043086 | BM86: -11.030858 | BN86: 7.5249104
A87: Georgia | B87: GEO | C87: GDP growth (annual %) | D87: NY.GDP.MKTP.KD.ZG | K87: 7.5356313 | L87: 6.2499995 | M87: 4.4563348 | N87: 4.7781497 | O87: 12.052116 | P87: 2.4709361 | Q87: 2.8368738 | R87: 6.4827615 | S87: 8.8082934 | T87: 7.3809453 | U87: 6.0975642 | V87: 6.8965502 | W87: 7.4291277 | X87: 7.3703461 | Y87: 4.5762663 | Z87: 5.2674237 | AA87: 2.0015385 | AB87: 4.3018868 | AC87: 5.426923 | AD87: 4.9416554 | AE87: -8.1752759 | AF87: 1.2820428 | AG87: 5.5555581 | AH87: -7.1952019 | AI87: -14.788226 | AJ87: -21.100001 | AK87: -44.899999 | AL87: -29.300002 | AM87: -10.399994 | AN87: 2.5999967 | AO87: 11.200002 | AP87: 10.519041 | AQ87: 3.1049027 | AR87: 2.869257 | AS87: 1.8383411 | AT87: 4.8054533 | AU87: 5.4738368 | AV87: 11.058723 | AW87: 5.7944963 | AX87: 9.5895741 | AY87: 9.4197706 | AZ87: 12.578953 | BA87: 2.4185717 | BB87: -3.6505136 | BC87: 6.2494878 | BD87: 7.3999999 | BE87: 6.3690083 | BF87: 3.6213054 | BG87: 4.4319248 | BH87: 3.0222074 | BI87: 2.9064388 | BJ87: 4.8426032 | BK87: 4.8429199 | BL87: 4.9823505 | BM87: -6.7604398 | BN87: 10.465537
A88: Ghana | B88: GHA | C88: GDP growth (annual %) | D88: NY.GDP.MKTP.KD.ZG | F88: 3.429674 | G88: 4.1091586 | H88: 4.4059742 | I88: 2.2093275 | J88: 1.3689989 | K88: -4.2582904 | L88: 3.0753641 | M88: 0.36886033 | N88: 6.006175 | O88: 9.7234726 | P88: 5.2161246 | Q88: -2.4876554 | R88: 2.8845842 | S88: 6.8525168 | T88: -12.431629 | U88: -3.5301828 | V88: 2.2741072 | W88: 8.4759356 | X88: -2.5149414 | Y88: 0.47169594 | Z88: -3.5030669 | AA88: -6.9236504 | AB88: -4.5637375 | AC88: 8.6475695 | AD88: 5.0916173 | AE88: 5.1991607 | AF88: 4.7948989 | AG88: 5.6281688 | AH88: 5.0858727 | AI88: 3.3288179 | AJ88: 5.2818264 | AK88: 3.8794191 | AL88: 4.8500006 | AM88: 3.2999997 | AN88: 4.112419 | AO88: 4.6024612 | AP88: 4.1963574 | AQ88: 4.7003908 | AR88: 4.3999968 | AS88: 3.7000001 | AT88: 4.0000001 | AU88: 4.4999996 | AV88: 5.2000001 | AW88: 5.6 | AX88: 5.9000038 | AY88: 6.3999126 | AZ88: 4.3468191 | BA88: 9.1497989 | BB88: 4.8444871 | BC88: 7.8997119 | BD88: 14.047124 | BE88: 9.2927894 | BF88: 7.312525 | BG88: 2.8562402 | BH88: 2.1207593 | BI88: 3.3734657 | BJ88: 8.1288949 | BK88: 6.2000777 | BL88: 6.5077748 | BM88: 0.51394165 | BN88: 5.3564779
A89: Gibraltar | B89: GIB | C89: GDP growth (annual %) | D89: NY.GDP.MKTP.KD.ZG
A90: Guinea | B90: GIN | C90: GDP growth (annual %) | D90: NY.GDP.MKTP.KD.ZG | AF90: 3.2999388 | AG90: 6.3081167 | AH90: 4.003476 | AI90: 4.3240628 | AJ90: 2.613423 | AK90: 3.2709473 | AL90: 5.0441445 | AM90: 3.9700991 | AN90: 4.6076732 | AO90: 4.4615751 | AP90: 5.1816035 | AQ90: 3.6441212 | AR90: 3.812004 | AS90: 2.5030606 | AT90: 3.6583465 | AU90: 5.1646095 | AV90: 1.2486013 | AW90: 2.3401173 | AX90: 2.9972726 | AY90: 1.1896021 | AZ90: 6.8174711 | BA90: 4.1330162 | BB90: -1.122642 | BC90: 4.8133602 | BD90: 5.6121118 | BE90: 5.9152863 | BF90: 3.9456871 | BG90: 3.6965531 | BH90: 3.8259106 | BI90: 10.820627 | BJ90: 10.300005 | BK90: 6.3584919 | BL90: 5.6169145 | BM90: 4.9202664 | BN90: 3.9
A91: Gambia, The | B91: GMB | C91: GDP growth (annual %) | D91: NY.GDP.MKTP.KD.ZG | L91: 0 | M91: 9.5761435 | N91: 2.4355229 | O91: 6.1538466 | P91: -0.065877039 | Q91: 0.24170479 | R91: 9.2503293 | S91: 5.8787936 | T91: 12.393429 | U91: 7.3512257 | V91: 3.4395761 | W91: 6.3164463 | X91: -1.3281832 | Y91: 6.2700796 | Z91: 3.321894 | AA91: -0.76458264 | AB91: 10.883228 | AC91: 3.5352573 | AD91: -0.81226466 | AE91: 4.0910707 | AF91: 2.4543326 | AG91: 4.4768269 | AH91: 5.8957219 | AI91: 3.5588794 | AJ91: 3.1070392 | AK91: 3.3786888 | AL91: 3.0121014 | AM91: 0.15434596 | AN91: 0.88184824 | AO91: 2.2235456 | AP91: 4.8999991 | AQ91: 3.4999987 | AR91: 6.3999991 | AS91: 5.5000002 | AT91: 5.8000002 | AU91: -3.2500001 | AV91: 6.8699996 | AW91: 7.05 | AX91: -2.3517294 | AY91: -0.55558098 | AZ91: 3.0432495 | BA91: 6.2559055 | BB91: 6.6657243 | BC91: 5.9083358 | BD91: -8.1304442 | BE91: 5.2415692 | BF91: 2.8727688 | BG91: -1.4073825 | BH91: 4.0580738 | BI91: 1.9433597 | BJ91: 4.8226112 | BK91: 7.2348903 | BL91: 6.2220532 | BM91: 0.59148729 | BN91: 4.2654922
A92: Guinea-Bissau | B92: GNB | C92: GDP growth (annual %) | D92: NY.GDP.MKTP.KD.ZG | P92: -3.9109675 | Q92: 6.3748609 | R92: 1.1098928 | S92: 4.559241 | T92: 7.8455843 | U92: 4.9434553 | V92: -7.17007 | W92: 13.126043 | X92: 1.9941444 | Y92: -15.952651 | Z92: 18.167528 | AA92: 4.2000821 | AB92: -3.3982874 | AC92: 9.109223 | AD92: 4.1664929 | AE92: -0.79384763 | AF92: 2.9 | AG92: 4.6 | AH92: 6.1 | AI92: 6.1 | AJ92: 5.1 | AK92: 1.1 | AL92: 2.1 | AM92: 3.2 | AN92: 4.4 | AO92: 11.6 | AP92: 6.5 | AQ92: -28.09998 | AR92: 1.0255374 | AS92: 5.4269874 | AT92: 2.1889068 | AU92: -0.98517752 | AV92: 0.56851018 | AW92: 2.761402 | AX92: 4.2660989 | AY92: 2.309358 | AZ92: 3.2629555 | BA92: 3.2035673 | BB92: 3.368975 | BC92: 4.6109709 | BD92: 8.0847797 | BE92: -1.712683 | BF92: 3.2559043 | BG92: 0.96456075 | BH92: 6.1340829 | BI92: 6.2628056 | BJ92: 5.9191766 | BK92: 1.2837367 | BL92: 4.5 | BM92: -2.4 | BN92: 3.8000024
A93: Equatorial Guinea | B93: GNQ | C93: GDP growth (annual %) | D93: NY.GDP.MKTP.KD.ZG | Z93: 5.7694205 | AA93: 2.2016759 | AB93: 5.0043872 | AC93: 1.0113817 | AD93: 12.905179 | AE93: -2.3305564 | AF93: 4.4367374 | AG93: 2.6552622 | AH93: -1.2291781 | AI93: -1.7585641 | AJ93: -1.0222389 | AK93: 34.74532 | AL93: 11.033213 | AM93: 16.668836 | AN93: 17.486264 | AO93: 66.579997 | AP93: 149.97296 | AQ93: 23.774482 | AR93: 25.664015 | AS93: 18.21378 | AT93: 63.379875 | AU93: 19.462834 | AV93: 13.95525 | AW93: 37.998727 | AX93: 16.748701 | AY93: 7.7049176 | AZ93: 15.282114 | BA93: 17.799109 | BB93: 1.3433563 | BC93: -8.9241759 | BD93: 6.5239236 | BE93: 8.3128718 | BF93: -4.1331985 | BG93: 0.4150663 | BH93: -9.1100411 | BI93: -8.8164172 | BJ93: -5.6675085 | BK93: -6.2365441 | BL93: -5.4818254 | BM93: -4.2414813 | BN93: -0.94538292
A94: Greece | B94: GRC | C94: GDP growth (annual %) | D94: NY.GDP.MKTP.KD.ZG | F94: 13.203841 | G94: 0.36481054 | H94: 11.844868 | I94: 9.4096766 | J94: 10.768011 | K94: 6.4945023 | L94: 5.6694855 | M94: 7.2037189 | N94: 11.563667 | O94: 8.5652475 | P94: 7.8411772 | Q94: 10.160152 | R94: 8.092379 | S94: -6.4382408 | T94: 6.3668086 | U94: 6.8518977 | V94: 2.9410018 | W94: 7.2468635 | X94: 3.2820801 | Y94: 0.67713082 | Z94: -1.553721 | AA94: -1.1326474 | AB94: -1.0786227 | AC94: 2.0105802 | AD94: 2.5095571 | AE94: 0.5176596 | AF94: -2.2588634 | AG94: 4.2878617 | AH94: 3.8000005 | AI94: 0 | AJ94: 3.0999994 | AK94: 0.70000021 | AL94: -1.6000002 | AM94: 2.0000003 | AN94: 2.0997197 | AO94: 2.8621288 | AP94: 4.484199 | AQ94: 3.894905 | AR94: 3.0725967 | AS94: 3.9197707 | AT94: 4.1316123 | AU94: 3.9228717 | AV94: 5.7945315 | AW94: 5.0609922 | AX94: 0.59914219 | AY94: 5.6524336 | AZ94: 3.2737469 | BA94: -0.33517234 | BB94: -4.3007337 | BC94: -5.4782177 | BD94: -10.149315 | BE94: -7.0866968 | BF94: -2.5159972 | BG94: 0.47569595 | BH94: -0.19608763 | BI94: -0.48717329 | BJ94: 1.0921491 | BK94: 1.6684286 | BL94: 1.8843418 | BM94: -9.0040436 | BN94: 8.4344255
A95: Grenada | B95: GRD | C95: GDP growth (annual %) | D95: NY.GDP.MKTP.KD.ZG | W95: 5.3414021 | X95: 5.6020835 | Y95: -0.53478405 | Z95: 1.5341875 | AA95: 4.1242616 | AB95: 3.6325749 | AC95: 3.5684652 | AD95: 5.9797082 | AE95: 7.1942738 | AF95: 9.097425 | AG95: 2.9667917 | AH95: 3.7677308 | AI95: 4.0126119 | AJ95: 1.3855458 | AK95: -0.85114876 | AL95: -1.9588156 | AM95: 1.693556 | AN95: 2.1294751 | AO95: 4.4382347 | AP95: 5.0154946 | AQ95: 11.753503 | AR95: 6.8983624 | AS95: 4.8879521 | AT95: -2.0239 | AU95: 3.4373235 | AV95: 9.4639734 | AW95: -0.64745032 | AX95: 13.276188 | AY95: -3.9953282 | AZ95: 6.1234509 | BA95: 0.94754262 | BB95: -6.6132813 | BC95: -0.51126275 | BD95: 0.76497682 | BE95: -1.1551437 | BF95: 2.3514188 | BG95: 7.3415062 | BH95: 6.4447678 | BI95: 3.7405526 | BJ95: 4.4391164 | BK95: 4.361422 | BL95: 0.6752959 | BM95: -13.755929 | BN95: 4.6879439
A96: Greenland | B96: GRL | C96: GDP growth (annual %) | D96: NY.GDP.MKTP.KD.ZG | P96: 13.060851 | Q96: 6.1772736 | R96: 6.806009 | S96: 5.706254 | T96: 0.64624014 | U96: 5.9592085 | V96: 8.8223153 | W96: 6.0167172 | X96: 4.8605975 | Y96: 8.6760063 | Z96: 0.66527956 | AA96: -4.4196608 | AB96: 3.4572167 | AC96: -5.1796155 | AD96: 3.656388 | AE96: 7.0973227 | AF96: 5.5158721 | AG96: 5.6036107 | AH96: 6.659545 | AI96: -11.719533 | AJ96: -0.1134646 | AK96: -5.1117 | AL96: -5.0279326 | AM96: 5.9243698 | AN96: 3.7286775 | AO96: 1.5296374 | AP96: 1.4689264 | AQ96: 7.7579817 | AR96: 1.3778844 | AS96: 7.1015969 | AT96: 1.2690351 | AU96: -0.97117731 | AV96: 4.4300457 | AW96: 6.9065828 | AX96: 4.9874918 | AY96: 5.5556949 | AZ96: 2.352438 | BA96: 6.1661327 | BB96: 0.86595233 | BC96: 1.7358251 | BD96: -0.49651939 | BE96: 1.3941934 | BF96: -1.2982807 | BG96: 4.7421357 | BH96: -2.529318 | BI96: 4.6819541 | BJ96: 0.052728183 | BK96: 0.62306543 | BL96: 2.2713109 | BM96: 0.35653166
A97: Guatemala | B97: GTM | C97: GDP growth (annual %) | D97: NY.GDP.MKTP.KD.ZG | F97: 4.2985183 | G97: 3.5365013 | H97: 9.5410439 | I97: 4.6329924 | J97: 4.3617693 | K97: 5.512104 | L97: 4.1121756 | M97: 8.7660351 | N97: 4.736909 | O97: 5.7078836 | P97: 5.5837545 | Q97: 7.3330516 | R97: 6.7828343 | S97: 6.3750299 | T97: 1.9499908 | U97: 7.3872656 | V97: 7.8092207 | W97: 4.9966898 | X97: 4.7134561 | Y97: 3.7599782 | Z97: 0.64685861 | AA97: -3.530089 | AB97: -2.5720914 | AC97: 0.49669775 | AD97: -0.60933896 | AE97: 0.1430496 | AF97: 3.5439833 | AG97: 3.8923871 | AH97: 3.9425895 | AI97: 3.1025632 | AJ97: 3.6582488 | AK97: 4.8383388 | AL97: 3.9271319 | AM97: 4.0337415 | AN97: 4.9485475 | AO97: 2.9577799 | AP97: 4.3640899 | AQ97: 4.9935278 | AR97: 3.8470622 | AS97: 3.6088687 | AT97: 2.3325749 | AU97: 3.8392871 | AV97: 2.5603777 | AW97: 3.1379168 | AX97: 3.2760269 | AY97: 5.3513978 | AZ97: 6.3377187 | BA97: 3.293524 | BB97: 0.47689811 | BC97: 2.8841754 | BD97: 4.1639069 | BE97: 2.9747086 | BF97: 3.6948192 | BG97: 4.4439776 | BH97: 4.0921708 | BI97: 2.6778026 | BJ97: 3.0798515 | BK97: 3.4068734 | BL97: 4.0023151 | BM97: -1.7640829 | BN97: 7.9807695
A98: Guam | B98: GUM | C98: GDP growth (annual %) | D98: NY.GDP.MKTP.KD.ZG | AV98: 0.87931413 | AW98: 6.4937895 | AX98: 3.6423163 | AY98: -3.6525173 | AZ98: 0.71721311 | BA98: 2.034588 | BB98: 0.43868395 | BC98: 2.2632519 | BD98: 0.077654824 | BE98: 2.1338506 | BF98: 1.6904084 | BG98: 1.7930519 | BH98: 0.82568807 | BI98: 0.18198362 | BJ98: 0.89009991 | BK98: -0.79222182 | BL98: 2.5952813 | BM98: -11.392181 | BN98: 1.0580954
A99: Guyana | B99: GUY | C99: GDP growth (annual %) | D99: NY.GDP.MKTP.KD.ZG | F99: 4.6895243 | G99: 1.1049258 | H99: -12.278657 | I99: 11.360282 | J99: 10.541019 | K99: 5.2332739 | L99: 4.3136218 | M99: 1.0248276 | N99: 6.9943867 | O99: 4.2554569 | P99: 3.1128508 | Q99: -3.3176709 | R99: 1.2447194 | S99: 7.7028399 | T99: 8.4830215 | U99: 1.5369133 | V99: -2.6386797 | W99: -1.8061888 | X99: -1.8356963 | Y99: 1.7338897 | Z99: 1.4961659 | AA99: -13.190134 | AB99: -6.7923867 | AC99: -5.0287379 | AD99: 2.3996675 | AE99: -0.90060224 | AF99: 0.89939659 | AG99: -3.6935331 | AH99: -4.9166667 | AI99: -3.0674847 | AJ99: 6.0578662 | AK99: 7.7578858 | AL99: 8.1751055 | AM99: 8.5324232 | AN99: 5.0314466 | AO99: 7.9555175 | AP99: 6.1806656 | AQ99: -1.6791045 | AR99: 2.9601518 | AS99: -1.3638039 | AT99: 2.2795217 | AU99: 1.132627 | AV99: -0.63222539 | AW99: 1.5633521 | AX99: -1.9509576 | AY99: 5.1296093 | AZ99: 7.1912362 | BA99: 1.7552235 | BB99: 3.6115085 | BC99: 4.1384416 | BD99: 5.1962516 | BE99: 5.2763306 | BF99: 3.6535048 | BG99: 1.6860277 | BH99: 0.68752121 | BI99: 3.8079188 | BJ99: 3.7343741 | BK99: 4.4410136 | BL99: 5.3526274 | BM99: 43.479556 | BN99: 20.060011
A100: High income | B100: HIC | C100: GDP growth (annual %) | D100: NY.GDP.MKTP.KD.ZG | F100: 4.3634296 | G100: 5.6641132 | H100: 5.2955812 | I100: 6.348015 | J100: 5.4821373 | K100: 5.899362 | L100: 4.3498148 | M100: 5.9881838 | N100: 5.3592535 | O100: 3.1082707 | P100: 3.8816352 | Q100: 5.5329181 | R100: 6.3030586 | S100: 1.0055786 | T100: -0.11257399 | U100: 5.1362088 | V100: 4.0012807 | W100: 4.2522712 | X100: 4.1123977 | Y100: 1.2497655 | Z100: 1.9009194 | AA100: -0.13721339 | AB100: 2.8231524 | AC100: 4.6647936 | AD100: 3.5358221 | AE100: 3.310057 | AF100: 3.4733827 | AG100: 4.7655296 | AH100: 3.9258022 | AI100: 3.1001381 | AJ100: 1.4349891 | AK100: 2.1915309 | AL100: 1.3577985 | AM100: 3.2906691 | AN100: 2.864973 | AO100: 3.0446704 | AP100: 3.4683997 | AQ100: 2.8777104 | AR100: 3.48048 | AS100: 4.1257893 | AT100: 1.4785954 | AU100: 1.5491262 | AV100: 2.1872756 | AW100: 3.4177019 | AX100: 2.881287 | AY100: 3.0725227 | AZ100: 2.7012801 | BA100: 0.54823307 | BB100: -3.2497714 | BC100: 3.0244156 | BD100: 1.9290103 | BE100: 1.4108947 | BF100: 1.494976 | BG100: 2.0916355 | BH100: 2.3650685 | BI100: 1.8311362 | BJ100: 2.3763545 | BK100: 2.3543293 | BL100: 1.7583227 | BM100: -4.2690505 | BN100: 5.2360452
A101: Hong Kong SAR, China | B101: HKG | C101: GDP growth (annual %) | D101: NY.GDP.MKTP.KD.ZG | G101: 14.291526 | H101: 15.764053 | I101: 8.6281964 | J101: 14.642133 | K101: 1.7946732 | L101: 1.6037091 | M101: 3.3971601 | N101: 11.34329 | O101: 9.2068923 | P101: 7.2930738 | Q101: 10.612118 | R101: 12.27986 | S101: 2.4151132 | T101: 0.49206093 | U101: 16.164165 | V101: 11.725808 | W101: 8.2608358 | X101: 11.556603 | Y101: 10.108252 | Z101: 9.2608766 | AA101: 2.9497462 | AB101: 5.9770081 | AC101: 9.9737376 | AD101: 0.75716904 | AE101: 11.056157 | AF101: 13.398456 | AG101: 8.5116318 | AH101: 2.2770111 | AI101: 3.8305265 | AJ101: 5.7020343 | AK101: 6.2349326 | AL101: 6.20114 | AM101: 6.0360615 | AN101: 2.3738082 | AO101: 4.2585396 | AP101: 5.0997187 | AQ101: -5.8827079 | AR101: 2.5067435 | AS101: 7.6634848 | AT101: 0.56080727 | AU101: 1.656669 | AV101: 3.0563116 | AW101: 8.7000669 | AX101: 7.3881945 | AY101: 7.0326026 | AZ101: 6.46483 | BA101: 2.1279566 | BB101: -2.45905 | BC101: 6.7676718 | BD101: 4.8147 | BE101: 1.7003175 | BF101: 3.1015255 | BG101: 2.7624196 | BH101: 2.3878319 | BI101: 2.1754243 | BJ101: 3.7961222 | BK101: 2.8469347 | BL101: -1.6782465 | BM101: -6.5450082 | BN101: 6.3431062
...

Sheet country-code
A1: Country Name | B1: Country Code
A2: Aruba | B2: ABW
A3: Africa Eastern and Southern | B3: AFE
A4: Afghanistan | B4: AFG
A5: Africa Western and Central | B5: AFW
A6: Angola | B6: AGO
A7: Albania | B7: ALB
A8: Andorra | B8: AND
A9: Arab World | B9: ARB
A10: United Arab Emirates | B10: ARE
A11: Argentina | B11: ARG
A12: Armenia | B12: ARM
... A267: Zimbabwe | B267: ZWE

Sheet GDP-Per Cap
A1: Country Name | B1: 2021 | C1: Short code | E1: Country Name | F1: Low bound | G1: High Bound
A2: Monaco | B2: 204190.16 | C2: =VLOOKUP(A2,'country-code'!$A$1:$B$267,2,FALSE) -> MCO | D2: =VLOOKUP(B2,$F$2:$H$5,3,TRUE) -> High income | E2: Low & middle income | F2: 1 | G2: 5102.6042 | H2: Low & middle income
A3: Switzerland | B3: 87339.76 | C3: =VLOOKUP(A3,'country-code'!$A$1:$B$267,2,FALSE) -> CHE | D3: =VLOOKUP(B3,$F$2:$H$5,3,TRUE) -> High income | E3: Middle income | F3: 5101 | G3: 5632 | H3: Middle income
A4: Ireland | B4: 88966.672 | C4: =VLOOKUP(A4,'country-code'!$A$1:$B$267,2,FALSE) -> IRL | D4: =VLOOKUP(B4,$F$2:$H$5,3,TRUE) -> High income | E4: Upper middle income | F4: 5631 | G4: 10050.318 | H4: Upper middle income
A5: Bermuda | B5: 105187.79 | C5: =VLOOKUP(A5,'country-code'!$A$1:$B$267,2,FALSE) -> BMU | D5: =VLOOKUP(B5,$F$2:$H$5,3,TRUE) -> High income | E5: High income | F5: 10049 | G5: 42539.881 | H5: High income
A6: Luxembourg | B6: 107792.19 | C6: =VLOOKUP(A6,'country-code'!$A$1:$B$267,2,FALSE) -> LUX | D6: =VLOOKUP(B6,$F$2:$H$5,3,TRUE) -> High income
A7: Norway | B7: 77512.897 | C7: =VLOOKUP(A7,'country-code'!$A$1:$B$267,2,FALSE) -> NOR | D7: =VLOOKUP(B7,$F$2:$H$5,3,TRUE) -> High income
A8: Cayman Islands | B8: 76577.822 | C8: =VLOOKUP(A8,'country-code'!$A$1:$B$267,2,FALSE) -> CYM | D8: =VLOOKUP(B8,$F$2:$H$5,3,TRUE) -> High income
A9: Singapore | B9: 66176.387 | C9: =VLOOKUP(A9,'country-code'!$A$1:$B$267,2,FALSE) -> SGP | D9: =VLOOKUP(B9,$F$2:$H$5,3,TRUE) -> High income
A10: United States | B10: 61855.519 | C10: =VLOOKUP(A10,'country-code'!$A$1:$B$267,2,FALSE) -> USA | D10: =VLOOKUP(B10,$F$2:$H$5,3,TRUE) -> High income
A11: Qatar | B11: 61000.833 | C11: =VLOOKUP(A11,'country-code'!$A$1:$B$267,2,FALSE) -> QAT | D11: =VLOOKUP(B11,$F$2:$H$5,3,TRUE) -> High income
A12: North America | B12: 60011.743 | C12: =VLOOKUP(A12,'country-code'!$A$1:$B$267,2,FALSE) -> NAC | D12: =VLOOKUP(B12,$F$2:$H$5,3,TRUE) -> High income
A13: Australia | B13: 59341.238 | C13: =VLOOKUP(A13,'country-code'!$A$1:$B$267,2,FALSE) -> AUS | D13: =VLOOKUP(B13,$F$2:$H$5,3,TRUE) -> High income
A14: Denmark | B14: 58359.584 | C14: =VLOOKUP(A14,'country-code'!$A$1:$B$267,2,FALSE) -> DNK | D14: =VLOOKUP(B14,$F$2:$H$5,3,TRUE) -> High income
A15: Iceland | B15: 54417.289 | C15: =VLOOKUP(A15,'country-code'!$A$1:$B$267,2,FALSE) -> ISL | D15: =VLOOKUP(B15,$F$2:$H$5,3,TRUE) -> High income
A16: Sweden | B16: 54262.439 | C16: =VLOOKUP(A16,'country-code'!$A$1:$B$267,2,FALSE) -> SWE | D16: =VLOOKUP(B16,$F$2:$H$5,3,TRUE) -> High income
A17: Netherlands | B17: 48301.529 | C17: =VLOOKUP(A17,'country-code'!$A$1:$B$267,2,FALSE) -> NLD | D17: =VLOOKUP(B17,$F$2:$H$5,3,TRUE) -> High income
... A243: Burundi | B243: 261.01938 | C243: =VLOOKUP(A243,'country-code'!$A$1:$B$267,2,FALSE) -> BDI | D243: =VLOOKUP(B243,$F$2:$H$5,3,TRUE) -> Low & middle income
A244: Channel Islands | C244: =VLOOKUP(A244,'country-code'!$A$1:$B$267,2,FALSE) -> CHI
A245: Eritrea | C245: =VLOOKUP(A245,'country-code'!$A$1:$B$267,2,FALSE) -> ERI
A246: Faroe Islands | C246: =VLOOKUP(A246,'country-code'!$A$1:$B$267,2,FALSE) -> FRO
A247: Gibraltar | C247: =VLOOKUP(A247,'country-code'!$A$1:$B$267,2,FALSE) -> GIB
A248: Greenland | C248: =VLOOKUP(A248,'country-code'!$A$1:$B$267,2,FALSE) -> GRL
A249: Isle of Man | C249: =VLOOKUP(A249,'country-code'!$A$1:$B$267,2,FALSE) -> IMN
A250: Not classified | C250: =VLOOKUP(A250,'country-code'!$A$1:$B$267,2,FALSE) -> INX
A251: Kuwait | C251: =VLOOKUP(A251,'country-code'!$A$1:$B$267,2,FALSE) -> KWT
A252: Liechtenstein | C252: =VLOOKUP(A252,'country-code'!$A$1:$B$267,2,FALSE) -> LIE
A253: St. Martin (French part) | C253: =VLOOKUP(A253,'country-code'!$A$1:$B$267,2,FALSE) -> MAF
A254: Northern Mariana Islands | C254: =VLOOKUP(A254,'country-code'!$A$1:$B$267,2,FALSE) -> MNP
A255: New Caledonia | C255: =VLOOKUP(A255,'country-code'!$A$1:$B$267,2,FALSE) -> NCL
... A265: Yemen, Rep. | C265: =VLOOKUP(A265,'country-code'!$A$1:$B$267,2,FALSE) -> YEM

Sheet GDP-10-ConstUSD
A1: Country | B1: GDP in 2021 | C1: GDP Trillion USD (2021) | D1: GDP in 2022 | E1: GDP Trillion USD (2022) | F1: GDP in 2024 | G1: GDP Trillion USD (2024)
A2: United States | B2: 20529500000000 | C2: =B2/10^12 -> 20.5295 | D2: =E2*10^(12) -> 25462730000000 | E2: 25.46273 | F2: 29184890000000 | G2: =F2/(10^12) -> 29.18489
A3: China | B3: 15801900000000 | C3: =B3/10^12 -> 15.8019 | D3: =E3*10^(12) -> 17886330000000 | E3: 17.88633 | F3: 1.8743803e+13 | G3: =F3/(10^12) -> 18.743803
A4: Japan | B4: 4435430000000 | C4: =B4/10^12 -> 4.43543 | D4: =E4*10^(12) -> 4.23753e+12 | E4: 4.23753 | F4: 4.6599293e+12 | G4: =F4/(10^12) -> 4.6599293
A5: Germany | B5: 3554680000000 | C5: =B5/10^12 -> 3.55468 | D5: =E5*10^(12) -> 4085680000000 | E5: 4.08568 | F5: 4.0262108e+12 | G5: =F5/(10^12) -> 4.0262108
A6: India | B6: 2726370000000 | C6: =B6/10^12 -> 2.72637 | D6: =E6*10^(12) -> 3389690000000 | E6: 3.38969 | F6: 3.9126862e+12 | G6: =F6/(10^12) -> 3.9126862
A7: United Kingdom | B7: 3036530000000 | C7: =B7/10^12 -> 3.03653 | D7: =E7*10^(12) -> 3081870000000 | E7: 3.08187 | F7: 3.6438342e+12 | G7: =F7/(10^12) -> 3.6438342
A8: France | B8: 2577600000000 | C8: =B8/10^12 -> 2.5776 | D8: =E8*10^(12) -> 2780140000000 | E8: 2.78014 | F8: 3.1620791e+12 | G8: =F8/(10^12) -> 3.1620791
A9: Russia | B9: 1490190000000 | C9: =B9/10^12 -> 1.49019 | D9: =E9*10^(12) -> 2244250000000 | E9: 2.24425 | F9: 2.3727745e+12 | G9: =F9/(10^12) -> 2.3727745
A10: Canada | B10: 1680390000000 | C10: =B10/10^12 -> 1.68039 | D10: =E10*10^(12) -> 2137940000000 | E10: 2.13794 | F10: 2.2412532e+12 | G10: =F10/(10^12) -> 2.2412532
A11: Italy | B11: 1862310000000 | C11: =B11/10^12 -> 1.86231 | D11: =E11*10^(12) -> 2012010000000 | E11: 2.01201 | F11: 2.1794121e+12 | G11: =F11/(10^12) -> 2.1794121
A12: Brazil | B12: 1829900000000 | C12: =B12/10^12 -> 1.8299 | D12: =E12*10^(12) -> 1920020000000 | E12: 1.92002 | F12: 2.1738358e+12 | G12: =F12/(10^12) -> 2.1738358
A13: Australia | B13: 1524360000000 | C13: =B13/10^12 -> 1.52436 | D13: =E13*10^(12) -> 1702550000000 | E13: 1.70255 | F13: 1.8527229e+12 | G13: =F13/(10^12) -> 1.8527229
... A18: Turkey | B18: 1131040000000 | C18: =B18/10^12 -> 1.13104 | D18: =E18*10^(12) -> 905840000000 | E18: 0.90584 | F18: 1.3232548e+12 | G18: =F18/(10^12) -> 1.3232548
A25: Source: WDI

Sheet IIP
A1: Index of Industrial Production : Economic Activity based Classification : Base Year 2011-12
A2: Index numbers : June 2011 to June 2022
A3: Quarter ended | B3: IIP | C3: Mining & quarrying | D3: Manufacturing | E3: Electricity | G3: Primary goods | H3: Capital goods | I3: Intermediate goods | J3: Infrastructure/construction goods | K3: Consumer goods | L3: Consumer goods(Durable) | M3: Consumer goods (Non-Durable)
B4: (Wt=100.00) | C4: (Wt=14.37) | D4: (Wt=77.63) | E4: (Wt=7.99) | G4: (Wt=34.05) | H4: (Wt=8.22) | I4: (Wt=17.22) | J4: (Wt=12.34) | K4: (Wt=28.17) | L4: (Wt=12.84) | M4: (Wt=15.33)
A5: 40695 | B5: 100 | C5: 100 | D5: 100 | E5: 100
A6: 40787 | B6: 100 | C6: 100 | D6: 100 | E6: 100
A7: 40878 | B7: 100 | C7: 100 | D7: 100 | E7: 100
A8: 40969 | B8: 100 | C8: 100 | D8: 100 | E8: 100
A9: 41061 | B9: 102.2 | C9: 98.4 | D9: 102.6 | E9: 105.6 | G9: 100.6 | H9: 96.7 | I9: 104.2 | J9: 107.6 | K9: 102.1 | L9: 104 | M9: 100.6
A10: 41153 | B10: 100.1 | C10: 86 | D10: 102.5 | E10: 102.3 | G10: 95.9 | H10: 100.6 | I10: 103.4 | J10: 100.7 | K10: 102.6 | L10: 103.5 | M10: 101.9
A11: 41244 | B11: 103 | C11: 93.4 | D11: 104.7 | E11: 104.3 | G11: 101.8 | H11: 96 | I11: 104.3 | J11: 102.7 | K11: 106.1 | L11: 104.3 | M11: 107.5
A12: 41334 | B12: 107.9 | C12: 101.1 | D12: 109.6 | E12: 103.9 | G12: 103.7 | H12: 108 | I12: 108.5 | J12: 110.6 | K12: 111.4 | L12: 107.8 | M12: 114.4
A13: 41426 | B13: 103.3 | C13: 90.9 | D13: 105 | E13: 109 | G13: 99.6 | H13: 93.8 | I13: 105.2 | J13: 111.4 | K13: 105.7 | L13: 104.5 | M13: 106.6
A14: 41518 | B14: 104.9 | C14: 86 | D14: 107.8 | E14: 110.8 | G14: 100.2 | H14: 94.9 | I14: 111.1 | J14: 108.9 | K14: 108.2 | L14: 109.5 | M14: 107
A15: 41609 | B15: 106.2 | C15: 95.4 | D15: 107.8 | E15: 109.5 | G15: 103.1 | H15: 94.6 | I15: 108.9 | J15: 107.1 | K15: 111.3 | L15: 113.4 | M15: 109.4
A16: 41699 | B16: 112.5 | C16: 106 | D16: 113.8 | E16: 111.8 | G16: 108.5 | H16: 103.2 | I16: 114.5 | J16: 118.2 | K16: 116.4 | L16: 115.8 | M16: 116.9
A17: 41791 | B17: 109.1 | C17: 93 | D17: 110.1 | E17: 127.8 | G17: 105.5 | H17: 92 | I17: 116.9 | J17: 117.9 | K17: 109.8 | L17: 110.4 | M17: 109.3
A18: 41883 | B18: 109.5 | C18: 83.6 | D18: 112.1 | E18: 130.9 | G18: 102.8 | H18: 96.9 | I18: 117.8 | J18: 114.7 | K18: 114 | L18: 118 | M18: 110.7
A19: 41974 | B19: 110.2 | C19: 93.6 | D19: 111.7 | E19: 125.7 | G19: 108.5 | H19: 89.8 | I19: 114.3 | J19: 116.6 | K19: 113 | L19: 114.1 | M19: 112
A20: 42064 | B20: 115.2 | C20: 102.9 | D20: 116.7 | E20: 122.1 | G20: 110 | H20: 103.4 | I20: 117.6 | J20: 118.6 | K20: 121.9 | L20: 118.4 | M20: 124.9
... A54: 44866 | B54: 137.1 | C54: 122.7 | D54: 136.7 | E54: 166.7 | G54: 132.5 | H54: 99.1 | I54: 145.6 | J54: 159.6 | K54: 138.7 | L54: 112 | M54: 161.1

Sheet ASI-Tex-Apparel
A1: 2021-22 | B1: Manufacture of Textiles | C1: Manufacture of Wearing Apparel | D1: Manufacture of Leather and Related Products
A2: Operational factories | B2: 13767 | C2: 9007 | D2: 3648
A3: Workers per factory | B3: 103.4 | C3: 113.9 | D3: 88.8
A4: Net value added per worker | B4: 5.9 lakh | C4: 3.89 lakh | D4: 4.03 lakh
A5: Profits per person engaged | B5: 1.92 lakh | C5: 0.87 lakh | D5: 0.69 lakh
A6: Fixed capital per person engaged | B6: 9.20 lakh | C6: 2.93 lakh | D6: 3.67 lakh
A7: Output to input | B7: 1.2 | C7: 1.3 | D7: 1.3

Sheet IIP-Textiles-Apparel
A2: Month | B2: Cotton Yarn (incl. Hosiery) | C2: Readymade Garments, not knitted | D2: Leather garments | E2: Readymade Garments, knitted | F2: Underwears, socks and other hosiery products | G2: IIP | H2: Mining & quarrying | I2: Manufacturing | J2: Electricity
A3: 43525 | B3: 8.74 | C3: 19.27 | D3: -23.37 | E3: 12.57 | F3: -4.9 | G3: 2.71 | H3: 0.84 | I3: 3.14 | J3: 2.17
A4: 43556 | B4: 6.87 | C4: 17.29 | D4: -32.48 | E4: 68.44 | F4: -5.91 | G4: 3.18 | H4: 5.07 | I4: 2.52 | J4: 5.99
A5: 43586 | B5: -1.51 | C5: 1.99 | D5: -15.43 | E5: 17.5 | F5: -5.13 | G5: 4.48 | H5: 2.32 | I5: 4.38 | J5: 7.41
A6: 43617 | B6: -5.27 | C6: 0.83 | D6: 20.36 | E6: 18.6 | F6: 1.81 | G6: 1.25 | H6: 1.53 | I6: 0.31 | J6: 8.57
A7: 43647 | B7: -6.8 | C7: 5.13 | D7: 0.84 | E7: 28.12 | F7: -3.09 | G7: 4.85 | H7: 4.92 | I7: 4.78 | J7: 5.25
A8: 43678 | B8: -8.71 | C8: -6.83 | D8: 2.34 | E8: 27.94 | F8: 0.67 | G8: -1.41 | H8: 0 | I8: -1.68 | J8: -0.9
A9: 43709 | B9: -7.94 | C9: -7.38 | D9: -5.02 | E9: 13.5 | F9: 2.29 | G9: -4.58 | H9: -8.57 | I9: -4.26 | J9: -2.58
A10: 43739 | B10: -8.18 | C10: -5.41 | D10: -8.21 | E10: 0.81 | F10: -7.63 | G10: -6.63 | H10: -8.04 | I10: -5.68 | J10: -12.17
A11: 43770 | B11: -1.28 | C11: -5.67 | D11: -30.74 | E11: 19.3 | F11: -7.28 | G11: 2.14 | H11: 1.9 | I11: 3 | J11: -5.02
A12: 43800 | B12: -2.39 | C12: -1.41 | D12: 8.19 | E12: -3.69 | F12: -7.69 | G12: 0.45 | H12: 5.68 | I12: -0.29 | J12: -0.07
A13: 43831 | B13: -2.4 | C13: 5.31 | D13: 7.23 | E13: -24.01 | F13: -13.08 | G13: 2.23 | H13: 4.37 | I13: 1.77 | J13: 3.11
A14: 43862 | B14: -1.23 | C14: -2.53 | D14: 8.1 | E14: -4.69 | F14: -14.96 | G14: 5.17 | H14: 9.6 | I14: 3.79 | J14: 11.46
A15: 43891 | B15: -16.48 | C15: -29.74 | D15: -1.58 | E15: -55.73 | F15: -28.04 | G15: -18.67 | H15: -1.28 | I15: -22.82 | J15: -8.24
A16: 43922 | B16: -93.76 | C16: -93.31 | E16: -94.37 | G16: -57.31 | H16: -26.9 | I16: -66.64 | J16: -22.9
A17: 43952 | B17: -76.06 | C17: -58.63 | D17: -85.41 | E17: -64.57 | F17: -63.16 | G17: -33.38 | H17: -20.44 | I17: -37.85 | J17: -14.87
A18: 43983 | B18: -53.21 | C18: -38.33 | D18: -48.93 | E18: -36.06 | F18: -28.83 | G18: -16.55 | H18: -19.53 | I18: -16.98 | J18: -10.02
A19: 44013 | B19: -7.15 | C19: -36.52 | D19: -30.6 | E19: -29.95 | F19: -32.36 | G19: -10.55 | H19: -12.67 | I19: -11.37 | J19: -2.46
A20: 44044 | B20: -1.39 | C20: -25.3 | D20: -34.16 | E20: -32.35 | F20: -18.56 | G20: -7.13 | H20: -8.7 | I20: -7.55 | J20: -1.81
A21: 44075 | B21: 3.07 | C21: -17.69 | D21: -25.96 | E21: -15.02 | F21: -11.46 | G21: 0.98 | H21: 1.39 | I21: 0.4 | J21: 4.85
A22: 44105 | B22: 6.77 | C22: -18.46 | D22: -14 | E22: -8.47 | F22: 3.1 | G22: 4.52 | H22: -1.01 | I22: 4.51 | J22: 11.25
A23: 44136 | B23: 0.15 | C23: -31.07 | D23: -36.83 | E23: -24.34 | F23: 2.98 | G23: -1.63 | H23: -5.41 | I23: -1.61 | J23: 3.5
A24: 44166 | B24: -1.3 | C24: -35.35 | D24: -42.29 | E24: 4.35 | F24: -0.74 | G24: 2.16 | H24: -2.98 | I24: 2.66 | J24: 5.12
A25: 44197 | B25: 0.35 | C25: -39.6 | D25: -44.68 | E25: 26.28 | F25: -7.12 | G25: -0.58 | H25: -2.41 | I25: -0.94 | J25: 5.53
A26: 44228 | B26: -2.19 | C26: -34.01 | D26: -53.58 | E26: 21.88 | F26: 0.69 | G26: -3.2 | H26: -4.38 | I26: -3.35 | J26: 0.13
A27: 44256 | B27: 13.01 | C27: -2.85 | D27: -35.21 | E27: 87.78 | F27: 16.3 | G27: 24.23 | H27: 6.11 | I27: 28.41 | J27: 22.53
A28: 44287 | B28: 1362.88 | C28: 889.13 | E28: 349.45 | G28: 133.52 | H28: 36.55 | I28: 195.96 | J28: 38.54
A29: 44317 | B29: 284.78 | C29: 38.53 | D29: 209.09 | E29: 22.43 | F29: 74.13 | G29: 27.61 | H29: 23.63 | I29: 32.11 | J29: 7.5
A30: 44348 | B30: 110.35 | C30: 24.77 | D30: 6.29 | E30: -11.89 | F30: 7.49 | G30: 13.81 | H30: 23.1 | I30: 13.17 | J30: 8.26
A31: 44378 | B31: 11.84 | C31: 30.57 | D31: 4.62 | E31: -17.44 | F31: 29.19 | G31: 11.54 | H31: 19.54 | I31: 10.55 | J31: 11.06
A32: 44409 | B32: 9.83 | C32: 23.57 | D32: 10.41 | E32: 40.98 | F32: 18.85 | G32: 12.97 | H32: 23.33 | I32: 11.12 | J32: 15.98
A33: 44440 | B33: 4.21 | C33: 25.79 | D33: 2.92 | E33: 51.44 | F33: 11.61 | G33: 4.35 | H33: 8.56 | I33: 4.27 | J33: 0.9
A34: 44470 | B34: 2.06 | C34: 33.17 | D34: 9.56 | E34: 58.16 | F34: 6.72 | G34: 4.17 | H34: 11.47 | I34: 3.33 | J34: 3.14
A35: 44501 | B35: 0.12 | C35: 33.49 | D35: 77.84 | E35: 42.14 | F35: 7.77 | G35: 1.03 | H35: 4.88 | I35: 0.31 | J35: 2.14
A36: 44531 | B36: 2.78 | C36: 38.72 | D36: 32.43 | E36: 4.39 | F36: 19.04 | G36: 1.02 | H36: 2.64 | I36: 0.58 | J36: 2.85
A37: 44562 | B37: 0.06 | C37: 40.77 | D37: 53.12 | E37: 3.8 | F37: 34.67 | G37: 1.98 | H37: 2.97 | I37: 1.9 | J37: 0.85
A38: 44593 | B38: -1.79 | C38: 27.8 | D38: 95.79 | E38: -1.35 | F38: 33.9 | G38: 1.15 | H38: 4.58 | I38: 0.15 | J38: 4.48
A39: 44621 | B39: -2.22 | C39: 31.99 | D39: 122.05 | E39: 41.11 | F39: 55.04 | G39: 2.2 | H39: 3.88 | I39: 1.4 | J39: 6.11
A40: 44652 | B40: -5.64 | C40: 30.44 | D40: 87.32 | E40: 176.77 | F40: 63.03 | G40: 6.66 | H40: 8.36 | I40: 5.62 | J40: 11.78
... A62: 45323 | B62: 3.25 | C62: 2.87 | D62: 28.2 | E62: -12.22 | F62: 25.95 | G62: 5.67 | H62: 8.05 | I62: 5.01 | J62: 7.53

Sheet OBICUS-Order-Books
A1: OBICUS (RBI Survey) : Order Books
A2: % change : March 2009 to December 2023
A3: Quarter ended | B3: Y-o-Y % change | C3: Y-o-Y % change | D3: Y-o-Y % change | E3: Q-o-Q % change | F3: Q-o-Q % change | G3: Q-o-Q % change
A4: Quarter | B4: Average backlog order | C4: Average new order book | D4: Average pending order | E4: Average backlog order | F4: Average new order book | G4: Average pending order
A5: 39873 | E5: -3.7 | F5: 8.1 | G5: -0.9
A6: 39965 | E6: -3.7 | F6: 10 | G6: 1.1
A7: 40057 | E7: 1.2 | F7: 9.8 | G7: 2.4
A8: 40148 | E8: 2.8 | F8: 4.1 | G8: 2.1
A9: 40238 | B9: 2 | C9: 35.9 | D9: 3.8 | E9: 2.6 | F9: 3.9 | G9: 0.3
A10: 40330 | B10: 3.9 | C10: 13.4 | D10: 3.3 | E10: -2.5 | F10: -5.6 | G10: -1.7
A11: 40422 | B11: 3.4 | C11: 10.7 | D11: 4 | E11: 0.5 | F11: 8.4 | G11: 3.2
A12: 40513 | B12: 4 | C12: 17.7 | D12: 6.7 | E12: 3.4 | F12: 10.6 | G12: 4.8
A13: 40603 | B13: 6.5 | C13: 21.8 | D13: 7.9 | E13: 5 | F13: 7.6 | G13: 1.4
A14: 40695 | B14: 9.2 | C14: 14 | D14: 7.7 | E14: 0 | F14: -11.7 | G14: -1.9
A15: 40787 | B15: 7.8 | C15: 12.9 | D15: 2.5 | E15: -0.8 | F15: 7.4 | G15: -1.7
A16: 40878 | B16: 6.3 | C16: 9.6 | D16: 3.7 | E16: -1.1 | F16: 5 | G16: 2.4
A17: 40969 | B17: 3.1 | C17: 7.3 | D17: 0.7 | E17: 3.6 | F17: 6.7 | G17: -1.5
A18: 41061 | B18: 7.4 | C18: 22.1 | D18: 10.3 | E18: -0.3 | F18: -0.2 | G18: 4.4
A19: 41153 | B19: 12.3 | C19: 5.6 | D19: 11 | E19: 3.8 | F19: -4 | G19: -0.7
A20: 41244 | B20: 11.7 | C20: -4.9 | D20: 3.1 | E20: -0.5 | F20: 1.6 | G20: -1.2
... A64: 45261 | B64: 13.75 | C64: 10.08 | D64: 19.01 | E64: 4.68 | F64: -0.43 | G64: 4.1
A65: Note: Data for Y-o-Y %% change and Q-o-Q %% change is as published by RBI for the latest 5 quarters based on common set of companies in the latest 9 quarters.

Sheet OBICUS-Survey
A1: OBICUS (RBI Survey) : Average Sales and Inventories
A2: June 2008 to March 2022
A3: Quarter ended | B3: Number of respondent companies | C3: Average sales | D3: Average total inventories | E3: Average finished goods inventories | F3: Average work-in- progress inventories | G3: Average raw material inventories
B4: Numbers | C4: Rs. Million | D4: Rs. Million | E4: Rs. Million | F4: Rs. Million | G4: Rs. Million
A5: 39600 | B5: 1232 | C5: 2477 | D5: 1416 | E5: 489 | F5: 199 | G5: 728
A6: 39692 | B6: 1386 | C6: 2670 | D6: 1560 | E6: 560 | F6: 210 | G6: 790
A7: 39783 | B7: 933 | C7: 2350 | D7: 1250 | E7: 420 | F7: 170 | G7: 650
A8: 39873 | B8: 894 | C8: 2630 | D8: 1290 | E8: 460 | F8: 180 | G8: 650
A9: 39965 | B9: 906 | C9: 2450 | D9: 1360 | E9: 460 | F9: 210 | G9: 690
A10: 40057 | B10: 891 | C10: 2880 | D10: 1480 | E10: 540 | F10: 220 | G10: 720
A11: 40148 | B11: 891 | C11: 3080 | D11: 1520 | E11: 510 | F11: 240 | G11: 770
A12: 40238 | B12: 891 | C12: 3300 | D12: 1620 | E12: 530 | F12: 230 | G12: 860
A13: 40330 | B13: 891 | C13: 3230 | D13: 1680 | E13: 580 | F13: 250 | G13: 850
A14: 40422 | B14: 891 | C14: 3380 | D14: 1750 | E14: 600 | F14: 270 | G14: 880
A15: 40513 | B15: 891 | C15: 3630 | D15: 1860 | E15: 520 | F15: 270 | G15: 1080
A16: 40603 | B16: 891 | C16: 4070 | D16: 2020 | E16: 680 | F16: 310 | G16: 1020
... A67: 45261 | B67: 714 | C67: 10695.5 | D67: 5814.3 | E67: 2259.9 | F67: 1102.7 | G67: 1874.7

Sheet RCA - Textiles
A1: Product_Code | B1: Product_Label | C1: India RCA | D1: Bangladesh RCA | E1: SriLanka RCA | F1: Year
A2: 264 | B2: Jute, other textile bast fibre, n.e.s., not spun; tow | C2: 3.2 | D2: 391.8 | E2: 0.3 | F2: 2022
A3: 265 | B3: Vegetable textile fibres, not spun; waste of them | C3: 8.5 | D3: 0.3 | E3: 190.6
A4: 269 | B4: Worn clothing and other worn textile articles | C4: 1.1 | D4: 8.5 | E4: 1.3
A5: 651 | B5: Textile yarn | C5: 5.1 | D5: 4.9 | E5: 1.1
A6: 654 | B6: Other textile fabrics, woven | C6: 1.9 | D6: 5.6 | E6: 1
A7: 657 | B7: Special yarn, special textile fabrics & related | C7: 0.8 | D7: 0.4 | E7: 2.7
A8: 658 | B8: Made-up articles, of textile materials, n.e.s. | C8: 4.2 | D8: 9.9 | E8: 2.5
A9: 724 | B9: Textile & leather machinery, & parts thereof, n.e.s. | C9: 1.4 | D9: 0.1 | E9: 0.4
A10: 841 | B10: Men's clothing of textile fabrics, not knitted | C10: 1.5 | D10: 67.2 | E10: 14.2
A11: 842 | B11: Women's clothing, of textile fabrics | C11: 2.1 | D11: 28.1 | E11: 12.3
A12: 843 | B12: Men's or boy's clothing, of textile, knitted, croche. | C12: 2.7 | D12: 38.9 | E12: 25.6
A13: 844 | B13: Women's clothing, of textile, knitted or crocheted | C13: 1.2 | D13: 27.2 | E13: 32.8
A14: 845 | B14: Articles of apparel, of textile fabrics, n.e.s. | C14: 1.7 | D14: 41.6 | E14: 19.4
... A16: 848 | B16: Articles of apparel, clothing access., excluding textile | C16: 1.1 | D16: 4.6 | E16: 13.9

Sheet BOP-FinAcct
A1: Balance of Payments : Financial Account : Net Inflows
A2: USD Million : 2011-12 to 2021-22
A3: Year | B3: Total | C3: Direct investments | D3: Portfolio investments | E3: Financial derivatives (other than reserves) and employee stock options | F3: Other investments | G3: Reserve assets
A4: 2011-12 | B4: 80673 | C4: 22061 | D4: 16573 | F4: 29208 | G4: 12831
A5: 2012-13 | B5: 85448.7 | C5: 19819.4 | D5: 26704 | E5: -2314.5 | F5: 45173.3 | G5: -3826
A6: 2013-14 | B6: 32580.9 | C6: 21564.1 | D6: 4801.9 | E6: 2006.3 | F6: 19717.1 | G6: -15508.4
A7: 2014-15 | B7: 27724.7 | C7: 31251.4 | D7: 40934 | E7: -1563.2 | F7: 18508.8 | G7: -61406.4
A8: 2015-16 | B8: 23120.2 | C8: 36021 | D8: -4503.2 | E8: 631 | F8: 8876 | G8: -17904.7
A9: 2016-17 | B9: 14715.2 | C9: 35612.2 | D9: 7611.6 | E9: 9821.8 | F9: -16780 | G9: -21550.3
A10: 2017-18 | B10: 47788.4 | C10: 30286.1 | D10: 22114.9 | E10: -2870 | F10: 41831.7 | G10: -43574.4
A11: 2018-19 | B11: 57829.6 | C11: 30712 | D11: -2438 | E11: 1032.1 | F11: 25184.2 | G11: 3339.4
A12: 2019-20 | B12: 24667.6 | C12: 43013.2 | D12: 1403.4 | E12: 4098.9 | F12: 35650.2 | G12: -59498.1
A13: 2020-21 | B13: -22588.9 | C13: 43955.1 | D13: 36136.8 | E13: -4800.3 | F13: -10594 | G13: -87286.5
A14: 2021-22 | B14: 38430 | C14: 38587 | D14: -16777 | E14: -6412 | F14: 70533 | G14: -47501

Sheet Unemp-rate
A1: Unemployment Rate : By Region and Gender
A2: Per cent : August 2017 to July 2022
B3: All India | C3: All India | D3: All India | E3: Urban | F3: Urban | G3: Urban | H3: Rural | I3: Rural | J3: Rural
A4: Month | B4: Total | C4: Male | D4: Female | E4: Total | F4: Male | G4: Female | H4: Total | I4: Male | J4: Female
A5: 42948 | B5: 4.07 | C5: 3.33 | D5: 9.29 | E5: 5.08 | F5: 3.84 | G5: 13.76 | H5: 3.59 | I5: 3.09 | J5: 7.17
A6: 42979 | B6: 4.63 | C6: 3.59 | D6: 11.96 | E6: 5.7 | F6: 4.3 | G6: 15.76 | H6: 4.13 | I6: 3.25 | J6: 10.23
A7: 43009 | B7: 5 | C7: 3.8 | D7: 13.44 | E7: 5.98 | F7: 4.33 | G7: 16.73 | H7: 4.52 | I7: 3.55 | J7: 11.69
A8: 43040 | B8: 4.72 | C8: 3.78 | D8: 10.95 | E8: 5.41 | F8: 3.95 | G8: 15.55 | H8: 4.39 | I8: 3.7 | J8: 8.91
A9: 43070 | B9: 4.74 | C9: 4.03 | D9: 9.48 | E9: 5.36 | F9: 3.9 | G9: 15.13 | H9: 4.46 | I9: 4.09 | J9: 6.86
A10: 43101 | B10: 5.01 | C10: 3.86 | D10: 12.93 | E10: 6.24 | F10: 4.67 | G10: 17.02 | H10: 4.43 | I10: 3.48 | J10: 10.99
